Workbook

Sheet Sheet3
B1: Date | C1: TAMO | D1: Maruti | E1: Mahindra | F1: Bajaj | G1: Eicher
B2: 45207 | C2: 665.05 | D2: 10727.55 | E2: 1562.45 | F2: 5052.4 | G2: 3476.4
B3: 45214 | C3: 661.16 | D3: 10725.65 | E3: 1558.25 | F3: 5489.3 | G3: 3480.9
B4: 45221 | C4: 639.08 | D4: 10560.7 | E4: 1510.8 | F4: 5373.55 | G4: 3394.85
B5: 45228 | C5: 645.51 | D5: 10276.3 | E5: 1469 | F5: 5368.95 | G5: 3428
B6: 45235 | C6: 649.05 | D6: 10388.8 | E6: 1524.1 | F6: 5392.05 | G6: 3540.75
B7: 45242 | C7: 679.45 | D7: 10523.5 | E7: 1584.55 | F7: 5631.5 | G7: 3865.3
B8: 45249 | C8: 671.63 | D8: 10515.65 | E8: 1553.2 | F8: 5930.3 | G8: 3849.05
B9: 45256 | C9: 703.28 | D9: 10585.7 | E9: 1625.5 | F9: 6046.05 | G9: 3891.2
B10: 45263 | C10: 712.35 | D10: 10618.55 | E10: 1668.55 | F10: 6075.7 | G10: 4055
B11: 45270 | C11: 730.15 | D11: 10286.4 | E11: 1724.95 | F11: 6275.2 | G11: 4059.9
B12: 45277 | C12: 722.47 | D12: 10217.15 | E12: 1634.25 | F12: 6372.1 | G12: 4006.05
B13: 45284 | C13: 777.55 | D13: 10302.35 | E13: 1729.4 | F13: 6797.25 | G13: 4143.5
... B105: 45928 | C105: 716.1 | D105: 15806 | E105: 3462 | F105: 8679.5 | G105: 6941

Sheet Data Input
B2: Date | C2: Price | E2: Shareholder's name | F2: No. Share (Crs) | G2: Shareholding (%) | H2: Market value (Crs)
B3: 45936 | C3: 712.65 | E3: Tata Sons Private Limited | F3: 147.82635 | G3: 40.15 | H3: =F3*716 -> 105843.67
B4: 45933 | C4: 716.1 | E4: Life Insurance Corporation Of India | F4: 14.332928 | G4: 3.89 | H4: =F4*716 -> 10262.377
B5: 45931 | C5: 718.35 | E5: SBI Nifty 50 Etf | F5: 10.253439 | G5: 2.79 | H5: =F5*716 -> 7341.4621
B6: 45930 | C6: 680.2 | E6: Tata Industries Limited | F6: 7.220363 | G6: 1.96 | H6: =F6*716 -> 5169.7799
B7: 45929 | C7: 672.5 | E7: ICICI Prudential Value Discovery Fund | F7: 6.8270492 | G7: 1.85 | H7: =F7*716 -> 4888.1672
B8: 45926 | C8: 672.9 | E8: HDFC Trustee Company Ltd. A/C Hdfc Large Cap Fund | F8: 4.9420875 | G8: 1.34 | H8: =F8*716 -> 3538.5347
B9: 45925 | C9: 664.3 | E9: Rekha Jhunjhunwala | F9: 4.777026 | G9: 1.3 | H9: =F9*716 -> 3420.3506
B10: 45924 | C10: 682.95 | E10: Tata Investment Corporation Limited | F10: 1.1 | G10: 0.3 | H10: =F10*716 -> 787.6
B11: 45923 | C11: 701.35 | E11: Investor Education and Protection Fund (IEPF) | F11: 0.9768824 | G11: 0.27 | H11: =F11*716 -> 699.4478
B12: 45922 | C12: 696.25 | E12: Ewart Investments Limited | F12: 0.3383746 | G12: 0.09 | H12: =F12*716 -> 242.27621
B13: 45919 | C13: 707.45
B14: 45918 | C14: 711.2 | E14: Promoters | F14: 0.4257
B15: 45917 | C15: 719.15 | E15: FII | F15: 0.1717
B16: 45916 | C16: 713.25 | E16: DII | F16: 0.1693
B17: 45915 | C17: 712.9 | E17: Public & Government | F17: =23.01%+0.31% -> 0.2332
B18: 45912 | C18: 715.25
B19: 45911 | C19: 705.85
B20: 45910 | C20: 709.1
B21: 45909 | C21: 715.55
B22: 45908 | C22: 719.5
B23: 45905 | C23: 691.7
B24: 45904 | C24: 687.5
B25: 45903 | C25: 692.05
B26: 45902 | C26: 684.4
B27: 45901 | C27: 690.15
B28: 45898 | C28: 669
B29: 45897 | C29: 675.45
... B1242: 44111 | C1242: 141

Sheet Teaser
B2: ='Data Sheet'!B1&" - One Page Profile" -> TATA MOTORS LTD - One Page Profile
C4: Tata Motors Group is a leading global automobile manufacturer. Part of the illustrious multi-national conglomerate, the Tata group, it offers a wide and diverse portfolio of cars, sports utility vehicles, trucks, buses and defence vehicles to the world.It has operations in India, the UK, South Korea, South Africa, China, Brazil, Austria and Slovakia through a strong global network of subsidiaries, associate companies and Joint Ventures (JVs), including Jaguar Land Rover in the UK and Tata Daewoo in South Korea.
B6: INR(in Crs)
B7: Key Financial metrics | C7: ='Data Sheet'!G16 -> 44286 | D7: ='Data Sheet'!H16 -> 44651 | E7: ='Data Sheet'!I16 -> 45016 | F7: ='Data Sheet'!J16 -> 45382 | G7: ='Data Sheet'!K16 -> 45747 | I7: Share Price - 5Y
B9: Total Sales | C9: ='Data Sheet'!G17 -> 249794.75 | D9: ='Data Sheet'!H17 -> 278453.62 | E9: ='Data Sheet'!I17 -> 345966.97 | F9: ='Data Sheet'!J17 -> 434016 | G9: ='Data Sheet'!K17 -> 439695
B10: Sales Growth (YOY %) | C10: ='Data Sheet'!G36 -> -0.043181168 | D10: ='Data Sheet'!H36 -> 0.11472967 | E10: ='Data Sheet'!I36 -> 0.24245815 | F10: ='Data Sheet'!J36 -> 0.25450126 | G10: ='Data Sheet'!K36 -> 0.013084771
B11: Gross profit Margin (%) | C11: ='Data Sheet'!G38 -> 0.36624273 | D11: ='Data Sheet'!H38 -> 0.32013629 | E11: ='Data Sheet'!I38 -> 0.27648532 | F11: ='Data Sheet'!J38 -> 0.31909884 | G11: ='Data Sheet'!K38 -> 0.34643332
B12: EBITDA Margins (%) | C12: ='Data Sheet'!G35 -> 0.083005548 | D12: ='Data Sheet'!H35 -> 0.096739163 | E12: ='Data Sheet'!I35 -> 0.11042728 | F12: ='Data Sheet'!J35 -> 0.14333112 | G12: ='Data Sheet'!K35 -> 0.15163011
B13: EBIT Margins (%) | C13: ='Data Sheet'!G39 -> -0.011258683 | D13: ='Data Sheet'!H39 -> 0.0075476842 | E13: ='Data Sheet'!I39 -> 0.038569665 | F13: ='Data Sheet'!J39 -> 0.080570762 | G13: ='Data Sheet'!K39 -> 0.098738899
B14: Net Profit Margins (%) | C14: ='Data Sheet'!G40 -> -0.053849771 | D14: ='Data Sheet'!H40 -> -0.04108932 | E14: ='Data Sheet'!I40 -> 0.0069783829 | F14: ='Data Sheet'!J40 -> 0.072345259 | G14: ='Data Sheet'!K40 -> 0.063293874
B15: Earnings Per Share (In Rs.) | C15: ='Historical FS'!H44 -> -6.1453869 | D15: ='Historical FS'!I44 -> -41.137096 | E15: ='Historical FS'!J44 -> -11.967657 | F15: ='Historical FS'!K44 -> 81.338632 | G15: ='Historical FS'!L44 -> 49.267383
B16: EPS Growth (YOY %) | C16: ='Historical FS'!H45 -> -0.83981519 | D16: ='Historical FS'!I45 -> 5.6939799 | E16: ='Historical FS'!J45 -> -0.7090787 | F16: ='Historical FS'!K45 -> -7.7965375 | G16: ='Historical FS'!L45 -> -0.39429295
B17: Dividend Per Share | C17: ='Historical FS'!H47 -> 0 | D17: ='Historical FS'!I47 -> 0 | E17: ='Historical FS'!J47 -> 2.3068028 | F17: ='Historical FS'!K47 -> 6.9280101 | G17: ='Historical FS'!L47 -> 6.6431988
B18: DPS Growth (YOY %) | C18: N/A | D18: N/A | E18: N/A | F18: =F17/E17-1 -> 2.0032954 | G18: =G17/F17-1 -> -0.041110112
B20: Key Financial Ratios | C20: =C7 -> 44286 | D20: =D7 -> 44651 | E20: =E7 -> 45016 | F20: =F7 -> 45382 | G20: =G7 -> 45747 | I20: Share Price - 5Y
B22: Price to Earnings | C22: ='[1]Profit & Loss'!G14 -> 0 | D22: ='[1]Profit & Loss'!H14 -> 0 | E22: ='[1]Profit & Loss'!I14 -> 0 | F22: ='[1]Profit & Loss'!J14 -> 0 | G22: ='[1]Profit & Loss'!K14 -> 0
B23: EV/EBITDA | C23: ='Data Sheet'!G103 -> 5.6565774 | D23: ='Data Sheet'!H103 -> 7.6468673 | E23: ='Data Sheet'!I103 -> 6.3116962 | F23: ='Data Sheet'!J103 -> 3.2345889 | G23: ='Data Sheet'!K103 -> 5.4098924
B24: EV/Sales | C24: ='Data Sheet'!G104 -> 0.4695273 | D24: ='Data Sheet'!H104 -> 0.73975154 | E24: ='Data Sheet'!I104 -> 0.69698342 | F24: ='Data Sheet'!J104 -> 0.46361725 | G24: ='Data Sheet'!K104 -> 0.82030256
B25: Price to Book Value | C25: ='Data Sheet'!G107 -> 0.3972606 | D25: ='Data Sheet'!H107 -> 2.2487403 | E25: ='Data Sheet'!I107 -> 3.1780599 | F25: ='Data Sheet'!J107 -> 1.6458266 | G25: ='Data Sheet'!K107 -> 2.8411019
B26: Return on Equity (%) | C26: -0.24347853 | D26: -0.25675834 | E26: 0.053269961 | F26: 0.36975671 | G26: 0.23961634
B27: Return on Capital Employed (%) | C27: -0.012340819 | D27: 0.011887353 | E27: 0.073529898 | F27: 0.19039483 | G27: 0.23026014
B29: Top 10 Share Holders | C29: ='Data Input'!F2 -> No. Share (Crs) | E29: Holdings (%) | F29: ='Data Input'!H2 -> Market value (Crs) | I29: Shareholding Pattern
B31: ='Data Input'!E3 -> Tata Sons Private Limited | C31: ='Data Input'!F3 -> 147.82635 | E31: =('Data Input'!G3)/100 -> 0.4015 | F31: ='Data Input'!H3 -> 105843.67
B32: ='Data Input'!E4 -> Life Insurance Corporation Of India | C32: ='Data Input'!F4 -> 14.332928 | E32: =('Data Input'!G4)/100 -> 0.0389 | F32: ='Data Input'!H4 -> 10262.377
B33: ='Data Input'!E5 -> SBI Nifty 50 Etf | C33: ='Data Input'!F5 -> 10.253439 | E33: =('Data Input'!G5)/100 -> 0.0279 | F33: ='Data Input'!H5 -> 7341.4621
B34: ='Data Input'!E6 -> Tata Industries Limited | C34: ='Data Input'!F6 -> 7.220363 | E34: =('Data Input'!G6)/100 -> 0.0196 | F34: ='Data Input'!H6 -> 5169.7799
B35: ='Data Input'!E7 -> ICICI Prudential Value Discovery Fund | C35: ='Data Input'!F7 -> 6.8270492 | E35: =('Data Input'!G7)/100 -> 0.0185 | F35: ='Data Input'!H7 -> 4888.1672
B36: ='Data Input'!E8 -> HDFC Trustee Company Ltd. A/C Hdfc Large Cap Fund | C36: ='Data Input'!F8 -> 4.9420875 | E36: =('Data Input'!G8)/100 -> 0.0134 | F36: ='Data Input'!H8 -> 3538.5347
B37: ='Data Input'!E9 -> Rekha Jhunjhunwala | C37: ='Data Input'!F9 -> 4.777026 | E37: =('Data Input'!G9)/100 -> 0.013 | F37: ='Data Input'!H9 -> 3420.3506
B38: ='Data Input'!E10 -> Tata Investment Corporation Limited | C38: ='Data Input'!F10 -> 1.1 | E38: =('Data Input'!G10)/100 -> 0.003 | F38: ='Data Input'!H10 -> 787.6
B39: ='Data Input'!E11 -> Investor Education and Protection Fund (IEPF) | C39: ='Data Input'!F11 -> 0.9768824 | E39: =('Data Input'!G11)/100 -> 0.0027 | F39: ='Data Input'!H11 -> 699.4478
B40: ='Data Input'!E12 -> Ewart Investments Limited | C40: ='Data Input'!F12 -> 0.3383746 | E40: =('Data Input'!G12)/100 -> 0.0009 | F40: ='Data Input'!H12 -> 242.27621
B42: Managerial Remuneration | D42: Designation | E42: Remuneration | F42: X of Median Salary | I42: Capital Structure
B44: Mr N Chandrasekaran | C44: Chairman & Non Exec. Director | E44: =F44 -> N/A | F44: =C18 -> N/A | I44: Share Price as on 05.10.2025 | K44: ='Data Sheet'!B8 -> 716.1
B45: Mr Girish Wagh | C45: Exec. Director | E45: 165.57 | F45: 69.31:1 | I45: Number of Shares O/s | K45: ='Data Sheet'!B6 -> 368.22747
B46: Mr Om Prakash Bhatt | C46: Independent Director | E46: 115 | F46: 10.44:1 | I46: Market Capitalization | K46: =K44*K45 -> 263687.69
B47: Ms Hanne Sorenson | C47: Independent Director | E47: 115 | F47: 10.32:1 | I47: Less: Cash & Equivalents | K47: =-'Data Sheet'!K71 -> -40834
B48: Ms Vedika Bhandarkar | C48: Independent Director | E48: 115 | F48: 10.21:1 | I48: Add: Total Debt | K48: ='Data Sheet'!K61 -> 71540
B49: Mr Kosaraju Veerayya Chowdary | C49: Independent Director | E49: 115 | F49: 10.18:1 | I49: Add: Minority Interest | K49: 6610
B50: Mr Al Noor Ramji | C50: Independent Director | E50: 115 | F50: 10.15:1 | I50: Enterprise Value | K50: =SUM(K46:K49) -> 301003.69
B52: 01. As a Policy, Mr N Chandrasekaran, Chairman, has abstained from receiving commission from the Company and hence not stated.
B53: 02. We have not considered the total remuneration for Mr. Wagh instead only the basic salary paid in FY25 has been condsidered
B55: Key updates - Demerger Summary

Sheet WACC-->

Sheet Historical FS
B2: TATA MOTORS LTD
B3: ( TATA MOTORS LTD | BSE Code : 500570 )
B4: INR 716.00 (as on 05.10.2025)
B5: 52 Week ( High - INR 948.45 & Low - 535.75)
B8: ="Historical Financial Statements - "&'[3]Data Sheet'!B1 -> Historical Financial Statements - TATA MOTORS LTD
B9: Years | C9: ='[3]Data Sheet'!B16 -> 42460 | D9: ='[3]Data Sheet'!C16 -> 42825 | E9: ='[3]Data Sheet'!D16 -> 43190 | F9: ='[3]Data Sheet'!E16 -> 43555 | G9: ='[3]Data Sheet'!F16 -> 43921 | H9: ='[3]Data Sheet'!G16 -> 44286 | I9: ='[3]Data Sheet'!H16 -> 44651 | J9: ='[3]Data Sheet'!I16 -> 45016 | ... L9: ='[3]Data Sheet'!K16 -> 45747 | M9: LTM
A11: x | B11: Income Statement
B12: Sales | C12: =IFERROR('[3]Data Sheet'!B17,0) -> 273045.6 | D12: =IFERROR('[3]Data Sheet'!C17,0) -> 269692.51 | E12: =IFERROR('[3]Data Sheet'!D17,0) -> 291550.48 | F12: =IFERROR('[3]Data Sheet'!E17,0) -> 301938.4 | G12: =IFERROR('[3]Data Sheet'!F17,0) -> 261067.97 | H12: =IFERROR('[3]Data Sheet'!G17,0) -> 249794.75 | I12: =IFERROR('[3]Data Sheet'!H17,0) -> 278453.62 | J12: =IFERROR('[3]Data Sheet'!I17,0) -> 345966.97 | ... L12: =IFERROR('[3]Data Sheet'!K17,0) -> 439695 | M12: =IFERROR(SUM('[3]Data Sheet'!H42:K42),0) -> 437968
B13: Sales Growth | C13: - | D13: =D12/C12-1 -> -0.01228033 | E13: =E12/D12-1 -> 0.081047746 | F13: =F12/E12-1 -> 0.035629919 | G13: =G12/F12-1 -> -0.13536016 | H13: =H12/G12-1 -> -0.043181168 | I13: =I12/H12-1 -> 0.11472967 | J13: =J12/I12-1 -> 0.24245815 | K13: =K12/J12-1 -> 0.25450126 | ... M13: =M12/L12-1 -> -0.0039277226
B15: COGS | C15: =IFERROR(SUM('[3]Data Sheet'!B18,'[3]Data Sheet'!B20,'[3]Data Sheet'!B21,'[3]Data Sheet'!B22)-1*'[3]Data Sheet'!B19,0) -> 205509.07 | D15: =IFERROR(SUM('[3]Data Sheet'!C18,'[3]Data Sheet'!C20,'[3]Data Sheet'!C21,'[3]Data Sheet'!C22)-1*'[3]Data Sheet'!C19,0) -> 205454.24 | E15: =IFERROR(SUM('[3]Data Sheet'!D18,'[3]Data Sheet'!D20,'[3]Data Sheet'!D21,'[3]Data Sheet'!D22)-1*'[3]Data Sheet'!D19,0) -> 228429.83 | F15: =IFERROR(SUM('[3]Data Sheet'!E18,'[3]Data Sheet'!E20,'[3]Data Sheet'!E21,'[3]Data Sheet'!E22)-1*'[3]Data Sheet'!E19,0) -> 242845.53 | G15: =IFERROR(SUM('[3]Data Sheet'!F18,'[3]Data Sheet'!F20,'[3]Data Sheet'!F21,'[3]Data Sheet'!F22)-1*'[3]Data Sheet'!F19,0) -> 210376.07 | H15: =IFERROR(SUM('[3]Data Sheet'!G18,'[3]Data Sheet'!G20,'[3]Data Sheet'!G21,'[3]Data Sheet'!G22)-1*'[3]Data Sheet'!G19,0) -> 195326.04 | I15: =IFERROR(SUM('[3]Data Sheet'!H18,'[3]Data Sheet'!H20,'[3]Data Sheet'!H21,'[3]Data Sheet'!H22)-1*'[3]Data Sheet'!H19,0) -> 223300.01 | J15: =IFERROR(SUM('[3]Data Sheet'!I18,'[3]Data Sheet'!I20,'[3]Data Sheet'!I21,'[3]Data Sheet'!I22)-1*'[3]Data Sheet'!I19,0) -> 274403.64 | ... L15: =IFERROR(SUM('[3]Data Sheet'!K18,'[3]Data Sheet'!K20,'[3]Data Sheet'!K21,'[3]Data Sheet'!K22)-1*'[3]Data Sheet'!K19,0) -> 340809 | M15: =IFERROR(SUM('[3]Data Sheet'!H43:K43),0) -> 386344
B16: COGS %Sales | C16: =C15/C12 -> 0.75265476 | D16: =D15/D12 -> 0.76180922 | E16: =E15/E12 -> 0.7835001 | F16: =F15/F12 -> 0.80428833 | G16: =G15/G12 -> 0.80582873 | H16: =H15/H12 -> 0.78194614 | I16: =I15/I12 -> 0.80192892 | J16: =J15/J12 -> 0.79314982 | ... M16: =M15/M12 -> 0.88212837
B18: Gross Proft | C18: =C12-C15 -> 67536.53 | D18: =D12-D15 -> 64238.27 | E18: =E12-E15 -> 63120.65 | F18: =F12-F15 -> 59092.87 | G18: =G12-G15 -> 50691.9 | H18: =H12-H15 -> 54468.71 | I18: =I12-I15 -> 55153.61 | J18: =J12-J15 -> 71563.33 | ... M18: =M12-M15 -> 51624
B19: Gross Margins | C19: =C18/C12 -> 0.24734524 | D19: =D18/D12 -> 0.23819078 | E19: =E18/E12 -> 0.2164999 | F19: =F18/F12 -> 0.19571167 | G19: =G18/G12 -> 0.19417127 | H19: =H18/H12 -> 0.21805386 | I19: =I18/I12 -> 0.19807108 | J19: =J18/J12 -> 0.20685018 | ... M19: =M18/M12 -> 0.11787163
B21: Selling & Genral Expenses | C21: =IFERROR(SUM('[3]Data Sheet'!B23:B24),0) -> 29141.28 | D21: =IFERROR(SUM('[3]Data Sheet'!C23:C24),0) -> 34649.58 | E21: =IFERROR(SUM('[3]Data Sheet'!D23:D24),0) -> 31662.97 | F21: =IFERROR(SUM('[3]Data Sheet'!E23:E24),0) -> 34428.54 | G21: =IFERROR(SUM('[3]Data Sheet'!F23:F24),0) -> 32704.83 | H21: =IFERROR(SUM('[3]Data Sheet'!G23:G24),0) -> 22181.28 | I21: =IFERROR(SUM('[3]Data Sheet'!H23:H24),0) -> 30433.52 | J21: =IFERROR(SUM('[3]Data Sheet'!I23:I24),0) -> 39747.53 | ... L21: =IFERROR(SUM('[3]Data Sheet'!K23:K24),0) -> 43670 | M21: 0
B22: S&G Expenses %Sales | C22: =C21/C12 -> 0.10672679 | D22: =D21/D12 -> 0.1284781 | E22: =E21/E12 -> 0.10860202 | F22: =F21/F12 -> 0.11402505 | G22: =G21/G12 -> 0.12527324 | H22: =H21/H12 -> 0.088798023 | I22: =I21/I12 -> 0.10929475 | J22: =J21/J12 -> 0.11488822 | ... M22: =M21/M12 -> 0
B24: EBITDA | C24: =C18-C21 -> 38395.25 | D24: =D18-D21 -> 29588.69 | E24: =E18-E21 -> 31457.68 | F24: =F18-F21 -> 24664.33 | G24: =G18-G21 -> 17987.07 | H24: =H18-H21 -> 32287.43 | I24: =I18-I21 -> 24720.09 | J24: =J18-J21 -> 31815.8 | ... L24: =L18-L21 -> 55216 | M24: =IFERROR(SUM('[3]Data Sheet'!H51:K51),0) -> 57272
B25: EBITDA %Sales | C25: =C24/C12 -> 0.14061845 | D25: =D24/D12 -> 0.10971269 | E25: =E24/E12 -> 0.10789788 | F25: =F24/F12 -> 0.081686629 | G25: =G24/G12 -> 0.068898034 | H25: =H24/H12 -> 0.12925584 | I25: =I24/I12 -> 0.088776328 | J25: =J24/J12 -> 0.091961958 | ... M25: =M24/M12 -> 0.13076754
B27: Interest | C27: =IFERROR('[3]Data Sheet'!B27,0) -> 4889.08 | D27: =IFERROR('[3]Data Sheet'!C27,0) -> 4238.01 | E27: =IFERROR('[3]Data Sheet'!D27,0) -> 4681.79 | F27: =IFERROR('[3]Data Sheet'!E27,0) -> 5758.6 | G27: =IFERROR('[3]Data Sheet'!F27,0) -> 7243.33 | H27: =IFERROR('[3]Data Sheet'!G27,0) -> 8097.17 | I27: =IFERROR('[3]Data Sheet'!H27,0) -> 9311.86 | J27: =IFERROR('[3]Data Sheet'!I27,0) -> 10225.48 | ... L27: =IFERROR('[3]Data Sheet'!K27,0) -> 5083 | M27: =IFERROR(SUM('[3]Data Sheet'!H27:K27),0) -> 32214.34
B28: Interest %Sales | C28: =C27/C12 -> 0.017905727 | D28: =D27/D12 -> 0.01571423 | E28: =E27/E12 -> 0.016058248 | F28: =F27/F12 -> 0.019072102 | G28: =G27/G12 -> 0.027744997 | H28: =H27/H12 -> 0.032415293 | I28: =I27/I12 -> 0.033441332 | J28: =J27/J12 -> 0.029556232 | ... M28: =M27/M12 -> 0.073554095
B30: Depriciation | C30: =IFERROR('[3]Data Sheet'!B26,0) -> 16710.78 | D30: =IFERROR('[3]Data Sheet'!C26,0) -> 17904.99 | E30: =IFERROR('[3]Data Sheet'!D26,0) -> 21553.59 | F30: =IFERROR('[3]Data Sheet'!E26,0) -> 23590.63 | G30: =IFERROR('[3]Data Sheet'!F26,0) -> 21425.43 | H30: =IFERROR('[3]Data Sheet'!G26,0) -> 23546.71 | I30: =IFERROR('[3]Data Sheet'!H26,0) -> 24835.69 | J30: =IFERROR('[3]Data Sheet'!I26,0) -> 24860.36 | ... L30: =IFERROR('[3]Data Sheet'!K26,0) -> 23256 | M30: =IFERROR(SUM('[3]Data Sheet'!H45:K45),0) -> 22019
B31: Depriciation %Sales | C31: =C30/C12 -> 0.061201426 | D31: =D30/D12 -> 0.066390387 | E31: =E30/E12 -> 0.073927472 | F31: =F30/F12 -> 0.078130605 | G31: =G30/G12 -> 0.082068398 | H31: =H30/H12 -> 0.094264231 | I31: =I30/I12 -> 0.089191478 | J31: =J30/J12 -> 0.071857611 | ... M31: =M30/M12 -> 0.050275363
B33: Earnings Before Tax | C33: =IFERROR(C24-SUM(C27,C30),0) -> 16795.39 | D33: =IFERROR(D24-SUM(D27,D30),0) -> 7445.69 | E33: =IFERROR(E24-SUM(E27,E30),0) -> 5222.3 | F33: =IFERROR(F24-SUM(F27,F30),0) -> -4684.9 | G33: =IFERROR(G24-SUM(G27,G30),0) -> -10681.69 | H33: =IFERROR(H24-SUM(H27,H30),0) -> 643.55 | I33: =IFERROR(I24-SUM(I27,I30),0) -> -9427.46 | J33: =IFERROR(J24-SUM(J27,J30),0) -> -3270.04 | ... L33: =IFERROR(L24-SUM(L27,L30),0) -> 26877 | M33: =IFERROR(SUM('[3]Data Sheet'!H47:K47),0) -> 30437
B34: EBT %Sales | C34: =C33/C12 -> 0.061511301 | D34: =D33/D12 -> 0.027608071 | E34: =E33/E12 -> 0.017912164 | F34: =F33/F12 -> -0.015516079 | G34: =G33/G12 -> -0.04091536 | H34: =H33/H12 -> 0.0025763152 | I34: =I33/I12 -> -0.033856482 | J34: =J33/J12 -> -0.009451885 | ... M34: =M33/M12 -> 0.069495945
B36: Tax | C36: =IFERROR('[3]Data Sheet'!B29,0) -> 3025.05 | D36: =IFERROR('[3]Data Sheet'!C29,0) -> 3251.23 | E36: =IFERROR('[3]Data Sheet'!D29,0) -> 4341.93 | F36: =IFERROR('[3]Data Sheet'!E29,0) -> -2437.45 | G36: =IFERROR('[3]Data Sheet'!F29,0) -> 395.25 | H36: =IFERROR('[3]Data Sheet'!G29,0) -> 2541.86 | I36: =IFERROR('[3]Data Sheet'!H29,0) -> 4231.29 | J36: =IFERROR('[3]Data Sheet'!I29,0) -> 704.06 | ... L36: =IFERROR('[3]Data Sheet'!K29,0) -> 10502 | M36: =IFERROR(SUM('[3]Data Sheet'!H48:K48),0) -> 8943
B37: Effective Tax Rate | C37: =C36/C33 -> 0.18011192 | D37: =D36/D33 -> 0.43665933 | E37: =E36/E33 -> 0.83142102 | F37: =F36/F33 -> 0.52027791 | G37: =G36/G33 -> -0.037002572 | H37: =H36/H33 -> 3.9497475 | I37: =I36/I33 -> -0.44882609 | J37: =J36/J33 -> -0.21530623 | ... M37: =M36/M33 -> 0.29382002
B39: Net Profit | C39: =IFERROR(C33-C36,0) -> 13770.34 | D39: =IFERROR(D33-D36,0) -> 4194.46 | E39: =IFERROR(E33-E36,0) -> 880.37 | F39: =IFERROR(F33-F36,0) -> -2247.45 | G39: =IFERROR(G33-G36,0) -> -11076.94 | H39: =IFERROR(H33-H36,0) -> -1898.31 | I39: =IFERROR(I33-I36,0) -> -13658.75 | J39: =IFERROR(J33-J36,0) -> -3974.1 | ... M39: =IFERROR(M33-M36,0) -> 21494
B40: Net Margins | C40: =C39/C12 -> 0.050432382 | D40: =D39/D12 -> 0.015552749 | E40: =E39/E12 -> 0.0030196143 | F40: =F39/F12 -> -0.0074434057 | G40: =G39/G12 -> -0.042429334 | H40: =H39/H12 -> -0.0075994792 | I40: =I39/I12 -> -0.049052155 | J40: =J39/J12 -> -0.011486935 | ... M40: =M39/M12 -> 0.049076645
B42: No. of Equity Shares | C42: =IFERROR('[3]Data Sheet'!B94,0) -> 288.74 | D42: =IFERROR('[3]Data Sheet'!C94,0) -> 288.72 | E42: =IFERROR('[3]Data Sheet'!D94,0) -> 288.73 | F42: =IFERROR('[3]Data Sheet'!E94,0) -> 288.73 | G42: =IFERROR('[3]Data Sheet'!F94,0) -> 288.73 | H42: =IFERROR('[3]Data Sheet'!G94,0) -> 308.9 | I42: =IFERROR('[3]Data Sheet'!H94,0) -> 332.03 | J42: =IFERROR('[3]Data Sheet'!I94,0) -> 332.07 | ... L42: =IFERROR('[3]Data Sheet'!K94,0) -> 332.37 | M42: =L42 -> 332.37
B44: Earning per Share | C44: =IFERROR(C39/C42,0) -> 47.691141 | D44: =IFERROR(D39/D42,0) -> 14.527778 | E44: =IFERROR(E39/E42,0) -> 3.0491116 | F44: =IFERROR(F39/F42,0) -> -7.7839158 | G44: =IFERROR(G39/G42,0) -> -38.364354 | H44: =IFERROR(H39/H42,0) -> -6.1453869 | I44: =IFERROR(I39/I42,0) -> -41.137096 | J44: =IFERROR(J39/J42,0) -> -11.967657 | ... M44: =IFERROR(M39/M42,0) -> 64.668893
B45: EPS Growth % | D45: =IFERROR(D44/C44-1,0) -> -0.69537785 | E45: =E44/D44-1 -> -0.79011851 | F45: =F44/E44-1 -> -3.5528471 | G45: =G44/F44-1 -> 3.9286703 | H45: =H44/G44-1 -> -0.83981519 | I45: =I44/H44-1 -> 5.6939799 | J45: =J44/I44-1 -> -0.7090787 | K45: =K44/J44-1 -> -7.7965375 | L45: =L44/K44-1 -> -0.39429295 | M45: =M44/L44-1 -> 0.31261069
B47: Dividend per Share | C47: =IFERROR('[3]Data Sheet'!B31/C42,0) -> 0.23522893 | D47: =IFERROR('[3]Data Sheet'!C31/D42,0) -> 0 | E47: =IFERROR('[3]Data Sheet'!D31/E42,0) -> 0 | F47: =IFERROR('[3]Data Sheet'!E31/F42,0) -> 0 | G47: =IFERROR('[3]Data Sheet'!F31/G42,0) -> 0 | H47: =IFERROR('[3]Data Sheet'!G31/H42,0) -> 0 | I47: =IFERROR('[3]Data Sheet'!H31/I42,0) -> 0 | J47: =IFERROR('[3]Data Sheet'!I31/J42,0) -> 2.3068028 | ... M47: =IFERROR('[3]Data Sheet'!L31/M42,0) -> 0
B48: Dividend Payout ratio | C48: =IFERROR(C47/C44,0) -> 0.0049323401 | D48: =IFERROR(D47/D44,0) -> 0 | E48: =IFERROR(E47/E44,0) -> 0 | F48: =IFERROR(F47/F44,0) -> 0 | G48: =IFERROR(G47/G44,0) -> 0 | H48: =IFERROR(H47/H44,0) -> 0 | I48: =IFERROR(I47/I44,0) -> 0 | J48: =IFERROR(J47/J44,0) -> -0.19275308 | ... M48: =IFERROR(M47/M44,0) -> 0
B50: Retained Earnings | C50: =IFERROR(IF(C44>C47,1-C48,0),0) -> 0.99506766 | D50: =IFERROR(IF(D44>D47,1-D48,0),0) -> 1 | E50: =IFERROR(IF(E44>E47,1-E48,0),0) -> 1 | F50: =IFERROR(IF(F44>F47,1-F48,0),0) -> 0 | G50: =IFERROR(IF(G44>G47,1-G48,0),0) -> 0 | H50: =IFERROR(IF(H44>H47,1-H48,0),0) -> 0 | I50: =IFERROR(IF(I44>I47,1-I48,0),0) -> 0 | J50: =IFERROR(IF(J44>J47,1-J48,0),0) -> 0 | ... M50: =IFERROR(IF(M44>M47,1-M48,0),0) -> 1
B52: TATA MOTORS LTD
B53: ( TATA MOTORS LTD | BSE Code : 500570 )
B54: INR 716.00 (as on 05.10.2025)
B55: 52 Week ( High - INR 948.45 & Low - 535.75)
B58: Balance Sheet
B59: Equity Share Capital | C59: =IFERROR('[3]Data Sheet'!B57,0) -> 679.18 | D59: =IFERROR('[3]Data Sheet'!C57,0) -> 679.22 | E59: =IFERROR('[3]Data Sheet'!D57,0) -> 679.22 | F59: =IFERROR('[3]Data Sheet'!E57,0) -> 679.22 | G59: =IFERROR('[3]Data Sheet'!F57,0) -> 719.54 | H59: =IFERROR('[3]Data Sheet'!G57,0) -> 765.81 | I59: =IFERROR('[3]Data Sheet'!H57,0) -> 765.88 | J59: =IFERROR('[3]Data Sheet'!I57,0) -> 766.02 | ... L59: =IFERROR('[3]Data Sheet'!K57,0) -> 736
B60: Reserves | C60: =IFERROR('[3]Data Sheet'!B58,0) -> 78273.23 | D60: =IFERROR('[3]Data Sheet'!C58,0) -> 57382.67 | E60: =IFERROR('[3]Data Sheet'!D58,0) -> 94748.69 | F60: =IFERROR('[3]Data Sheet'!E58,0) -> 59500.34 | G60: =IFERROR('[3]Data Sheet'!F58,0) -> 62358.99 | H60: =IFERROR('[3]Data Sheet'!G58,0) -> 54480.91 | I60: =IFERROR('[3]Data Sheet'!H58,0) -> 43795.36 | J60: =IFERROR('[3]Data Sheet'!I58,0) -> 44555.77 | ... L60: =IFERROR('[3]Data Sheet'!K58,0) -> 115408
B61: Borrowings | C61: =IFERROR('[3]Data Sheet'!B59,0) -> 69359.96 | D61: =IFERROR('[3]Data Sheet'!C59,0) -> 78603.98 | E61: =IFERROR('[3]Data Sheet'!D59,0) -> 88950.47 | F61: =IFERROR('[3]Data Sheet'!E59,0) -> 106175.34 | G61: =IFERROR('[3]Data Sheet'!F59,0) -> 124787.64 | H61: =IFERROR('[3]Data Sheet'!G59,0) -> 142130.57 | I61: =IFERROR('[3]Data Sheet'!H59,0) -> 146449.03 | J61: =IFERROR('[3]Data Sheet'!I59,0) -> 134113.44 | ... L61: =IFERROR('[3]Data Sheet'!K59,0) -> 71540
A62: x | B62: Other Liabilities | C62: =IFERROR('[3]Data Sheet'!B60,0) -> 114871.75 | D62: =IFERROR('[3]Data Sheet'!C60,0) -> 135914.49 | E62: =IFERROR('[3]Data Sheet'!D60,0) -> 142813.43 | F62: =IFERROR('[3]Data Sheet'!E60,0) -> 139348.59 | G62: =IFERROR('[3]Data Sheet'!F60,0) -> 132313.22 | H62: =IFERROR('[3]Data Sheet'!G60,0) -> 144192.62 | I62: =IFERROR('[3]Data Sheet'!H60,0) -> 138051.22 | J62: =IFERROR('[3]Data Sheet'!I60,0) -> 155239.2 | ... L62: =IFERROR('[3]Data Sheet'!K60,0) -> 189289
B63: Total Liabilities | C63: =IFERROR('[3]Data Sheet'!B61,0) -> 263184.12 | D63: =IFERROR('[3]Data Sheet'!C61,0) -> 272580.36 | E63: =IFERROR('[3]Data Sheet'!D61,0) -> 327191.81 | F63: =IFERROR('[3]Data Sheet'!E61,0) -> 305703.49 | G63: =IFERROR('[3]Data Sheet'!F61,0) -> 320179.39 | H63: =IFERROR('[3]Data Sheet'!G61,0) -> 341569.91 | I63: =IFERROR('[3]Data Sheet'!H61,0) -> 329061.49 | J63: =IFERROR('[3]Data Sheet'!I61,0) -> 334674.43 | ... L63: =IFERROR('[3]Data Sheet'!K61,0) -> 376973
B65: Fixed Assets Net Block | C65: =IFERROR('[3]Data Sheet'!B62,0) -> 107231.76 | D65: =IFERROR('[3]Data Sheet'!C62,0) -> 95944.08 | E65: =IFERROR('[3]Data Sheet'!D62,0) -> 121413.86 | F65: =IFERROR('[3]Data Sheet'!E62,0) -> 111234.47 | G65: =IFERROR('[3]Data Sheet'!F62,0) -> 127107.14 | H65: =IFERROR('[3]Data Sheet'!G62,0) -> 138707.61 | I65: =IFERROR('[3]Data Sheet'!H62,0) -> 138855.45 | J65: =IFERROR('[3]Data Sheet'!I62,0) -> 132079.76 | ... L65: =IFERROR('[3]Data Sheet'!K62,0) -> 115697
B66: Capital Work in Progress | C66: =IFERROR('[3]Data Sheet'!B63,0) -> 25918.94 | D66: =IFERROR('[3]Data Sheet'!C63,0) -> 33698.84 | E66: =IFERROR('[3]Data Sheet'!D63,0) -> 40033.5 | F66: =IFERROR('[3]Data Sheet'!E63,0) -> 31883.84 | G66: =IFERROR('[3]Data Sheet'!F63,0) -> 35622.29 | H66: =IFERROR('[3]Data Sheet'!G63,0) -> 20963.93 | I66: =IFERROR('[3]Data Sheet'!H63,0) -> 10251.09 | J66: =IFERROR('[3]Data Sheet'!I63,0) -> 14274.5 | ... L66: =IFERROR('[3]Data Sheet'!K63,0) -> 65806
B67: Investments | C67: =IFERROR('[3]Data Sheet'!B64,0) -> 23767.02 | D67: =IFERROR('[3]Data Sheet'!C64,0) -> 20337.92 | E67: =IFERROR('[3]Data Sheet'!D64,0) -> 20812.75 | F67: =IFERROR('[3]Data Sheet'!E64,0) -> 15770.72 | G67: =IFERROR('[3]Data Sheet'!F64,0) -> 16308.48 | H67: =IFERROR('[3]Data Sheet'!G64,0) -> 24620.28 | I67: =IFERROR('[3]Data Sheet'!H64,0) -> 29379.53 | J67: =IFERROR('[3]Data Sheet'!I64,0) -> 26379.16 | ... L67: =IFERROR('[3]Data Sheet'!K64,0) -> 35656
B68: Other Assets | C68: =IFERROR('[3]Data Sheet'!B65-SUM('[3]Data Sheet'!B67:B69),0) -> 29579.36 | D68: =IFERROR('[3]Data Sheet'!C65-SUM('[3]Data Sheet'!C67:C69),0) -> 37360.78 | E68: =IFERROR('[3]Data Sheet'!D65-SUM('[3]Data Sheet'!D67:D69),0) -> 48286.86 | F68: =IFERROR('[3]Data Sheet'!E65-SUM('[3]Data Sheet'!E67:E69),0) -> 56155.74 | G68: =IFERROR('[3]Data Sheet'!F65-SUM('[3]Data Sheet'!F67:F69),0) -> 58784.94 | H68: =IFERROR('[3]Data Sheet'!G65-SUM('[3]Data Sheet'!G67:G69),0) -> 61717.96 | I68: =IFERROR('[3]Data Sheet'!H65-SUM('[3]Data Sheet'!H67:H69),0) -> 62223.77 | J68: =IFERROR('[3]Data Sheet'!I65-SUM('[3]Data Sheet'!I67:I69),0) -> 68432.09 | ... L68: =IFERROR('[3]Data Sheet'!K65-SUM('[3]Data Sheet'!K67:K69),0) -> 58463
B69: Total Non Current Assets | C69: =SUM(C65:C68) -> 186497.08 | D69: =SUM(D65:D68) -> 187341.62 | E69: =SUM(E65:E68) -> 230546.97 | F69: =SUM(F65:F68) -> 215044.77 | G69: =SUM(G65:G68) -> 237822.85 | H69: =SUM(H65:H68) -> 246009.78 | I69: =SUM(I65:I68) -> 240709.84 | J69: =SUM(J65:J68) -> 241165.51 | ... L69: =SUM(L65:L68) -> 275622
B71: Receivables | C71: =IFERROR('[3]Data Sheet'!B67,0) -> 13570.91 | D71: =IFERROR('[3]Data Sheet'!C67,0) -> 14075.55 | E71: =IFERROR('[3]Data Sheet'!D67,0) -> 19893.3 | F71: =IFERROR('[3]Data Sheet'!E67,0) -> 18996.17 | G71: =IFERROR('[3]Data Sheet'!F67,0) -> 11172.69 | H71: =IFERROR('[3]Data Sheet'!G67,0) -> 12679.08 | I71: =IFERROR('[3]Data Sheet'!H67,0) -> 12442.12 | J71: =IFERROR('[3]Data Sheet'!I67,0) -> 15737.97 | ... L71: =IFERROR('[3]Data Sheet'!K67,0) -> 13248
B72: Inventory | C72: =IFERROR('[3]Data Sheet'!B68,0) -> 32655.73 | D72: =IFERROR('[3]Data Sheet'!C68,0) -> 35085.31 | E72: =IFERROR('[3]Data Sheet'!D68,0) -> 42137.63 | F72: =IFERROR('[3]Data Sheet'!E68,0) -> 39013.73 | G72: =IFERROR('[3]Data Sheet'!F68,0) -> 37456.88 | H72: =IFERROR('[3]Data Sheet'!G68,0) -> 36088.59 | I72: =IFERROR('[3]Data Sheet'!H68,0) -> 35240.34 | J72: =IFERROR('[3]Data Sheet'!I68,0) -> 40755.39 | ... L72: =IFERROR('[3]Data Sheet'!K68,0) -> 47269
B73: Cash & Bank | C73: =IFERROR('[3]Data Sheet'!B69,0) -> 30460.4 | D73: =IFERROR('[3]Data Sheet'!C69,0) -> 36077.88 | E73: =IFERROR('[3]Data Sheet'!D69,0) -> 34613.91 | F73: =IFERROR('[3]Data Sheet'!E69,0) -> 32648.82 | G73: =IFERROR('[3]Data Sheet'!F69,0) -> 33726.97 | H73: =IFERROR('[3]Data Sheet'!G69,0) -> 46792.46 | I73: =IFERROR('[3]Data Sheet'!H69,0) -> 40669.19 | J73: =IFERROR('[3]Data Sheet'!I69,0) -> 37015.56 | ... L73: =IFERROR('[3]Data Sheet'!K69,0) -> 40834
B74: Total current Assets | C74: =IFERROR(SUM(C71:C73),0) -> 76687.04 | D74: =IFERROR(SUM(D71:D73),0) -> 85238.74 | E74: =IFERROR(SUM(E71:E73),0) -> 96644.84 | F74: =IFERROR(SUM(F71:F73),0) -> 90658.72 | G74: =IFERROR(SUM(G71:G73),0) -> 82356.54 | H74: =IFERROR(SUM(H71:H73),0) -> 95560.13 | I74: =IFERROR(SUM(I71:I73),0) -> 88351.65 | J74: =IFERROR(SUM(J71:J73),0) -> 93508.92 | ... L74: =IFERROR(SUM(L71:L73),0) -> 101351
B76: Total Assets | C76: =IFERROR(C69+C74,0) -> 263184.12 | D76: =IFERROR(D69+D74,0) -> 272580.36 | E76: =IFERROR(E69+E74,0) -> 327191.81 | F76: =IFERROR(F69+F74,0) -> 305703.49 | G76: =IFERROR(G69+G74,0) -> 320179.39 | H76: =IFERROR(H69+H74,0) -> 341569.91 | I76: =IFERROR(I69+I74,0) -> 329061.49 | J76: =IFERROR(J69+J74,0) -> 334674.43 | ... L76: =IFERROR(L69+L74,0) -> 376973
B78: Check | C78: =C76=C63 -> TRUE | D78: =D76=D63 -> TRUE | E78: =E76=E63 -> TRUE | F78: =F76=F63 -> TRUE | G78: =G76=G63 -> TRUE | H78: =H76=H63 -> TRUE | I78: =I76=I63 -> TRUE | J78: =J76=J63 -> TRUE | ... L78: =L76=L63 -> TRUE
B80: Cash Flow Statements
B82: Cash From Operating Activities | C82: =IFERROR('[3]Data Sheet'!B83,0) -> -36693.9 | D82: =IFERROR('[3]Data Sheet'!C83,0) -> -39571.4 | E82: =IFERROR('[3]Data Sheet'!D83,0) -> -25139.14 | F82: =IFERROR('[3]Data Sheet'!E83,0) -> -20878.07 | G82: =IFERROR('[3]Data Sheet'!F83,0) -> -33114.55 | H82: =IFERROR('[3]Data Sheet'!G83,0) -> -25672.5 | I82: =IFERROR('[3]Data Sheet'!H83,0) -> -4443.66 | J82: =IFERROR('[3]Data Sheet'!I83,0) -> -15417.17 | ... L82: =IFERROR('[3]Data Sheet'!K83,0) -> -49982
A84: x | B84: Cash From Invrsting Activities | C84: =IFERROR('[3]Data Sheet'!B84,0) -> -3795.12 | D84: =IFERROR('[3]Data Sheet'!C84,0) -> 6205.3 | E84: =IFERROR('[3]Data Sheet'!D84,0) -> 2011.71 | F84: =IFERROR('[3]Data Sheet'!E84,0) -> 8830.37 | G84: =IFERROR('[3]Data Sheet'!F84,0) -> 3389.61 | H84: =IFERROR('[3]Data Sheet'!G84,0) -> 9904.2 | I84: =IFERROR('[3]Data Sheet'!H84,0) -> -3380.17 | J84: =IFERROR('[3]Data Sheet'!I84,0) -> -26242.9 | ... L84: =IFERROR('[3]Data Sheet'!K84,0) -> -18786
B86: Cash From Financing Activities | C86: =IFERROR('[3]Data Sheet'!B85,0) -> -2589.48 | D86: =IFERROR('[3]Data Sheet'!C85,0) -> -3166.85 | E86: =IFERROR('[3]Data Sheet'!D85,0) -> 729.99 | F86: =IFERROR('[3]Data Sheet'!E85,0) -> 6843.05 | G86: =IFERROR('[3]Data Sheet'!F85,0) -> -3092 | H86: =IFERROR('[3]Data Sheet'!G85,0) -> 13232.21 | I86: =IFERROR('[3]Data Sheet'!H85,0) -> 6459 | J86: =IFERROR('[3]Data Sheet'!I85,0) -> -6272.06 | ... L86: =IFERROR('[3]Data Sheet'!K85,0) -> -5666
B88: Net Cash Flow | C88: =C82+C84+C86 -> -43078.5 | D88: =D82+D84+D86 -> -36532.95 | E88: =E82+E84+E86 -> -22397.44 | F88: =F82+F84+F86 -> -5204.65 | G88: =G82+G84+G86 -> -32816.94 | H88: =H82+H84+H86 -> -2536.09 | I88: =I82+I84+I86 -> -1364.83 | J88: =J82+J84+J86 -> -47932.13 | ... L88: =L82+L84+L86 -> -74434

Sheet Ratio Analysis
B2: TATA MOTORS LTD
B3: ( TATA MOTORS LTD | BSE Code : 500570 )
B4: INR 716.00 (as on 05.10.2025)
B5: 52 Week ( High - INR 948.45 & Low - 535.75)
B8: ="Ratio Analysis - "&'[3]Data Sheet'!B1 -> Ratio Analysis - TATA MOTORS LTD
B9: Years | C9: ='[3]Data Sheet'!B16 -> 42460 | D9: ='[3]Data Sheet'!C16 -> 42825 | E9: ='[3]Data Sheet'!D16 -> 43190 | F9: ='[3]Data Sheet'!E16 -> 43555 | G9: ='[3]Data Sheet'!F16 -> 43921 | H9: ='[3]Data Sheet'!G16 -> 44286 | I9: ='[3]Data Sheet'!H16 -> 44651 | J9: ='[3]Data Sheet'!I16 -> 45016 | ... L9: ='[3]Data Sheet'!K16 -> 45747 | M9: Trend | N9: Mean | O9: Median
B11: SalesGrowth | D11: =IFERROR([3]HistoricalFS!D7,0) -> -0.01228033 | E11: =IFERROR([3]HistoricalFS!E7,0) -> 0.081047746 | F11: =IFERROR([3]HistoricalFS!F7,0) -> 0.035629919 | G11: =IFERROR([3]HistoricalFS!G7,0) -> -0.13536016 | H11: =IFERROR([3]HistoricalFS!H7,0) -> -0.043181168 | I11: =IFERROR([3]HistoricalFS!I7,0) -> 0.11472967 | J11: =IFERROR([3]HistoricalFS!J7,0) -> 0.24245815 | K11: =IFERROR([3]HistoricalFS!K7,0) -> 0.25450126 | L11: =IFERROR([3]HistoricalFS!L7,0) -> 0.013084771 | N11: =IFERROR(AVERAGE(D11:L11),0) -> 0.061181096 | O11: =IFERROR(MEDIAN(C11:L11),0) -> 0.035629919
B12: EBITDA Growth | D12: =IFERROR([3]HistoricalFS!D18/[3]HistoricalFS!C18-1,0) -> -0.22936587 | E12: =IFERROR([3]HistoricalFS!E18/[3]HistoricalFS!D18-1,0) -> 0.063165689 | F12: =IFERROR([3]HistoricalFS!F18/[3]HistoricalFS!E18-1,0) -> -0.21595203 | G12: =IFERROR([3]HistoricalFS!G18/[3]HistoricalFS!F18-1,0) -> -0.27072538 | H12: =IFERROR([3]HistoricalFS!H18/[3]HistoricalFS!G18-1,0) -> 0.79503554 | I12: =IFERROR([3]HistoricalFS!I18/[3]HistoricalFS!H18-1,0) -> -0.23437418 | J12: =IFERROR([3]HistoricalFS!J18/[3]HistoricalFS!I18-1,0) -> 0.28704224 | K12: =IFERROR([3]HistoricalFS!K18/[3]HistoricalFS!J18-1,0) -> 0.81746176 | L12: =IFERROR([3]HistoricalFS!L18/[3]HistoricalFS!K18-1,0) -> -0.04510238 | N12: =IFERROR(AVERAGE(D12:L12),0) -> 0.10746504 | O12: =IFERROR(MEDIAN(C12:L12),0) -> -0.04510238
B13: EBIT Growth | D13: =IFERROR([3]HistoricalFS!D27/[3]HistoricalFS!C27-1,0) -> -0.55668252 | E13: =IFERROR([3]HistoricalFS!E27/[3]HistoricalFS!D27-1,0) -> -0.29861437 | F13: =IFERROR([3]HistoricalFS!F27/[3]HistoricalFS!E27-1,0) -> -1.8970951 | G13: =IFERROR([3]HistoricalFS!G27/[3]HistoricalFS!F27-1,0) -> 1.2800252 | H13: =IFERROR([3]HistoricalFS!H27/[3]HistoricalFS!G27-1,0) -> -1.060248 | I13: =IFERROR([3]HistoricalFS!I27/[3]HistoricalFS!H27-1,0) -> -15.649149 | J13: =IFERROR([3]HistoricalFS!J27/[3]HistoricalFS!I27-1,0) -> -0.65313669 | K13: =IFERROR([3]HistoricalFS!K27/[3]HistoricalFS!J27-1,0) -> -8.0308008 | L13: =IFERROR([3]HistoricalFS!L27/[3]HistoricalFS!K27-1,0) -> 0.16902266 | N13: =IFERROR(AVERAGE(D13:L13),0) -> -2.9662977 | O13: =IFERROR(MEDIAN(C13:L13),0) -> -0.65313669
B14: Net Profit Growth | D14: =IFERROR([3]HistoricalFS!D33/[3]HistoricalFS!C33-1,0) -> -0.69539895 | E14: =IFERROR([3]HistoricalFS!E33/[3]HistoricalFS!D33-1,0) -> -0.79011124 | F14: =IFERROR([3]HistoricalFS!F33/[3]HistoricalFS!E33-1,0) -> -3.5528471 | G14: =IFERROR([3]HistoricalFS!G33/[3]HistoricalFS!F33-1,0) -> 3.9286703 | H14: =IFERROR([3]HistoricalFS!H33/[3]HistoricalFS!G33-1,0) -> -0.82862505 | I14: =IFERROR([3]HistoricalFS!I33/[3]HistoricalFS!H33-1,0) -> 6.1952157 | J14: =IFERROR([3]HistoricalFS!J33/[3]HistoricalFS!I33-1,0) -> -0.70904365 | K14: =IFERROR([3]HistoricalFS!K33/[3]HistoricalFS!J33-1,0) -> -7.7977655 | L14: =IFERROR([3]HistoricalFS!L33/[3]HistoricalFS!K33-1,0) -> -0.39385527 | N14: =IFERROR(AVERAGE(D14:L14),0) -> -0.51597342 | O14: =IFERROR(MEDIAN(C14:L14),0) -> -0.70904365
B15: Dividend Growth | D15: =IFERROR([3]HistoricalFS!D41/[3]HistoricalFS!C41-1,0) -> -1 | E15: =IFERROR([3]HistoricalFS!E41/[3]HistoricalFS!D41-1,0) -> 0 | F15: =IFERROR([3]HistoricalFS!F41/[3]HistoricalFS!E41-1,0) -> 0 | G15: =IFERROR([3]HistoricalFS!G41/[3]HistoricalFS!F41-1,0) -> 0 | H15: =IFERROR([3]HistoricalFS!H41/[3]HistoricalFS!G41-1,0) -> 0 | I15: =IFERROR([3]HistoricalFS!I41/[3]HistoricalFS!H41-1,0) -> 0 | J15: =IFERROR([3]HistoricalFS!J41/[3]HistoricalFS!I41-1,0) -> 0 | K15: =IFERROR([3]HistoricalFS!K41/[3]HistoricalFS!J41-1,0) -> 2.0032954 | L15: =IFERROR([3]HistoricalFS!L41/[3]HistoricalFS!K41-1,0) -> -0.041110112 | N15: =IFERROR(AVERAGE(D15:L15),0) -> 0.10690947 | O15: =IFERROR(MEDIAN(C15:L15),0) -> 0
B17: Gross Margin | C17: =IFERROR([3]HistoricalFS!C13,0) -> 0.24734524 | D17: =IFERROR([3]HistoricalFS!D13,0) -> 0.23819078 | E17: =IFERROR([3]HistoricalFS!E13,0) -> 0.2164999 | F17: =IFERROR([3]HistoricalFS!F13,0) -> 0.19571167 | G17: =IFERROR([3]HistoricalFS!G13,0) -> 0.19417127 | H17: =IFERROR([3]HistoricalFS!H13,0) -> 0.21805386 | I17: =IFERROR([3]HistoricalFS!I13,0) -> 0.19807108 | J17: =IFERROR([3]HistoricalFS!J13,0) -> 0.20685018 | ... L17: =IFERROR([3]HistoricalFS!L13,0) -> 0.2248968 | N17: =IFERROR(AVERAGE(C17:L17),0) -> 0.21693584 | O17: =IFERROR(MEDIAN(C17:L17),0) -> 0.21727688
B18: EBITDA Margin | C18: =IFERROR([3]HistoricalFS!C19,0) -> 0.14061845 | D18: =IFERROR([3]HistoricalFS!D19,0) -> 0.10971269 | E18: =IFERROR([3]HistoricalFS!E19,0) -> 0.10789788 | F18: =IFERROR([3]HistoricalFS!F19,0) -> 0.081686629 | G18: =IFERROR([3]HistoricalFS!G19,0) -> 0.068898034 | H18: =IFERROR([3]HistoricalFS!H19,0) -> 0.12925584 | I18: =IFERROR([3]HistoricalFS!I19,0) -> 0.088776328 | J18: =IFERROR([3]HistoricalFS!J19,0) -> 0.091961958 | ... L18: =IFERROR([3]HistoricalFS!L19,0) -> 0.12557796 | N18: =IFERROR(AVERAGE(C18:L18),0) -> 0.10776159 | O18: =IFERROR(MEDIAN(C18:L18),0) -> 0.10880529
B19: EBIT Margin | C19: =IFERROR(([3]HistoricalFS!C18-[3]HistoricalFS!C24)/[3]HistoricalFS!C6,0) -> 0.079417028 | D19: =IFERROR(([3]HistoricalFS!D18-[3]HistoricalFS!D24)/[3]HistoricalFS!D6,0) -> 0.043322301 | E19: =IFERROR(([3]HistoricalFS!E18-[3]HistoricalFS!E24)/[3]HistoricalFS!E6,0) -> 0.033970412 | F19: =IFERROR(([3]HistoricalFS!F18-[3]HistoricalFS!F24)/[3]HistoricalFS!F6,0) -> 0.0035560233 | G19: =IFERROR(([3]HistoricalFS!G18-[3]HistoricalFS!G24)/[3]HistoricalFS!G6,0) -> -0.013170363 | H19: =IFERROR(([3]HistoricalFS!H18-[3]HistoricalFS!H24)/[3]HistoricalFS!H6,0) -> 0.034991608 | I19: =IFERROR(([3]HistoricalFS!I18-[3]HistoricalFS!I24)/[3]HistoricalFS!I6,0) -> -0.00041514993 | J19: =IFERROR(([3]HistoricalFS!J18-[3]HistoricalFS!J24)/[3]HistoricalFS!J6,0) -> 0.020104347 | ... L19: =IFERROR(([3]HistoricalFS!L18-[3]HistoricalFS!L24)/[3]HistoricalFS!L6,0) -> 0.072686749 | N19: =IFERROR(AVERAGE(C19:L19),0) -> 0.034493271 | O19: =IFERROR(MEDIAN(C19:L19),0) -> 0.03448101
B20: EBT Margin | C20: =IFERROR([3]HistoricalFS!C28,0) -> 0.061511301 | D20: =IFERROR([3]HistoricalFS!D28,0) -> 0.027608071 | E20: =IFERROR([3]HistoricalFS!E28,0) -> 0.017912164 | F20: =IFERROR([3]HistoricalFS!F28,0) -> -0.015516079 | G20: =IFERROR([3]HistoricalFS!G28,0) -> -0.04091536 | H20: =IFERROR([3]HistoricalFS!H28,0) -> 0.0025763152 | I20: =IFERROR([3]HistoricalFS!I28,0) -> -0.033856482 | J20: =IFERROR([3]HistoricalFS!J28,0) -> -0.009451885 | ... L20: =IFERROR([3]HistoricalFS!L28,0) -> 0.061126463 | N20: =IFERROR(AVERAGE(C20:L20),0) -> 0.012396721 | O20: =IFERROR(MEDIAN(C20:L20),0) -> 0.01024424
B21: Net Profit Margin | C21: =IFERROR([3]HistoricalFS!C34,0) -> 0.050432382 | D21: =IFERROR([3]HistoricalFS!D34,0) -> 0.015552749 | E21: =IFERROR([3]HistoricalFS!E34,0) -> 0.0030196143 | F21: =IFERROR([3]HistoricalFS!F34,0) -> -0.0074434057 | G21: =IFERROR([3]HistoricalFS!G34,0) -> -0.042429334 | H21: =IFERROR([3]HistoricalFS!H34,0) -> -0.0075994792 | I21: =IFERROR([3]HistoricalFS!I34,0) -> -0.049052155 | J21: =IFERROR([3]HistoricalFS!J34,0) -> -0.011486935 | ... L21: =IFERROR([3]HistoricalFS!L34,0) -> 0.037241724 | N21: =IFERROR(AVERAGE(C21:L21),0) -> 0.0050479411 | O21: =IFERROR(MEDIAN(C21:L21),0) -> -0.0022118957
B23: SalesExpense%Sales | C23: =IFERROR([3]HistoricalFS!C16,0) -> 0.10672679 | D23: =IFERROR([3]HistoricalFS!D16,0) -> 0.1284781 | E23: =IFERROR([3]HistoricalFS!E16,0) -> 0.10860202 | F23: =IFERROR([3]HistoricalFS!F16,0) -> 0.11402505 | G23: =IFERROR([3]HistoricalFS!G16,0) -> 0.12527324 | H23: =IFERROR([3]HistoricalFS!H16,0) -> 0.088798023 | I23: =IFERROR([3]HistoricalFS!I16,0) -> 0.10929475 | J23: =IFERROR([3]HistoricalFS!J16,0) -> 0.11488822 | ... L23: =IFERROR([3]HistoricalFS!L16,0) -> 0.099318846 | N23: =IFERROR(AVERAGE(C23:L23),0) -> 0.10917425 | O23: =IFERROR(MEDIAN(C23:L23),0) -> 0.10894839
B24: Depreciation%Sales | C24: =IFERROR([3]HistoricalFS!C25,0) -> 0.061201426 | D24: =IFERROR([3]HistoricalFS!D25,0) -> 0.066390387 | E24: =IFERROR([3]HistoricalFS!E25,0) -> 0.073927472 | F24: =IFERROR([3]HistoricalFS!F25,0) -> 0.078130605 | G24: =IFERROR([3]HistoricalFS!G25,0) -> 0.082068398 | H24: =IFERROR([3]HistoricalFS!H25,0) -> 0.094264231 | I24: =IFERROR([3]HistoricalFS!I25,0) -> 0.089191478 | J24: =IFERROR([3]HistoricalFS!J25,0) -> 0.071857611 | ... L24: =IFERROR([3]HistoricalFS!L25,0) -> 0.052891209 | N24: =IFERROR(AVERAGE(C24:L24),0) -> 0.073268318 | O24: =IFERROR(MEDIAN(C24:L24),0) -> 0.072892542
B25: OperatingIncome%Sales | C25: =C19 -> 0.079417028 | D25: =D19 -> 0.043322301 | E25: =E19 -> 0.033970412 | F25: =F19 -> 0.0035560233 | G25: =G19 -> -0.013170363 | H25: =H19 -> 0.034991608 | I25: =I19 -> -0.00041514993 | J25: =J19 -> 0.020104347 | ... L25: =L19 -> 0.072686749 | N25: =IFERROR(AVERAGE(C25:L25),0) -> 0.034493271 | O25: =IFERROR(MEDIAN(C25:L25),0) -> 0.03448101
B27: Return on Capital Employed | C27: =IFERROR(([3]HistoricalFS!C18-[3]HistoricalFS!C24)/(SUM([3]HistoricalFS!C47:C49)),0) -> 0.1462081 | D27: =IFERROR(([3]HistoricalFS!D18-[3]HistoricalFS!D24)/(SUM([3]HistoricalFS!D47:D49)),0) -> 0.085490986 | E27: =IFERROR(([3]HistoricalFS!E18-[3]HistoricalFS!E24)/(SUM([3]HistoricalFS!E47:E49)),0) -> 0.053716114 | F27: =IFERROR(([3]HistoricalFS!F18-[3]HistoricalFS!F24)/(SUM([3]HistoricalFS!F47:F49)),0) -> 0.0064542734 | G27: =IFERROR(([3]HistoricalFS!G18-[3]HistoricalFS!G24)/(SUM([3]HistoricalFS!G47:G49)),0) -> -0.018302178 | H27: =IFERROR(([3]HistoricalFS!H18-[3]HistoricalFS!H24)/(SUM([3]HistoricalFS!H47:H49)),0) -> 0.044284325 | I27: =IFERROR(([3]HistoricalFS!I18-[3]HistoricalFS!I24)/(SUM([3]HistoricalFS!I47:I49)),0) -> -0.00060520306 | J27: =IFERROR(([3]HistoricalFS!J18-[3]HistoricalFS!J24)/(SUM([3]HistoricalFS!J47:J49)),0) -> 0.038762956 | ... L27: =IFERROR(([3]HistoricalFS!L18-[3]HistoricalFS!L24)/(SUM([3]HistoricalFS!L47:L49)),0) -> 0.17028623 | N27: =IFERROR(AVERAGE(C27:L27),0) -> 0.068544162 | O27: =IFERROR(MEDIAN(C27:L27),0) -> 0.049000219
B28: Retaind Earnings% | C28: =IFERROR([3]HistoricalFS!C44,0) -> 0.99506766 | D28: =IFERROR([3]HistoricalFS!D44,0) -> 1 | E28: =IFERROR([3]HistoricalFS!E44,0) -> 1 | F28: =IFERROR([3]HistoricalFS!F44,0) -> 0 | G28: =IFERROR([3]HistoricalFS!G44,0) -> 0 | H28: =IFERROR([3]HistoricalFS!H44,0) -> 0 | I28: =IFERROR([3]HistoricalFS!I44,0) -> 0 | J28: =IFERROR([3]HistoricalFS!J44,0) -> 0 | ... L28: =IFERROR([3]HistoricalFS!L44,0) -> 0.86516031 | N28: =IFERROR(AVERAGE(C28:L28),0) -> 0.47750531 | O28: =IFERROR(MEDIAN(C28:L28),0) -> 0.43258015
B29: Return on Equity% | C29: =IFERROR([3]HistoricalFS!C33/SUM([3]HistoricalFS!C47:C48),0) -> 0.17441317 | D29: =IFERROR([3]HistoricalFS!D33/SUM([3]HistoricalFS!D47:D48),0) -> 0.07224119 | E29: =IFERROR([3]HistoricalFS!E33/SUM([3]HistoricalFS!E47:E48),0) -> 0.0092254981 | F29: =IFERROR([3]HistoricalFS!F33/SUM([3]HistoricalFS!F47:F48),0) -> -0.037345737 | G29: =IFERROR([3]HistoricalFS!G33/SUM([3]HistoricalFS!G47:G48),0) -> -0.17560555 | H29: =IFERROR([3]HistoricalFS!H33/SUM([3]HistoricalFS!H47:H48),0) -> -0.034360592 | I29: =IFERROR([3]HistoricalFS!I33/SUM([3]HistoricalFS!I47:I48),0) -> -0.30651638 | J29: =IFERROR([3]HistoricalFS!J33/SUM([3]HistoricalFS!J47:J48),0) -> -0.087686298 | ... L29: =IFERROR([3]HistoricalFS!L33/SUM([3]HistoricalFS!L47:L48),0) -> 0.14098877 | N29: =IFERROR(AVERAGE(C29:L29),0) -> 0.0073484502 | O29: =IFERROR(MEDIAN(C29:L29),0) -> -0.012567547
B30: Self Sustained Growth Rate | C30: =IFERROR(C28*C29,0) -> 0.1735529 | D30: =IFERROR(D28*D29,0) -> 0.07224119 | E30: =IFERROR(E28*E29,0) -> 0.0092254981 | F30: =IFERROR(F28*F29,0) -> 0 | G30: =IFERROR(G28*G29,0) -> 0 | H30: =IFERROR(H28*H29,0) -> 0 | I30: =IFERROR(I28*I29,0) -> 0 | J30: =IFERROR(J28*J29,0) -> 0 | ... L30: =IFERROR(L28*L29,0) -> 0.12197789 | N30: =IFERROR(AVERAGE(C30:L30),0) -> 0.066803118 | O30: =IFERROR(MEDIAN(C30:L30),0) -> 0.004612749
B31: Interest Coverage Ration | C31: =IFERROR((([3]HistoricalFS!C18-[3]HistoricalFS!C24)/[3]HistoricalFS!C21),0) -> 4.4352864 | D31: =IFERROR((([3]HistoricalFS!D18-[3]HistoricalFS!D24)/[3]HistoricalFS!D21),0) -> 2.7568835 | E31: =IFERROR((([3]HistoricalFS!E18-[3]HistoricalFS!E24)/[3]HistoricalFS!E21),0) -> 2.1154494 | F31: =IFERROR((([3]HistoricalFS!F18-[3]HistoricalFS!F24)/[3]HistoricalFS!F21),0) -> 0.18645157 | G31: =IFERROR((([3]HistoricalFS!G18-[3]HistoricalFS!G24)/[3]HistoricalFS!G21),0) -> -0.47469327 | H31: =IFERROR((([3]HistoricalFS!H18-[3]HistoricalFS!H24)/[3]HistoricalFS!H21),0) -> 1.0794784 | I31: =IFERROR((([3]HistoricalFS!I18-[3]HistoricalFS!I24)/[3]HistoricalFS!I21),0) -> -0.012414276 | J31: =IFERROR((([3]HistoricalFS!J18-[3]HistoricalFS!J24)/[3]HistoricalFS!J21),0) -> 0.6802067 | ... L31: =IFERROR((([3]HistoricalFS!L18-[3]HistoricalFS!L24)/[3]HistoricalFS!L21),0) -> 6.2876254 | N31: =IFERROR(AVERAGE(C31:L31),0) -> 2.1081796 | O31: =IFERROR(MEDIAN(C31:L31),0) -> 1.5974639
B33: Debtor Turnover Ratio | C33: =IFERROR([3]HistoricalFS!C6/[3]HistoricalFS!C59,0) -> 20.119918 | D33: =IFERROR([3]HistoricalFS!D6/[3]HistoricalFS!D59,0) -> 19.160353 | E33: =IFERROR([3]HistoricalFS!E6/[3]HistoricalFS!E59,0) -> 14.655712 | F33: =IFERROR([3]HistoricalFS!F6/[3]HistoricalFS!F59,0) -> 15.894699 | G33: =IFERROR([3]HistoricalFS!G6/[3]HistoricalFS!G59,0) -> 23.366617 | H33: =IFERROR([3]HistoricalFS!H6/[3]HistoricalFS!H59,0) -> 19.701331 | I33: =IFERROR([3]HistoricalFS!I6/[3]HistoricalFS!I59,0) -> 22.379918 | J33: =IFERROR([3]HistoricalFS!J6/[3]HistoricalFS!J59,0) -> 21.982948 | ... L33: =IFERROR([3]HistoricalFS!L6/[3]HistoricalFS!L59,0) -> 33.189538 | N33: =IFERROR(AVERAGE(C33:L33),0) -> 21.605368 | O33: =IFERROR(MEDIAN(C33:L33),0) -> 21.051433
B34: Creditor Turnover Ratio | C34: =IFERROR([3]HistoricalFS!C6/[3]HistoricalFS!C50,0) -> 2.3769604 | D34: =IFERROR([3]HistoricalFS!D6/[3]HistoricalFS!D50,0) -> 1.9842808 | E34: =IFERROR([3]HistoricalFS!E6/[3]HistoricalFS!E50,0) -> 2.041478 | F34: =IFERROR([3]HistoricalFS!F6/[3]HistoricalFS!F50,0) -> 2.1667848 | G34: =IFERROR([3]HistoricalFS!G6/[3]HistoricalFS!G50,0) -> 1.9731057 | H34: =IFERROR([3]HistoricalFS!H6/[3]HistoricalFS!H50,0) -> 1.7323685 | I34: =IFERROR([3]HistoricalFS!I6/[3]HistoricalFS!I50,0) -> 2.0170312 | J34: =IFERROR([3]HistoricalFS!J6/[3]HistoricalFS!J50,0) -> 2.2286057 | ... L34: =IFERROR([3]HistoricalFS!L6/[3]HistoricalFS!L50,0) -> 2.3228767 | N34: =IFERROR(AVERAGE(C34:L34),0) -> 2.1290872 | O34: =IFERROR(MEDIAN(C34:L34),0) -> 2.1041314
B35: Inventory Turnover ratio | C35: =IFERROR([3]HistoricalFS!C6/[3]HistoricalFS!C60,0) -> 8.3613381 | D35: =IFERROR([3]HistoricalFS!D6/[3]HistoricalFS!D60,0) -> 7.6867643 | E35: =IFERROR([3]HistoricalFS!E6/[3]HistoricalFS!E60,0) -> 6.9190052 | F35: =IFERROR([3]HistoricalFS!F6/[3]HistoricalFS!F60,0) -> 7.7392856 | G35: =IFERROR([3]HistoricalFS!G6/[3]HistoricalFS!G60,0) -> 6.9698269 | H35: =IFERROR([3]HistoricalFS!H6/[3]HistoricalFS!H60,0) -> 6.9217099 | I35: =IFERROR([3]HistoricalFS!I6/[3]HistoricalFS!I60,0) -> 7.9015588 | J35: =IFERROR([3]HistoricalFS!J6/[3]HistoricalFS!J60,0) -> 8.4888642 | ... L35: =IFERROR([3]HistoricalFS!L6/[3]HistoricalFS!L60,0) -> 9.3019738 | N35: =IFERROR(AVERAGE(C35:L35),0) -> 7.937244 | O35: =IFERROR(MEDIAN(C35:L35),0) -> 7.8204222
B36: Fixed Asset Turnover Ratio | C36: =IFERROR([3]HistoricalFS!C6/[3]HistoricalFS!C53,0) -> 2.5463128 | D36: =IFERROR([3]HistoricalFS!D6/[3]HistoricalFS!D53,0) -> 2.8109343 | E36: =IFERROR([3]HistoricalFS!E6/[3]HistoricalFS!E53,0) -> 2.4012949 | F36: =IFERROR([3]HistoricalFS!F6/[3]HistoricalFS!F53,0) -> 2.714432 | G36: =IFERROR([3]HistoricalFS!G6/[3]HistoricalFS!G53,0) -> 2.0539206 | H36: =IFERROR([3]HistoricalFS!H6/[3]HistoricalFS!H53,0) -> 1.8008727 | I36: =IFERROR([3]HistoricalFS!I6/[3]HistoricalFS!I53,0) -> 2.0053489 | J36: =IFERROR([3]HistoricalFS!J6/[3]HistoricalFS!J53,0) -> 2.6193792 | ... L36: =IFERROR([3]HistoricalFS!L6/[3]HistoricalFS!L53,0) -> 3.800401 | N36: =IFERROR(AVERAGE(C36:L36),0) -> 2.6331377 | O36: =IFERROR(MEDIAN(C36:L36),0) -> 2.582846
B37: Capital Turnover Ratio | C37: =IFERROR([3]HistoricalFS!C6/SUM([3]HistoricalFS!C47:C48),0) -> 3.4583567 | D37: =IFERROR([3]HistoricalFS!D6/SUM([3]HistoricalFS!D47:D48),0) -> 4.6449144 | E37: =IFERROR([3]HistoricalFS!E6/SUM([3]HistoricalFS!E47:E48),0) -> 3.0551909 | F37: =IFERROR([3]HistoricalFS!F6/SUM([3]HistoricalFS!F47:F48),0) -> 5.0172916 | G37: =IFERROR([3]HistoricalFS!G6/SUM([3]HistoricalFS!G47:G48),0) -> 4.138777 | H37: =IFERROR([3]HistoricalFS!H6/SUM([3]HistoricalFS!H47:H48),0) -> 4.5214404 | I37: =IFERROR([3]HistoricalFS!I6/SUM([3]HistoricalFS!I47:I48),0) -> 6.2487853 | J37: =IFERROR([3]HistoricalFS!J6/SUM([3]HistoricalFS!J47:J48),0) -> 7.6335681 | ... L37: =IFERROR([3]HistoricalFS!L6/SUM([3]HistoricalFS!L47:L48),0) -> 3.7857746 | N37: =IFERROR(AVERAGE(C37:L37),0) -> 4.76151 | O37: =IFERROR(MEDIAN(C37:L37),0) -> 4.5831774
B39: (in days)
B40: Debtor Days | C40: =IFERROR(365/C33,0) -> 18.141227 | D40: =IFERROR(365/D33,0) -> 19.049753 | E40: =IFERROR(365/E33,0) -> 24.904965 | F40: =IFERROR(365/F33,0) -> 22.963631 | G40: =IFERROR(365/G33,0) -> 15.620575 | H40: =IFERROR(365/H33,0) -> 18.526667 | I40: =IFERROR(365/I33,0) -> 16.309265 | J40: =IFERROR(365/J33,0) -> 16.603779 | ... L40: =IFERROR(365/L33,0) -> 10.997441 | N40: =IFERROR(AVERAGE(C40:L40),0) -> 17.737364 | O40: =IFERROR(MEDIAN(C40:L40),0) -> 17.372503
B41: Payable Days | C41: =IFERROR(365/C34,0) -> 153.55746 | D41: =IFERROR(365/D34,0) -> 183.94574 | E41: =IFERROR(365/E34,0) -> 178.79203 | F41: =IFERROR(365/F34,0) -> 168.45236 | G41: =IFERROR(365/G34,0) -> 184.98755 | H41: =IFERROR(365/H34,0) -> 210.69421 | I41: =IFERROR(365/I34,0) -> 180.95902 | J41: =IFERROR(365/J34,0) -> 163.77953 | ... L41: =IFERROR(365/L34,0) -> 157.13275 | N41: =IFERROR(AVERAGE(C41:L41),0) -> 173.14397 | O41: =IFERROR(MEDIAN(C41:L41),0) -> 173.62219
B42: Inventory Days | C42: =IFERROR(365/C35,0) -> 43.6533 | D42: =IFERROR(365/D35,0) -> 47.484219 | E42: =IFERROR(365/E35,0) -> 52.753249 | F42: =IFERROR(365/F35,0) -> 47.161976 | G42: =IFERROR(365/G35,0) -> 52.368589 | H42: =IFERROR(365/H35,0) -> 52.732635 | I42: =IFERROR(365/I35,0) -> 46.193417 | J42: =IFERROR(365/J35,0) -> 42.997507 | ... L42: =IFERROR(365/L35,0) -> 39.238984 | N42: =IFERROR(AVERAGE(C42:L42),0) -> 46.477276 | O42: =IFERROR(MEDIAN(C42:L42),0) -> 46.677696
B43: Cash Conversion Cycle | C43: =SUM(C40,C42)-C41 -> -91.762933 | D43: =SUM(D40,D42)-D41 -> -117.41177 | E43: =SUM(E40,E42)-E41 -> -101.13382 | F43: =SUM(F40,F42)-F41 -> -98.326751 | G43: =SUM(G40,G42)-G41 -> -116.99839 | H43: =SUM(H40,H42)-H41 -> -139.4349 | I43: =SUM(I40,I42)-I41 -> -118.45634 | J43: =SUM(J40,J42)-J41 -> -104.17824 | ... L43: =SUM(L40,L42)-L41 -> -106.89633 | N43: =IFERROR(AVERAGE(C43:L43),0) -> -108.92933 | O43: =IFERROR(MEDIAN(C43:L43),0) -> -105.53729
B45: CFO/Sales | C45: =IFERROR([3]HistoricalFS!C70/[3]HistoricalFS!C6,0) -> -0.13438744 | D45: =IFERROR([3]HistoricalFS!D70/[3]HistoricalFS!D6,0) -> -0.14672784 | E45: =IFERROR([3]HistoricalFS!E70/[3]HistoricalFS!E6,0) -> -0.086225686 | F45: =IFERROR([3]HistoricalFS!F70/[3]HistoricalFS!F6,0) -> -0.069146786 | G45: =IFERROR([3]HistoricalFS!G70/[3]HistoricalFS!G6,0) -> -0.12684264 | H45: =IFERROR([3]HistoricalFS!H70/[3]HistoricalFS!H6,0) -> -0.10277438 | I45: =IFERROR([3]HistoricalFS!I70/[3]HistoricalFS!I6,0) -> -0.015958349 | J45: =IFERROR([3]HistoricalFS!J70/[3]HistoricalFS!J6,0) -> -0.044562549 | ... L45: =IFERROR([3]HistoricalFS!L70/[3]HistoricalFS!L6,0) -> -0.11367425 | N45: =IFERROR(AVERAGE(C45:L45),0) -> -0.089278877 | O45: =IFERROR(MEDIAN(C45:L45),0) -> -0.094500032
B46: CFO/Total Assets | C46: =IFERROR([3]HistoricalFS!C70/[3]HistoricalFS!C64,0) -> -0.13942293 | D46: =IFERROR([3]HistoricalFS!D70/[3]HistoricalFS!D64,0) -> -0.14517334 | E46: =IFERROR([3]HistoricalFS!E70/[3]HistoricalFS!E64,0) -> -0.076833036 | F46: =IFERROR([3]HistoricalFS!F70/[3]HistoricalFS!F64,0) -> -0.068295164 | G46: =IFERROR([3]HistoricalFS!G70/[3]HistoricalFS!G64,0) -> -0.10342499 | H46: =IFERROR([3]HistoricalFS!H70/[3]HistoricalFS!H64,0) -> -0.075160309 | I46: =IFERROR([3]HistoricalFS!I70/[3]HistoricalFS!I64,0) -> -0.013504041 | J46: =IFERROR([3]HistoricalFS!J70/[3]HistoricalFS!J64,0) -> -0.046066172 | ... L46: =IFERROR([3]HistoricalFS!L70/[3]HistoricalFS!L64,0) -> -0.13258775 | N46: =IFERROR(AVERAGE(C46:L46),0) -> -0.08621178 | O46: =IFERROR(MEDIAN(C46:L46),0) -> -0.075996672
B47: CFO/Total Debts | C47: =IFERROR([3]HistoricalFS!C70/[3]HistoricalFS!C49,0) -> -0.52903577 | D47: =IFERROR([3]HistoricalFS!D70/[3]HistoricalFS!D49,0) -> -0.50342743 | E47: =IFERROR([3]HistoricalFS!E70/[3]HistoricalFS!E49,0) -> -0.28261953 | F47: =IFERROR([3]HistoricalFS!F70/[3]HistoricalFS!F49,0) -> -0.19663766 | G47: =IFERROR([3]HistoricalFS!G70/[3]HistoricalFS!G49,0) -> -0.26536723 | H47: =IFERROR([3]HistoricalFS!H70/[3]HistoricalFS!H49,0) -> -0.18062617 | I47: =IFERROR([3]HistoricalFS!I70/[3]HistoricalFS!I49,0) -> -0.030342707 | J47: =IFERROR([3]HistoricalFS!J70/[3]HistoricalFS!J49,0) -> -0.11495619 | ... L47: =IFERROR([3]HistoricalFS!L70/[3]HistoricalFS!L49,0) -> -0.69865809 | N47: =IFERROR(AVERAGE(C47:L47),0) -> -0.30140533 | O47: =IFERROR(MEDIAN(C47:L47),0) -> -0.23887488

Sheet Forecasting
B2: TATA MOTORS LTD
B3: ( TATA MOTORS LTD | BSE Code : 500570 )
B4: INR 716.00 (as on 05.10.2025)
B5: 52 Week ( High - INR 948.45 & Low - 535.75)
B8: ='[4]Data Sheet'!$B$1&" - "&'[4]Data Sheet'!A17&" Forecasting" -> TATA MOTORS LTD - Sales Forecasting | G8: ='[4]Data Sheet'!$B$1&" - "&[4]HistoricalFS!B23&" Forecasting" -> TATA MOTORS LTD - EBITDA Forecasting | L8: ='[4]Data Sheet'!$B$1&" - "&[4]HistoricalFS!B43&" Forecasting" -> TATA MOTORS LTD - Earning per Share Forecasting
B9: Year weight | C9: Year | D9: Sales | E9: Sales Growth | G9: Year weight | H9: Year | I9: EBITDA | J9: Sales Growth | L9: Year weight | M9: Year | N9: EBITDA | O9: Sales Growth
B10: 1 | C10: ='[3]Data Sheet'!B16 -> 42460 | D10: 273045.6 | G10: 1 | H10: ='[3]Data Sheet'!B16 -> 42460 | I10: 36204.22 | L10: 1 | M10: ='[3]Data Sheet'!G16 -> 44286 | N10: 47.691141
B11: =B10+1 -> 2 | C11: =C10+365 -> 42825 | D11: 269692.51 | E11: =D11/D10-1 -> -0.01228033 | G11: =G10+1 -> 2 | H11: =H10+365 -> 42825 | I11: 32848.59 | J11: =I11/I10-1 -> -0.092686156 | L11: =L10+1 -> 2 | M11: =M10+365 -> 44651 | N11: 14.527778 | O11: =N11/N10-1 -> -0.69537785
B12: =B11+1 -> 3 | C12: =C11+365 -> 43190 | D12: 291550.48 | E12: =D12/D11-1 -> 0.081047746 | G12: =G11+1 -> 3 | H12: =H11+365 -> 43190 | I12: 39566.22 | J12: =I12/I11-1 -> 0.20450284 | L12: =L11+1 -> 3 | M12: =M11+365 -> 45016 | N12: 3.0491116 | O12: =N12/N11-1 -> -0.79011851
B13: =B12+1 -> 4 | C13: =C12+365 -> 43555 | D13: 301938.4 | E13: =D13/D12-1 -> 0.035629919 | G13: =G12+1 -> 4 | H13: =H12+365 -> 43555 | I13: -1914.45 | J13: =I13/I12-1 -> -1.048386 | L13: =L12+1 -> 4 | M13: =M12+365 -> 45381 | N13: -7.7839158 | O13: =N13/N12-1 -> -3.5528471
B14: =B13+1 -> 5 | C14: =C13+365 -> 43920 | D14: 261067.97 | E14: =D14/D13-1 -> -0.13536016 | G14: =G13+1 -> 5 | H14: =H13+365 -> 43920 | I14: 16993.16 | J14: =I14/I13-1 -> -9.8762621 | L14: =L13+1 -> 5 | M14: =M13+365 -> 45746 | N14: -38.364354 | O14: =N14/N13-1 -> 3.9286703
B15: =B14+1 -> 6 | C15: =C14+365 -> 44285 | D15: 249794.75 | E15: =D15/D14-1 -> -0.043181168 | G15: =G14+1 -> 6 | H15: =H14+365 -> 44285 | I15: 20734.35 | J15: =I15/I14-1 -> 0.22015858 | L15: =L14+1 -> 6 | M15: =M14+365 -> 46111 | N15: -6.1453869 | O15: =N15/N14-1 -> -0.83981519
B16: =B15+1 -> 7 | C16: =C15+365 -> 44650 | D16: 278453.62 | E16: =D16/D15-1 -> 0.11472967 | G16: =G15+1 -> 7 | H16: =H15+365 -> 44650 | I16: 26937.37 | J16: =I16/I15-1 -> 0.29916636 | L16: =L15+1 -> 7 | M16: =M15+365 -> 46476 | N16: -41.137096 | O16: =N16/N15-1 -> 5.6939799
B17: =B16+1 -> 8 | C17: =C16+365 -> 45015 | D17: 345966.97 | E17: =D17/D16-1 -> 0.24245815 | G17: =G16+1 -> 8 | H17: =H16+365 -> 45015 | I17: 38204.19 | J17: =I17/I16-1 -> 0.41825984 | L17: =L16+1 -> 8 | M17: =M16+365 -> 46841 | N17: -11.967657 | O17: =N17/N16-1 -> -0.7090787
B18: =B17+1 -> 9 | C18: =C17+365 -> 45380 | D18: 434016 | E18: =D18/D17-1 -> 0.25450126 | G18: =G17+1 -> 9 | H18: =H17+365 -> 45380 | I18: 62208 | J18: =I18/I17-1 -> 0.62830307 | L18: =L17+1 -> 9 | M18: =M17+365 -> 47206 | N18: 81.338632 | O18: =N18/N17-1 -> -7.7965375
B19: =B18+1 -> 10 | C19: =C18+365 -> 45745 | D19: 439695 | E19: =D19/D18-1 -> 0.013084771 | G19: =G18+1 -> 10 | H19: =H18+365 -> 45745 | I19: 66671 | J19: =I19/I18-1 -> 0.071743184 | L19: =L18+1 -> 10 | M19: =M18+365 -> 47571 | N19: 49.267383 | O19: =N19/N18-1 -> -0.39429295
B20: =B19+1 -> 11 | C20: =C19+365 -> 46110 | D20: =FORECAST(B20,$D$10:$D$19,$B$10:$B$19) -> 409204.26 | E20: =D20/D19-1 -> -0.069345204 | G20: =G19+1 -> 11 | H20: =H19+365 -> 46110 | I20: =FORECAST($G$20,I10:I19,$G$10:$G$19) -> 52618.711 | J20: =I20/I19-1 -> -0.21077063 | L20: =L19+1 -> 11 | M20: =M19+365 -> 47936 | N20: =FORECAST($L$20,N10:N19,$L$10:$L$19) -> 20.345488 | O20: =N20/N19-1 -> -0.58703939
B21: =B20+1 -> 12 | C21: =C20+365 -> 46475 | D21: =FORECAST(B21,$D$10:$D$19,$B$10:$B$19) -> 426419.19 | E21: =D21/D20-1 -> 0.04206929 | G21: =G20+1 -> 12 | H21: =H20+365 -> 46475 | I21: =FORECAST($G$20,I11:I20,$G$10:$G$19) -> 60757.145 | J21: =I21/I20-1 -> 0.15466804 | L21: =L20+1 -> 12 | M21: =M20+365 -> 48301 | N21: =FORECAST($L$20,N11:N20,$L$10:$L$19) -> 35.169612 | O21: =N21/N20-1 -> 0.72861972
B22: =B21+1 -> 13 | C22: =C21+365 -> 46840 | D22: =FORECAST(B22,$D$10:$D$19,$B$10:$B$19) -> 443634.13 | E22: =D22/D21-1 -> 0.040370915 | G22: =G21+1 -> 13 | H22: =H21+365 -> 46840 | I22: =FORECAST($G$20,I12:I21,$G$10:$G$19) -> 70161.817 | J22: =I22/I21-1 -> 0.15479122 | L22: =L21+1 -> 13 | M22: =M21+365 -> 48666 | N22: =FORECAST($L$20,N12:N21,$L$10:$L$19) -> 48.902865 | O22: =N22/N21-1 -> 0.39048635
B23: =B22+1 -> 14 | C23: =C22+365 -> 47205 | D23: =FORECAST(B23,$D$10:$D$19,$B$10:$B$19) -> 460849.06 | E23: =D23/D22-1 -> 0.038804348 | G23: =G22+1 -> 14 | H23: =H22+365 -> 47205 | I23: =FORECAST($G$20,I13:I22,$G$10:$G$19) -> 83259.156 | J23: =I23/I22-1 -> 0.18667332 | L23: =L22+1 -> 14 | M23: =M22+365 -> 49031 | N23: =FORECAST($L$20,N13:N22,$L$10:$L$19) -> 63.69232 | O23: =N23/N22-1 -> 0.30242512
B24: =B23+1 -> 15 | C24: =C23+365 -> 47570 | D24: =FORECAST(B24,$D$10:$D$19,$B$10:$B$19) -> 478063.99 | E24: =D24/D23-1 -> 0.037354818 | G24: =G23+1 -> 15 | H24: =H23+365 -> 47570 | I24: =FORECAST($G$20,I14:I23,$G$10:$G$19) -> 88494.212 | J24: =I24/I23-1 -> 0.062876643 | L24: =L23+1 -> 15 | M24: =M23+365 -> 49396 | N24: =FORECAST($L$20,N14:N23,$L$10:$L$19) -> 78.451833 | O24: =N24/N23-1 -> 0.23173143

Sheet Common Size Statement
B2: TATA MOTORS LTD
B3: ( TATA MOTORS LTD | BSE Code : 500570 )
B4: INR 716.00 (as on 05.10.2025)
B5: 52 Week ( High - INR 948.45 & Low - 535.75)
B8: ="Common Sixe Income Statement"& " "&" - "&'[3]Data Sheet'!$B$1 -> Common Sixe Income Statement - TATA MOTORS LTD
B10: Particulars | C10: ='[3]Data Sheet'!B$16 -> 42460 | D10: ='[3]Data Sheet'!C$16 -> 42825 | E10: ='[3]Data Sheet'!D$16 -> 43190 | F10: ='[3]Data Sheet'!E$16 -> 43555 | G10: ='[3]Data Sheet'!F$16 -> 43921 | H10: ='[3]Data Sheet'!G$16 -> 44286 | I10: ='[3]Data Sheet'!H$16 -> 44651 | J10: ='[3]Data Sheet'!I$16 -> 45016 | ... L10: ='[3]Data Sheet'!K$16 -> 45747
B12: ='[3]Data Sheet'!A17 -> Sales | C12: ='[3]Data Sheet'!B17/'[3]Data Sheet'!B$17 -> 1 | D12: ='[3]Data Sheet'!C17/'[3]Data Sheet'!C$17 -> 1 | E12: ='[3]Data Sheet'!D17/'[3]Data Sheet'!D$17 -> 1 | F12: ='[3]Data Sheet'!E17/'[3]Data Sheet'!E$17 -> 1 | G12: ='[3]Data Sheet'!F17/'[3]Data Sheet'!F$17 -> 1 | H12: ='[3]Data Sheet'!G17/'[3]Data Sheet'!G$17 -> 1 | I12: ='[3]Data Sheet'!H17/'[3]Data Sheet'!H$17 -> 1 | J12: ='[3]Data Sheet'!I17/'[3]Data Sheet'!I$17 -> 1 | ... L12: ='[3]Data Sheet'!K17/'[3]Data Sheet'!K$17 -> 1
B13: ='[3]Data Sheet'!A18 -> Raw Material Cost | C13: ='[3]Data Sheet'!B18/'[3]Data Sheet'!B$17 -> 0.60844786 | D13: ='[3]Data Sheet'!C18/'[3]Data Sheet'!C$17 -> 0.64256171 | E13: ='[3]Data Sheet'!D18/'[3]Data Sheet'!D$17 -> 0.64447357 | F13: ='[3]Data Sheet'!E18/'[3]Data Sheet'!E$17 -> 0.64340246 | G13: ='[3]Data Sheet'!F18/'[3]Data Sheet'!F$17 -> 0.63163559 | H13: ='[3]Data Sheet'!G18/'[3]Data Sheet'!G$17 -> 0.6149343 | I13: ='[3]Data Sheet'!H18/'[3]Data Sheet'!H$17 -> 0.64389657 | J13: ='[3]Data Sheet'!I18/'[3]Data Sheet'!I$17 -> 0.66842005 | ... L13: ='[3]Data Sheet'!K18/'[3]Data Sheet'!K$17 -> 0.611674
B14: ='[3]Data Sheet'!A19 -> Change in Inventory | C14: ='[3]Data Sheet'!B19/'[3]Data Sheet'!B$17 -> 0.010075204 | D14: ='[3]Data Sheet'!C19/'[3]Data Sheet'!C$17 -> 0.027438359 | E14: ='[3]Data Sheet'!D19/'[3]Data Sheet'!D$17 -> 0.007019642 | F14: ='[3]Data Sheet'!E19/'[3]Data Sheet'!E$17 -> -0.0068003275 | G14: ='[3]Data Sheet'!F19/'[3]Data Sheet'!F$17 -> -0.008546395 | H14: ='[3]Data Sheet'!G19/'[3]Data Sheet'!G$17 -> -0.018752035 | I14: ='[3]Data Sheet'!H19/'[3]Data Sheet'!H$17 -> -0.0057118668 | J14: ='[3]Data Sheet'!I19/'[3]Data Sheet'!I$17 -> 0.01382103 | ... L14: ='[3]Data Sheet'!K19/'[3]Data Sheet'!K$17 -> -0.0064499255
B15: ='[3]Data Sheet'!A20 -> Power and Fuel | C15: ='[3]Data Sheet'!B20/'[3]Data Sheet'!B$17 -> 0.0041884213 | D15: ='[3]Data Sheet'!C20/'[3]Data Sheet'!C$17 -> 0.0043005273 | E15: ='[3]Data Sheet'!D20/'[3]Data Sheet'!D$17 -> 0.004486633 | F15: ='[3]Data Sheet'!E20/'[3]Data Sheet'!E$17 -> 0.0052524952 | G15: ='[3]Data Sheet'!F20/'[3]Data Sheet'!F$17 -> 0.0048452899 | H15: ='[3]Data Sheet'!G20/'[3]Data Sheet'!G$17 -> 0.0044551377 | I15: ='[3]Data Sheet'!H20/'[3]Data Sheet'!H$17 -> 0.0078228109 | J15: ='[3]Data Sheet'!I20/'[3]Data Sheet'!I$17 -> 0.007264653 | ... L15: ='[3]Data Sheet'!K20/'[3]Data Sheet'!K$17 -> 0.0055561241
B16: ='[3]Data Sheet'!A21 -> Other Mfr. Exp | C16: ='[3]Data Sheet'!B21/'[3]Data Sheet'!B$17 -> 0.044320546 | D16: ='[3]Data Sheet'!C21/'[3]Data Sheet'!C$17 -> 0.037329068 | E16: ='[3]Data Sheet'!D21/'[3]Data Sheet'!D$17 -> 0.037632111 | F16: ='[3]Data Sheet'!E21/'[3]Data Sheet'!E$17 -> 0.038731543 | G16: ='[3]Data Sheet'!F21/'[3]Data Sheet'!F$17 -> 0.044208832 | H16: ='[3]Data Sheet'!G21/'[3]Data Sheet'!G$17 -> 0.033119871 | I16: ='[3]Data Sheet'!H21/'[3]Data Sheet'!H$17 -> 0.033856195 | J16: ='[3]Data Sheet'!I21/'[3]Data Sheet'!I$17 -> 0.03400894 | ... L16: ='[3]Data Sheet'!K21/'[3]Data Sheet'!K$17 -> 0.042786477
B17: ='[3]Data Sheet'!A22 -> Employee Cost | C17: ='[3]Data Sheet'!B22/'[3]Data Sheet'!B$17 -> 0.10577314 | D17: ='[3]Data Sheet'!C22/'[3]Data Sheet'!C$17 -> 0.10505627 | E17: ='[3]Data Sheet'!D22/'[3]Data Sheet'!D$17 -> 0.10392742 | F17: ='[3]Data Sheet'!E22/'[3]Data Sheet'!E$17 -> 0.1101015 | G17: ='[3]Data Sheet'!F22/'[3]Data Sheet'!F$17 -> 0.11659263 | H17: ='[3]Data Sheet'!G22/'[3]Data Sheet'!G$17 -> 0.11068479 | I17: ='[3]Data Sheet'!H22/'[3]Data Sheet'!H$17 -> 0.11064148 | J17: ='[3]Data Sheet'!I22/'[3]Data Sheet'!I$17 -> 0.097277205 | ... L17: ='[3]Data Sheet'!K22/'[3]Data Sheet'!K$17 -> 0.10863667
B18: ='[3]Data Sheet'!A23 -> Selling and admin | C18: ='[3]Data Sheet'!B23/'[3]Data Sheet'!B$17 -> 0.080542957 | D18: ='[3]Data Sheet'!C23/'[3]Data Sheet'!C$17 -> 0.11138381 | E18: ='[3]Data Sheet'!D23/'[3]Data Sheet'!D$17 -> 0.10634378 | F18: ='[3]Data Sheet'!E23/'[3]Data Sheet'!E$17 -> 0.10836581 | G18: ='[3]Data Sheet'!F23/'[3]Data Sheet'!F$17 -> 0.11203335 | H18: ='[3]Data Sheet'!G23/'[3]Data Sheet'!G$17 -> 0.092138806 | I18: ='[3]Data Sheet'!H23/'[3]Data Sheet'!H$17 -> 0.10488425 | J18: ='[3]Data Sheet'!I23/'[3]Data Sheet'!I$17 -> 0.10070091 | ... L18: ='[3]Data Sheet'!K23/'[3]Data Sheet'!K$17 -> 0.10711743
B19: ='[3]Data Sheet'!A24 -> Other Expenses | C19: ='[3]Data Sheet'!B24/'[3]Data Sheet'!B$17 -> 0.026183832 | D19: ='[3]Data Sheet'!C24/'[3]Data Sheet'!C$17 -> 0.017094283 | E19: ='[3]Data Sheet'!D24/'[3]Data Sheet'!D$17 -> 0.0022582367 | F19: ='[3]Data Sheet'!E24/'[3]Data Sheet'!E$17 -> 0.0056592338 | G19: ='[3]Data Sheet'!F24/'[3]Data Sheet'!F$17 -> 0.013239885 | H19: ='[3]Data Sheet'!G24/'[3]Data Sheet'!G$17 -> -0.0033407828 | I19: ='[3]Data Sheet'!H24/'[3]Data Sheet'!H$17 -> 0.0044105011 | J19: ='[3]Data Sheet'!I24/'[3]Data Sheet'!I$17 -> 0.014187308 | ... L19: ='[3]Data Sheet'!K24/'[3]Data Sheet'!K$17 -> -0.0077985877
B20: ='[3]Data Sheet'!A25 -> Other Income | C20: ='[3]Data Sheet'!B25/'[3]Data Sheet'!B$17 -> -0.0097771947 | D20: ='[3]Data Sheet'!C25/'[3]Data Sheet'!C$17 -> 0.0069304854 | E20: ='[3]Data Sheet'!D25/'[3]Data Sheet'!D$17 -> 0.020348895 | F20: ='[3]Data Sheet'!E25/'[3]Data Sheet'!E$17 -> -0.088383094 | G20: ='[3]Data Sheet'!F25/'[3]Data Sheet'!F$17 -> 0.00038959203 | H20: ='[3]Data Sheet'!G25/'[3]Data Sheet'!G$17 -> -0.044507861 | I20: ='[3]Data Sheet'!H25/'[3]Data Sheet'!H$17 -> 0.0087053995 | J20: ='[3]Data Sheet'!I25/'[3]Data Sheet'!I$17 -> 0.019261868 | ... L20: ='[3]Data Sheet'!K25/'[3]Data Sheet'!K$17 -> 0.026777653
B21: ='[3]Data Sheet'!A26 -> Depreciation | C21: ='[3]Data Sheet'!B26/'[3]Data Sheet'!B$17 -> 0.061201426 | D21: ='[3]Data Sheet'!C26/'[3]Data Sheet'!C$17 -> 0.066390387 | E21: ='[3]Data Sheet'!D26/'[3]Data Sheet'!D$17 -> 0.073927472 | F21: ='[3]Data Sheet'!E26/'[3]Data Sheet'!E$17 -> 0.078130605 | G21: ='[3]Data Sheet'!F26/'[3]Data Sheet'!F$17 -> 0.082068398 | H21: ='[3]Data Sheet'!G26/'[3]Data Sheet'!G$17 -> 0.094264231 | I21: ='[3]Data Sheet'!H26/'[3]Data Sheet'!H$17 -> 0.089191478 | J21: ='[3]Data Sheet'!I26/'[3]Data Sheet'!I$17 -> 0.071857611 | ... L21: ='[3]Data Sheet'!K26/'[3]Data Sheet'!K$17 -> 0.052891209
B22: ='[3]Data Sheet'!A27 -> Interest | C22: ='[3]Data Sheet'!B27/'[3]Data Sheet'!B$17 -> 0.017905727 | D22: ='[3]Data Sheet'!C27/'[3]Data Sheet'!C$17 -> 0.01571423 | E22: ='[3]Data Sheet'!D27/'[3]Data Sheet'!D$17 -> 0.016058248 | F22: ='[3]Data Sheet'!E27/'[3]Data Sheet'!E$17 -> 0.019072102 | G22: ='[3]Data Sheet'!F27/'[3]Data Sheet'!F$17 -> 0.027744997 | H22: ='[3]Data Sheet'!G27/'[3]Data Sheet'!G$17 -> 0.032415293 | I22: ='[3]Data Sheet'!H27/'[3]Data Sheet'!H$17 -> 0.033441332 | J22: ='[3]Data Sheet'!I27/'[3]Data Sheet'!I$17 -> 0.029556232 | ... L22: ='[3]Data Sheet'!K27/'[3]Data Sheet'!K$17 -> 0.011560286
B23: ='[3]Data Sheet'!A28 -> Profit before tax | C23: ='[3]Data Sheet'!B28/'[3]Data Sheet'!B$17 -> 0.051734106 | D23: ='[3]Data Sheet'!C28/'[3]Data Sheet'!C$17 -> 0.034538557 | E23: ='[3]Data Sheet'!D28/'[3]Data Sheet'!D$17 -> 0.038261059 | F23: ='[3]Data Sheet'!E28/'[3]Data Sheet'!E$17 -> -0.10389917 | G23: ='[3]Data Sheet'!F28/'[3]Data Sheet'!F$17 -> -0.040525768 | H23: ='[3]Data Sheet'!G28/'[3]Data Sheet'!G$17 -> -0.041931546 | I23: ='[3]Data Sheet'!H28/'[3]Data Sheet'!H$17 -> -0.025151083 | J23: ='[3]Data Sheet'!I28/'[3]Data Sheet'!I$17 -> 0.0098099827 | ... L23: ='[3]Data Sheet'!K28/'[3]Data Sheet'!K$17 -> 0.087904115
... B26: ='[3]Data Sheet'!A31 -> Dividend Amount | C26: ='[3]Data Sheet'!B31/'[3]Data Sheet'!B$17 -> 0.00024874966 | D26: ='[3]Data Sheet'!C31/'[3]Data Sheet'!C$17 -> 0 | E26: ='[3]Data Sheet'!D31/'[3]Data Sheet'!D$17 -> 0 | F26: ='[3]Data Sheet'!E31/'[3]Data Sheet'!E$17 -> 0 | G26: ='[3]Data Sheet'!F31/'[3]Data Sheet'!F$17 -> 0 | H26: ='[3]Data Sheet'!G31/'[3]Data Sheet'!G$17 -> 0 | I26: ='[3]Data Sheet'!H31/'[3]Data Sheet'!H$17 -> 0 | J26: ='[3]Data Sheet'!I31/'[3]Data Sheet'!I$17 -> 0.002214142 | ... L26: ='[3]Data Sheet'!K31/'[3]Data Sheet'!K$17 -> 0.0050216627
B27: ='[3]Data Sheet'!A34 -> EBITDA | C27: ='[3]Data Sheet'!B34/'[3]Data Sheet'!B$17 -> 0.13259404 | D27: ='[3]Data Sheet'!C34/'[3]Data Sheet'!C$17 -> 0.12180016 | E27: ='[3]Data Sheet'!D34/'[3]Data Sheet'!D$17 -> 0.13570967 | F27: ='[3]Data Sheet'!E34/'[3]Data Sheet'!E$17 -> -0.0063405317 | G27: ='[3]Data Sheet'!F34/'[3]Data Sheet'!F$17 -> 0.065090942 | H27: ='[3]Data Sheet'!G34/'[3]Data Sheet'!G$17 -> 0.083005548 | I27: ='[3]Data Sheet'!H34/'[3]Data Sheet'!H$17 -> 0.096739163 | J27: ='[3]Data Sheet'!I34/'[3]Data Sheet'!I$17 -> 0.11042728 | ... L27: ='[3]Data Sheet'!K34/'[3]Data Sheet'!K$17 -> 0.15163011
B29: ="Common Sixe Balance Sheet"& " "&" - "&'[3]Data Sheet'!$B$1 -> Common Sixe Balance Sheet - TATA MOTORS LTD
B31: Particulars | C31: ='[3]Data Sheet'!B$16 -> 42460 | D31: ='[3]Data Sheet'!C$16 -> 42825 | E31: ='[3]Data Sheet'!D$16 -> 43190 | F31: ='[3]Data Sheet'!E$16 -> 43555 | G31: ='[3]Data Sheet'!F$16 -> 43921 | H31: ='[3]Data Sheet'!G$16 -> 44286 | I31: ='[3]Data Sheet'!H$16 -> 44651 | J31: ='[3]Data Sheet'!I$16 -> 45016 | ... L31: ='[3]Data Sheet'!K$16 -> 45747
B33: Total Liabilities | C33: ='[3]Data Sheet'!B61/'[3]Data Sheet'!B$61 -> 1 | D33: ='[3]Data Sheet'!C61/'[3]Data Sheet'!C$61 -> 1 | E33: ='[3]Data Sheet'!D61/'[3]Data Sheet'!D$61 -> 1 | F33: ='[3]Data Sheet'!E61/'[3]Data Sheet'!E$61 -> 1 | G33: ='[3]Data Sheet'!F61/'[3]Data Sheet'!F$61 -> 1 | H33: ='[3]Data Sheet'!G61/'[3]Data Sheet'!G$61 -> 1 | I33: ='[3]Data Sheet'!H61/'[3]Data Sheet'!H$61 -> 1 | J33: ='[3]Data Sheet'!I61/'[3]Data Sheet'!I$61 -> 1 | ... L33: ='[3]Data Sheet'!K61/'[3]Data Sheet'!K$61 -> 1
B34: ='[3]Data Sheet'!A57 -> Equity Share Capital | C34: ='[3]Data Sheet'!B57/'[3]Data Sheet'!B$61 -> 0.0025806268 | D34: ='[3]Data Sheet'!C57/'[3]Data Sheet'!C$61 -> 0.0024918156 | E34: ='[3]Data Sheet'!D57/'[3]Data Sheet'!D$61 -> 0.0020759077 | F34: ='[3]Data Sheet'!E57/'[3]Data Sheet'!E$61 -> 0.0022218261 | G34: ='[3]Data Sheet'!F57/'[3]Data Sheet'!F$61 -> 0.0022473027 | H34: ='[3]Data Sheet'!G57/'[3]Data Sheet'!G$61 -> 0.00224203 | I34: ='[3]Data Sheet'!H57/'[3]Data Sheet'!H$61 -> 0.0023274677 | J34: ='[3]Data Sheet'!I57/'[3]Data Sheet'!I$61 -> 0.0022888513 | ... L34: ='[3]Data Sheet'!K57/'[3]Data Sheet'!K$61 -> 0.0019523945
B35: ='[3]Data Sheet'!A58 -> Reserves | C35: ='[3]Data Sheet'!B58/'[3]Data Sheet'!B$61 -> 0.29740864 | D35: ='[3]Data Sheet'!C58/'[3]Data Sheet'!C$61 -> 0.21051652 | E35: ='[3]Data Sheet'!D58/'[3]Data Sheet'!D$61 -> 0.28958148 | F35: ='[3]Data Sheet'!E58/'[3]Data Sheet'!E$61 -> 0.19463415 | G35: ='[3]Data Sheet'!F58/'[3]Data Sheet'!F$61 -> 0.19476266 | H35: ='[3]Data Sheet'!G58/'[3]Data Sheet'!G$61 -> 0.15950149 | I35: ='[3]Data Sheet'!H58/'[3]Data Sheet'!H$61 -> 0.13309172 | J35: ='[3]Data Sheet'!I58/'[3]Data Sheet'!I$61 -> 0.13313168 | ... L35: ='[3]Data Sheet'!K58/'[3]Data Sheet'!K$61 -> 0.30614394
B36: ='[3]Data Sheet'!A59 -> Borrowings | C36: ='[3]Data Sheet'!B59/'[3]Data Sheet'!B$61 -> 0.26354158 | D36: ='[3]Data Sheet'!C59/'[3]Data Sheet'!C$61 -> 0.28836993 | E36: ='[3]Data Sheet'!D59/'[3]Data Sheet'!D$61 -> 0.27186032 | F36: ='[3]Data Sheet'!E59/'[3]Data Sheet'!E$61 -> 0.34731478 | G36: ='[3]Data Sheet'!F59/'[3]Data Sheet'!F$61 -> 0.38974289 | H36: ='[3]Data Sheet'!G59/'[3]Data Sheet'!G$61 -> 0.41610975 | I36: ='[3]Data Sheet'!H59/'[3]Data Sheet'!H$61 -> 0.44505065 | J36: ='[3]Data Sheet'!I59/'[3]Data Sheet'!I$61 -> 0.40072807 | ... L36: ='[3]Data Sheet'!K59/'[3]Data Sheet'!K$61 -> 0.18977486
B37: ='[3]Data Sheet'!A60 -> Other Liabilities | C37: ='[3]Data Sheet'!B60/'[3]Data Sheet'!B$61 -> 0.43646915 | D37: ='[3]Data Sheet'!C60/'[3]Data Sheet'!C$61 -> 0.49862173 | E37: ='[3]Data Sheet'!D60/'[3]Data Sheet'!D$61 -> 0.43648229 | F37: ='[3]Data Sheet'!E60/'[3]Data Sheet'!E$61 -> 0.45582924 | G37: ='[3]Data Sheet'!F60/'[3]Data Sheet'!F$61 -> 0.41324715 | H37: ='[3]Data Sheet'!G60/'[3]Data Sheet'!G$61 -> 0.42214673 | I37: ='[3]Data Sheet'!H60/'[3]Data Sheet'!H$61 -> 0.41953016 | J37: ='[3]Data Sheet'!I60/'[3]Data Sheet'!I$61 -> 0.46385139 | ... L37: ='[3]Data Sheet'!K60/'[3]Data Sheet'!K$61 -> 0.5021288
B39: Total Assets | C39: ='[3]Data Sheet'!B75/'[3]Data Sheet'!B$75 -> 1 | D39: ='[3]Data Sheet'!C75/'[3]Data Sheet'!C$75 -> 1 | E39: ='[3]Data Sheet'!D75/'[3]Data Sheet'!D$75 -> 1 | F39: ='[3]Data Sheet'!E75/'[3]Data Sheet'!E$75 -> 1 | G39: ='[3]Data Sheet'!F75/'[3]Data Sheet'!F$75 -> 1 | H39: ='[3]Data Sheet'!G75/'[3]Data Sheet'!G$75 -> 1 | I39: ='[3]Data Sheet'!H75/'[3]Data Sheet'!H$75 -> 1 | J39: ='[3]Data Sheet'!I75/'[3]Data Sheet'!I$75 -> 1 | ... L39: ='[3]Data Sheet'!K75/'[3]Data Sheet'!K$75 -> 1
B40: ='[3]Data Sheet'!A62 -> Net Block | C40: ='[3]Data Sheet'!B62/'[3]Data Sheet'!B$75 -> 0.40744008 | D40: ='[3]Data Sheet'!C62/'[3]Data Sheet'!C$75 -> 0.35198457 | E40: ='[3]Data Sheet'!D62/'[3]Data Sheet'!D$75 -> 0.37107854 | F40: ='[3]Data Sheet'!E62/'[3]Data Sheet'!E$75 -> 0.36386392 | G40: ='[3]Data Sheet'!F62/'[3]Data Sheet'!F$75 -> 0.39698726 | H40: ='[3]Data Sheet'!G62/'[3]Data Sheet'!G$75 -> 0.40608849 | I40: ='[3]Data Sheet'!H62/'[3]Data Sheet'!H$75 -> 0.42197417 | J40: ='[3]Data Sheet'!I62/'[3]Data Sheet'!I$75 -> 0.39465148 | ... L40: ='[3]Data Sheet'!K62/'[3]Data Sheet'!K$75 -> 0.30691057
B41: ='[3]Data Sheet'!A63 -> Capital Work in Progress | C41: ='[3]Data Sheet'!B63/'[3]Data Sheet'!B$75 -> 0.098482158 | D41: ='[3]Data Sheet'!C63/'[3]Data Sheet'!C$75 -> 0.12362901 | E41: ='[3]Data Sheet'!D63/'[3]Data Sheet'!D$75 -> 0.12235484 | F41: ='[3]Data Sheet'!E63/'[3]Data Sheet'!E$75 -> 0.10429662 | G41: ='[3]Data Sheet'!F63/'[3]Data Sheet'!F$75 -> 0.11125729 | H41: ='[3]Data Sheet'!G63/'[3]Data Sheet'!G$75 -> 0.061375225 | I41: ='[3]Data Sheet'!H63/'[3]Data Sheet'!H$75 -> 0.031152506 | J41: ='[3]Data Sheet'!I63/'[3]Data Sheet'!I$75 -> 0.042651899 | ... L41: ='[3]Data Sheet'!K63/'[3]Data Sheet'!K$75 -> 0.17456423
B42: ='[3]Data Sheet'!A64 -> Investments | C42: ='[3]Data Sheet'!B64/'[3]Data Sheet'!B$75 -> 0.090305676 | D42: ='[3]Data Sheet'!C64/'[3]Data Sheet'!C$75 -> 0.074612566 | E42: ='[3]Data Sheet'!D64/'[3]Data Sheet'!D$75 -> 0.063610241 | F42: ='[3]Data Sheet'!E64/'[3]Data Sheet'!E$75 -> 0.051588289 | G42: ='[3]Data Sheet'!F64/'[3]Data Sheet'!F$75 -> 0.050935446 | H42: ='[3]Data Sheet'!G64/'[3]Data Sheet'!G$75 -> 0.072079768 | I42: ='[3]Data Sheet'!H64/'[3]Data Sheet'!H$75 -> 0.089282796 | J42: ='[3]Data Sheet'!I64/'[3]Data Sheet'!I$75 -> 0.078820363 | ... L42: ='[3]Data Sheet'!K64/'[3]Data Sheet'!K$75 -> 0.094585023
B43: ='[3]Data Sheet'!A65 -> Other Assets | C43: ='[3]Data Sheet'!B74/'[3]Data Sheet'!B$75 -> 0.11239037 | D43: ='[3]Data Sheet'!C74/'[3]Data Sheet'!C$75 -> 0.13706336 | E43: ='[3]Data Sheet'!D74/'[3]Data Sheet'!D$75 -> 0.14757967 | F43: ='[3]Data Sheet'!E74/'[3]Data Sheet'!E$75 -> 0.18369349 | G43: ='[3]Data Sheet'!F74/'[3]Data Sheet'!F$75 -> 0.18360001 | H43: ='[3]Data Sheet'!G74/'[3]Data Sheet'!G$75 -> 0.1806891 | I43: ='[3]Data Sheet'!H74/'[3]Data Sheet'!H$75 -> 0.18909466 | J43: ='[3]Data Sheet'!I74/'[3]Data Sheet'!I$75 -> 0.20447361 | ... L43: ='[3]Data Sheet'!K74/'[3]Data Sheet'!K$75 -> 0.15508538
B44: ='[3]Data Sheet'!A67 -> Receivables | C44: ='[3]Data Sheet'!B67/'[3]Data Sheet'!B$75 -> 0.051564319 | D44: ='[3]Data Sheet'!C67/'[3]Data Sheet'!C$75 -> 0.051638166 | E44: ='[3]Data Sheet'!D67/'[3]Data Sheet'!D$75 -> 0.060800116 | F44: ='[3]Data Sheet'!E67/'[3]Data Sheet'!E$75 -> 0.062139199 | G44: ='[3]Data Sheet'!F67/'[3]Data Sheet'!F$75 -> 0.034895094 | H44: ='[3]Data Sheet'!G67/'[3]Data Sheet'!G$75 -> 0.037120014 | I44: ='[3]Data Sheet'!H67/'[3]Data Sheet'!H$75 -> 0.037810927 | J44: ='[3]Data Sheet'!I67/'[3]Data Sheet'!I$75 -> 0.047024716 | ... L44: ='[3]Data Sheet'!K67/'[3]Data Sheet'!K$75 -> 0.0351431
B45: ='[3]Data Sheet'!A68 -> Inventory | C45: ='[3]Data Sheet'!B68/'[3]Data Sheet'!B$75 -> 0.12407941 | D45: ='[3]Data Sheet'!C68/'[3]Data Sheet'!C$75 -> 0.12871547 | E45: ='[3]Data Sheet'!D68/'[3]Data Sheet'!D$75 -> 0.12878571 | F45: ='[3]Data Sheet'!E68/'[3]Data Sheet'!E$75 -> 0.12761951 | G45: ='[3]Data Sheet'!F68/'[3]Data Sheet'!F$75 -> 0.11698717 | H45: ='[3]Data Sheet'!G68/'[3]Data Sheet'!G$75 -> 0.10565506 | I45: ='[3]Data Sheet'!H68/'[3]Data Sheet'!H$75 -> 0.10709348 | J45: ='[3]Data Sheet'!I68/'[3]Data Sheet'!I$75 -> 0.12177623 | ... L45: ='[3]Data Sheet'!K68/'[3]Data Sheet'!K$75 -> 0.12539094
B46: ='[3]Data Sheet'!A69 -> Cash & Bank | C46: ='[3]Data Sheet'!B69/'[3]Data Sheet'!B$75 -> 0.11573799 | D46: ='[3]Data Sheet'!C69/'[3]Data Sheet'!C$75 -> 0.13235686 | E46: ='[3]Data Sheet'!D69/'[3]Data Sheet'!D$75 -> 0.10579088 | F46: ='[3]Data Sheet'!E69/'[3]Data Sheet'!E$75 -> 0.10679898 | G46: ='[3]Data Sheet'!F69/'[3]Data Sheet'!F$75 -> 0.10533773 | H46: ='[3]Data Sheet'!G69/'[3]Data Sheet'!G$75 -> 0.13699234 | I46: ='[3]Data Sheet'!H69/'[3]Data Sheet'!H$75 -> 0.12359146 | J46: ='[3]Data Sheet'!I69/'[3]Data Sheet'!I$75 -> 0.1106017 | ... L46: ='[3]Data Sheet'!K69/'[3]Data Sheet'!K$75 -> 0.10832076

Sheet Intrinsic Growth
B2: TATA MOTORS LTD
B3: ( TATA MOTORS LTD | BSE Code : 500570 )
B4: INR 716.00 (as on 05.10.2025)
B5: 52 Week ( High - INR 948.45 & Low - 535.75)
B8: Calculation of ROIC | E8: ='Raw FS'!H$2 -> 44256 | F8: ='Raw FS'!I$2 -> 44621 | G8: ='Raw FS'!J$2 -> 44986 | H8: ='Raw FS'!K$2 -> 45352 | I8: ='Raw FS'!L$2 -> 45717
B10: Current Assets
B11: ='Raw FS'!B36 -> Inventories | E11: =IFERROR('Raw FS'!H36,0) -> 36089 | F11: =IFERROR('Raw FS'!I36,0) -> 35240 | G11: =IFERROR('Raw FS'!J36,0) -> 40755 | H11: =IFERROR('Raw FS'!K36,0) -> 47788 | I11: =IFERROR('Raw FS'!L36,0) -> 47269
B12: ='Raw FS'!B37 -> Trade receivables + | E12: =IFERROR('Raw FS'!H37,0) -> 12679 | F12: =IFERROR('Raw FS'!I37,0) -> 12442 | G12: =IFERROR('Raw FS'!J37,0) -> 15738 | H12: =IFERROR('Raw FS'!K37,0) -> 16952 | I12: =IFERROR('Raw FS'!L37,0) -> 13248
B13: ='Raw FS'!B39 -> Loans n Advances | E13: =IFERROR('Raw FS'!H39,0) -> 4520 | F13: =IFERROR('Raw FS'!I39,0) -> 4583 | G13: =IFERROR('Raw FS'!J39,0) -> -4029 | H13: =IFERROR('Raw FS'!K39,0) -> -1743 | I13: =IFERROR('Raw FS'!L39,0) -> 7552
B14: ='Raw FS'!B40 -> Other asset items | E14: =IFERROR('Raw FS'!H40,0) -> 57198 | F14: =IFERROR('Raw FS'!I40,0) -> 57641 | G14: =IFERROR('Raw FS'!J40,0) -> 72461 | H14: =IFERROR('Raw FS'!K40,0) -> 80763 | I14: =IFERROR('Raw FS'!L40,0) -> 50911
B15: Total Current Assets | E15: =SUM(E11:E14) -> 110486 | F15: =SUM(F11:F14) -> 109906 | G15: =SUM(G11:G14) -> 124925 | H15: =SUM(H11:H14) -> 143760 | I15: =SUM(I11:I14) -> 118980
B17: Current Liabilities
B18: ='Raw FS'!B13 -> Trade Payables | E18: =IFERROR('Raw FS'!H13,0) -> 76040 | F18: =IFERROR('Raw FS'!I13,0) -> 69750 | G18: =IFERROR('Raw FS'!J13,0) -> 79252 | H18: =IFERROR('Raw FS'!K13,0) -> 93978 | I18: =IFERROR('Raw FS'!L13,0) -> 97368
B19: ='Raw FS'!B14 -> Advance from Customers | E19: =IFERROR('Raw FS'!H14,0) -> 0 | F19: =IFERROR('Raw FS'!I14,0) -> 0 | G19: =IFERROR('Raw FS'!J14,0) -> 0 | H19: =IFERROR('Raw FS'!K14,0) -> 0 | I19: =IFERROR('Raw FS'!L14,0) -> 0
B20: ='Raw FS'!B15 -> Other liability items | E20: =IFERROR('Raw FS'!H15,0) -> 66579 | F20: =IFERROR('Raw FS'!I15,0) -> 64030 | G20: =IFERROR('Raw FS'!J15,0) -> 68710 | H20: =IFERROR('Raw FS'!K15,0) -> 75185 | I20: =IFERROR('Raw FS'!L15,0) -> 85311
B21: Total Current Liabilities | E21: =SUM(E18:E20) -> 142619 | F21: =SUM(F18:F20) -> 133780 | G21: =SUM(G18:G20) -> 147962 | H21: =SUM(H18:H20) -> 169163 | I21: =SUM(I18:I20) -> 182679
A23: x | B23: Net Working Capital | E23: =E15-E21 -> -32133 | F23: =F15-F21 -> -23874 | G23: =G15-G21 -> -23037 | H23: =H15-H21 -> -25403 | I23: =I15-I21 -> -63699
B25: Non Current Assets
B26: ='Raw FS'!B19 -> Land | E26: =IFERROR('Raw FS'!H19,0) -> 7819 | F26: =IFERROR('Raw FS'!I19,0) -> 7760 | G26: =IFERROR('Raw FS'!J19,0) -> 8045 | H26: =IFERROR('Raw FS'!K19,0) -> 7996 | I26: =IFERROR('Raw FS'!L19,0) -> 7900
B27: ='Raw FS'!B20 -> Building | E27: =IFERROR('Raw FS'!H20,0) -> 35537 | F27: =IFERROR('Raw FS'!I20,0) -> 36466 | G27: =IFERROR('Raw FS'!J20,0) -> 38674 | H27: =IFERROR('Raw FS'!K20,0) -> 40583 | I27: =IFERROR('Raw FS'!L20,0) -> 44662
B28: ='Raw FS'!B21 -> Plant Machinery | E28: =IFERROR('Raw FS'!H21,0) -> 138868 | F28: =IFERROR('Raw FS'!I21,0) -> 148585 | G28: =IFERROR('Raw FS'!J21,0) -> 153672 | H28: =IFERROR('Raw FS'!K21,0) -> 151877 | I28: =IFERROR('Raw FS'!L21,0) -> 155939
B29: ='Raw FS'!B22 -> Equipments | E29: =IFERROR('Raw FS'!H22,0) -> 0 | F29: =IFERROR('Raw FS'!I22,0) -> 0 | G29: =IFERROR('Raw FS'!J22,0) -> 0 | H29: =IFERROR('Raw FS'!K22,0) -> 0 | I29: =IFERROR('Raw FS'!L22,0) -> 0
B30: ='Raw FS'!B23 -> Computers | E30: =IFERROR('Raw FS'!H23,0) -> 3172 | F30: =IFERROR('Raw FS'!I23,0) -> 3383 | G30: =IFERROR('Raw FS'!J23,0) -> 3499 | H30: =IFERROR('Raw FS'!K23,0) -> 3667 | I30: =IFERROR('Raw FS'!L23,0) -> 3879
B31: ='Raw FS'!B24 -> Furniture n fittings | E31: =IFERROR('Raw FS'!H24,0) -> 1956 | F31: =IFERROR('Raw FS'!I24,0) -> 1984 | G31: =IFERROR('Raw FS'!J24,0) -> 2084 | H31: =IFERROR('Raw FS'!K24,0) -> 2029 | I31: =IFERROR('Raw FS'!L24,0) -> 1970
B32: ='Raw FS'!B25 -> Vehicles | E32: =IFERROR('Raw FS'!H25,0) -> 845 | F32: =IFERROR('Raw FS'!I25,0) -> 725 | G32: =IFERROR('Raw FS'!J25,0) -> 788 | H32: =IFERROR('Raw FS'!K25,0) -> 956 | I32: =IFERROR('Raw FS'!L25,0) -> 1151
B33: ='Raw FS'!B26 -> Intangible Assets | E33: =IFERROR('Raw FS'!H26,0) -> 114809 | F33: =IFERROR('Raw FS'!I26,0) -> 114323 | G33: =IFERROR('Raw FS'!J26,0) -> 112538 | H33: =IFERROR('Raw FS'!K26,0) -> 116714 | I33: =IFERROR('Raw FS'!L26,0) -> 93455
B34: ='Raw FS'!B27 -> Other fixed assets | E34: =IFERROR('Raw FS'!H27,0) -> 10686 | F34: =IFERROR('Raw FS'!I27,0) -> 10870 | G34: =IFERROR('Raw FS'!J27,0) -> 11841 | H34: =IFERROR('Raw FS'!K27,0) -> 10657 | I34: =IFERROR('Raw FS'!L27,0) -> 11044
B35: Gross Block | E35: =SUM(E26:E34) -> 313692 | F35: =SUM(F26:F34) -> 324096 | G35: =SUM(G26:G34) -> 331141 | H35: =SUM(H26:H34) -> 334479 | I35: =SUM(I26:I34) -> 320000
B36: ='Raw FS'!B29 -> Accumulated Depreciation | E36: =-IFERROR('Raw FS'!H29,0) -> -174985 | F36: =-IFERROR('Raw FS'!I29,0) -> -185241 | G36: =-IFERROR('Raw FS'!J29,0) -> -199062 | H36: =-IFERROR('Raw FS'!K29,0) -> -213194 | I36: =-IFERROR('Raw FS'!L29,0) -> -204303
A37: x | B37: Net Non Current Assets | E37: =SUM(E35:E36) -> 138707 | F37: =SUM(F35:F36) -> 138855 | G37: =SUM(G35:G36) -> 132079 | H37: =SUM(H35:H36) -> 121285 | I37: =SUM(I35:I36) -> 115697
A39: x | B39: Invested Capital | E39: =E37+E23 -> 106574 | F39: =F37+F23 -> 114981 | G39: =G37+G23 -> 109042 | H39: =H37+H23 -> 95882 | I39: =I37+I23 -> 51998
B40: EBIT | E40: ='Historical FS'!H33+'Historical FS'!H27 -> 8740.72 | F40: ='Historical FS'!I33+'Historical FS'!I27 -> -115.6 | G40: ='Historical FS'!J33+'Historical FS'!J27 -> 6955.44 | H40: ='Historical FS'!K33+'Historical FS'!K27 -> 30585 | I40: ='Historical FS'!L33+'Historical FS'!L27 -> 31960
A42: x | B42: ROIC | E42: =E40/E39 -> 0.082015501 | F42: =F40/F39 -> -0.0010053835 | G42: =G40/G39 -> 0.063786798 | H42: =H40/H39 -> 0.31898584 | I42: =I40/I39 -> 0.61463902
B45: Calculation of Reinvestment Rate | E45: =E$8 -> 44256 | F45: =F$8 -> 44621 | G45: =G$8 -> 44986 | H45: =H$8 -> 45352 | I45: =I$8 -> 45717
B47: Net Capex | E47: =-IFERROR(SUM('Raw FS'!H55:H56),0) -> 19854 | F47: =-IFERROR(SUM('Raw FS'!I55:I56),0) -> 14938 | G47: =-IFERROR(SUM('Raw FS'!J55:J56),0) -> 18945 | H47: =-IFERROR(SUM('Raw FS'!K55:K56),0) -> 31183 | I47: =-IFERROR(SUM('Raw FS'!L55:L56),0) -> 37068
B48: Change in Working Capital | F48: =F23-E23 -> 8259 | G48: =G23-F23 -> 837 | H48: =H23-G23 -> -2366 | I48: =I23-H23 -> -38296
B50: EBIT | E50: =E40 -> 8740.72 | F50: =F40 -> -115.6 | G50: =G40 -> 6955.44 | H50: =H40 -> 30585 | I50: =I40 -> 31960
B51: Marginal Tax Rate | E51: 0.25 | F51: 0.25 | G51: 0.25 | H51: 0.25 | I51: 0.25
B52: EBIT(1-Tax) | E52: =E50*(1-E51) -> 6555.54 | F52: =F50*(1-F51) -> -86.7 | G52: =G50*(1-G51) -> 5216.58 | H52: =H50*(1-H51) -> 22938.75 | I52: =I50*(1-I51) -> 23970
B54: Reinvestment | F54: =SUM(F47:F48) -> 23197 | G54: =SUM(G47:G48) -> 19782 | H54: =SUM(H47:H48) -> 28817 | I54: =SUM(I47:I48) -> -1228
B56: Reinvestment Rate | F56: =F54/F52 -> -267.55479 | G56: =G54/G52 -> 3.7921397 | H56: =H54/H52 -> 1.2562585 | I56: =I54/I52 -> -0.051230705
H58: 4 Year Average | I58: =AVERAGE(F56:I56) -> -65.639405
H59: 4 Year Median | I59: =MEDIAN(F56:I56) -> 0.6025139
B61: Calculation of Growth Rate | E61: ='Raw FS'!H$2 -> 44256 | F61: ='Raw FS'!I$2 -> 44621 | G61: ='Raw FS'!J$2 -> 44986 | H61: ='Raw FS'!K$2 -> 45352 | I61: ='Raw FS'!L$2 -> 45717
B63: =B56 -> Reinvestment Rate | F63: =F56 -> -267.55479 | G63: =G56 -> 3.7921397 | H63: =H56 -> 1.2562585 | I63: =I56 -> -0.051230705
B64: ROIC | F64: =F42 -> -0.0010053835 | G64: =G42 -> 0.063786798 | H64: =H42 -> 0.31898584 | I64: =I42 -> 0.61463902
B66: Intrinsic Growth | F66: =F63*F64 -> 0.26899517 | G66: =G63*G64 -> 0.24188845 | H66: =H63*H64 -> 0.40072867 | I66: =I63*I64 -> -0.031488391
H68: 4 Year Average | I68: =AVERAGE(F66:I66) -> 0.22003097
H69: 4 Year Median | I69: =MEDIAN(F66:I66) -> 0.25544181

Sheet WACC
B3: TATA MOTORS LTD
B4: ( TATA MOTORS LTD | BSE Code : 500570 )
B5: INR 716.00 (as on 05.10.2025)
B6: 52 Week ( High - INR 948.45 & Low - 535.75)
B9: Weighted Average Cost of Capital
B11: All figures are in INR unless stated otherwise.
B13: Peer Comps
G14: Debt/ | H14: Debt/ | I14: Levered | J14: Unlevered
B15: Name | C15: Country | D15: Total Debt | E15: Total Equity | F15: Tax Rate 1 | G15: Equity | H15: Capital | I15: Beta 2 | J15: Beta 3
B16: ='Beta - Comps'!C8 -> Maruti Suzuki | C16: India | D16: ='Beta - Comps'!G8 -> 87 | E16: ='Beta - Comps'!E8 -> 496944.71 | F16: 0.3 | G16: =D16/E16 -> 0.00017506978 | H16: =D16/(D16+E16) -> 0.00017503913 | I16: ='Maruti Suzuki'!J11 -> 0.74366658 | J16: =I16/(1+(1-F16)*G16) -> 0.74357546
B17: ='Beta - Comps'!C9 -> M & M | C17: India | D17: ='Beta - Comps'!G9 -> 129024.58 | E17: ='Beta - Comps'!E9 -> 430509.68 | F17: 0.3 | G17: =D17/E17 -> 0.29970193 | H17: =D17/(D17+E17) -> 0.23059281 | I17: =TAMO!J12 -> 1.3913567 | J17: =I17/(1+(1-F17)*G17) -> 1.1500799
B18: ='Beta - Comps'!C10 -> Tata Motors | C18: India | D18: ='Beta - Comps'!G10 -> 71540 | E18: ='Beta - Comps'!E10 -> 263687.69 | F18: 0.3 | G18: =D18/E18 -> 0.2713058 | H18: =D18/(D18+E18) -> 0.21340719 | I18: =Mahindra!J11 -> 1.7587691 | J18: =I18/(1+(1-F18)*G18) -> 1.478064
B19: ='Beta - Comps'!C11 -> Bajaj Auto | C19: India | D19: ='Beta - Comps'!G11 -> 9364.16 | E19: ='Beta - Comps'!E11 -> 242381.64 | F19: 0.3 | G19: =D19/E19 -> 0.038633949 | H19: =D19/(D19+E19) -> 0.037196887 | I19: ='Bajaj Auto'!J11 -> 1.1030738 | J19: =I19/(1+(1-F19)*G19) -> 1.0740281
B20: ='Beta - Comps'!C12 -> Eicher Motors | C20: India | D20: ='Beta - Comps'!G12 -> 458.13 | E20: ='Beta - Comps'!E12 -> 190376.35 | F20: 0.3 | G20: =D20/E20 -> 0.0024064439 | H20: =D20/(D20+E20) -> 0.0024006668 | I20: ='Eicher Motors'!J11 -> 1.0732584 | J20: =I20/(1+(1-F20)*G20) -> 1.0714535
E23: Average | F23: =AVERAGE(F16:F20) -> 0.3 | G23: =AVERAGE(G16:G20) -> 0.12244464 | H23: =AVERAGE(H16:H20) -> 0.09675452 | I23: =AVERAGE(I16:I20) -> 1.2140249 | J23: =AVERAGE(J16:J20) -> 1.1034402
E24: Median | F24: =MEDIAN(F16:F20) -> 0.3 | G24: =MEDIAN(G16:G20) -> 0.038633949 | H24: =MEDIAN(H16:H20) -> 0.037196887 | I24: =MEDIAN(I16:I20) -> 1.1030738 | J24: =MEDIAN(J16:J20) -> 1.0740281
B27: Cost of Debt | G27: Cost of Equity
B29: Pre-tax Cost of Debt | E29: ='Data Sheet'!K27/D18 -> 0.07105116 | G29: Risk Free Rate - 10Y Bond Yield | J29: 0.06515
B30: After Tax Cost of Debt | E30: =F16 -> 0.3 | G30: Equity Risk Premium | J30: =ERP!F12-WACC!J29 -> 0.10474167
B31: After Tax Cost of Debt | E31: =E29*(1-E30) -> 0.049735812 | G31: Levered Beta 4 | J31: =J40 -> 0.99911156
G32: Cost of Equity | J32: =J29+(J30)*J31 -> 0.16979861
B35: Capital Structure | G35: Levered Beta
D37: Current | E37: Target | G37: Comps Median Unlevered Beta | J37: =J24 -> 1.0740281
B38: Total Debt | C38: =D18 -> 71540 | D38: =C38/C40 -> 0.21340719 | E38: =H23 -> 0.09675452 | G38: Target Debt/ Equity | J38: =E42 -> 0.10711874
B39: Market Capitalization | C39: =E18 -> 263687.69 | D39: =C39/C40 -> 0.78659281 | E39: =E40-E38 -> 0.90324548 | G39: Tax Rate | J39: =E30 -> 0.3
B40: Total Capitalization | C40: =SUM(C38:C39) -> 335227.69 | D40: =SUM(D38:D39) -> 1 | E40: =D40 -> 1 | G40: Levered Beta | J40: =J37/(1+(1-J39)*J38) -> 0.99911156
B42: Debt / Equity | D42: =D38/D39 -> 0.2713058 | E42: =E38/E39 -> 0.10711874 | G42: Weighted Average Cost of Capital
G44: Cost of Equity | J44: =J32 -> 0.16979861
G45: Equity Weight | J45: =E39 -> 0.90324548
B47: 1. Tax Rate considered as Marginal Tax Rate for the country | G47: Cost of Debt | J47: =E31 -> 0.049735812
B48: 2. Levered Beta is based on 5 year monthly data | G48: Debt Weight | J48: =E38 -> 0.09675452
B49: 3. Unlevered Beta = Levered Beta/(1+(1-Tax Rate) x Debt/Equity)
B50: 3. Levered Beta = Unlevered Beta/(1+(1-Tax Rate) x Debt/Equity) | G50: WACC | J50: =(J44*J45)+(J47*J48) -> 0.15818199

Sheet DCF
B2: TATA MOTORS LTD
B3: ( TATA MOTORS LTD | BSE Code : 500570 )
B4: INR 716.00 (as on 05.10.2025)
B5: 52 Week ( High - INR 948.45 & Low - 535.75)
B8: Calculation of PV of FCFF | F8: ='[5]Intrinsic Growth'!K2 -> 45352 | G8: =F8+365 -> 45717 | H8: =G8+365 -> 46082 | I8: =H8+365 -> 46447 | J8: =I8+366 -> 46813 | K8: =J8+365 -> 47178
B10: EBIT | F10: ='Intrinsic Growth'!I40 -> 31960 | G10: =F10*(1+$D$21) -> 35648.852 | H10: =G10*(1+$D$21) -> 39763.474 | I10: =H10*(1+$D$21) -> 44353.01 | J10: =I10*(1+$D$21) -> 49472.274 | K10: =J10*(1+$D$21) -> 55182.408
B11: Tax Rate | F11: ='Intrinsic Growth'!I51 -> 0.25 | G11: =F11 -> 0.25 | H11: =G11 -> 0.25 | I11: =H11 -> 0.25 | J11: =I11 -> 0.25 | K11: =J11 -> 0.25
B12: EBIT*(1-Tax Rate) | F12: =F10*(1-F11) -> 23970 | G12: =G10*(1-G11) -> 26736.639 | H12: =H10*(1-H11) -> 29822.606 | I12: =I10*(1-I11) -> 33264.757 | J12: =J10*(1-J11) -> 37104.205 | K12: =K10*(1-K11) -> 41386.806
B13: Less:Reinvestment Rate | F13: =+'Intrinsic Growth'!I59 -> 0.6025139 | G13: =F13+(($K$13-$F$13)/4) -> 0.51577092 | H13: =G13+(($K$13-$F$13)/4) -> 0.42902793 | I13: =H13+(($K$13-$F$13)/4) -> 0.34228494 | J13: =I13+(($K$13-$F$13)/4) -> 0.25554195 | K13: =[6]Sheet1!$L$75 -> 0.25554195
B14: Free Cash Flow to Firm | F14: =F12*(1-F13) -> 9527.7417 | G14: =G12*(1-G13) -> 12946.658 | H14: =H12*(1-H13) -> 17027.875 | I14: =I12*(1-I13) -> 21878.732 | J14: =J12*(1-J13) -> 27622.524 | K14: =K12*(1-K13) -> 30810.741
B15: Mid year Convention | G15: 0.5 | H15: =G15+1 -> 1.5 | I15: =H15+1 -> 2.5 | J15: =I15+1 -> 3.5 | K15: =J15+1 -> 4.5
B16: Discounting factor | G16: =1/(1+$D$23)^G15 -> 0.92920512 | H16: =1/(1+$D$23)^H15 -> 0.8022963 | I16: =1/(1+$D$23)^I15 -> 0.6927204 | J16: =1/(1+$D$23)^J15 -> 0.59811015 | K16: =1/(1+$D$23)^K15 -> 0.51642156
B18: PV of FCFF | G18: =G14*G16 -> 12030.101 | H18: =H14*H16 -> 13661.401 | I18: =I14*I16 -> 15155.844 | J18: =J14*J16 -> 16521.312 | K18: =K14*K16 -> 15911.331
B21: Expected Growth | D21: =[6]Sheet1!$M$75 -> 0.11542089 | F21: Sensitivity Table (Implied Share Price)
B22: Terminal Growth | D22: 0.084
B23: WACC | D23: =WACC!J50 -> 0.15818199 | H23: WACC
G24: =D44 -> 789.89803 | H24: =I24-0.5% -> 0.14818199 | I24: =J24-0.5% -> 0.15318199 | J24: =D23 -> 0.15818199 | K24: =J24+0.5% -> 0.16318199 | L24: =K24+0.5% -> 0.16818199
B25: Calculation of Terminal Value | F25: Growth Rate | G25: =G26-0.5% -> 0.074 | H25: 789.89803 | I25: 748.87061 | J25: 712.71685 | K25: 680.61701 | L25: -928.04069
G26: =G27-0.5% -> 0.079 | H26: 836.85581 | I26: 789.89803 | J26: 748.87061 | K26: 712.71685 | L26: -1007.8314
B27: FCFF(n+1) | D27: =K14*(1+D21) -> 34366.944 | G27: =D22 -> 0.084 | H27: 891.12993 | I27: 836.85581 | J27: 789.89803 | K27: 748.87061 | L27: -1103.0928
B28: WACC | D28: =D23 -> 0.15818199 | G28: =G27+0.5% -> 0.089 | H28: 954.57478 | I28: 891.12993 | J28: 836.85581 | K28: 789.89803 | L28: -1218.8073
B29: Terminal Growth Rate | D29: =D22 -> 0.084 | G29: =G28+0.5% -> 0.094 | H29: 1029.7292 | I29: 954.57478 | J29: 891.12993 | K29: 836.85581 | L29: -1362.3542
E30: `
B31: Terminal Value | D31: =D27/(D28-D29) -> 463278.8
B33: Calculation of Equity Value per Share | F33: Sensitivity Table (Value of Operations)
B35: PV of FCFF | D35: =SUM(G18:K18) -> 73279.989 | H35: WACC
B36: Terminal Value | D36: =D31*K16 -> 239247.16 | G36: =D37 -> 312527.15 | H36: =I36-0.5% -> 0.14818199 | I36: =J36-0.5% -> 0.15318199 | J36: =D23 -> 0.15818199 | K36: =J36+0.5% -> 0.16318199
B37: Value of Operating Assets | D37: =SUM(D35:D36) -> 312527.15 | F37: Growth Rate | G37: =G38-0.5% -> 0.074 | H37: 312527.15 | I37: 297419.73 | J37: 284106.92 | K37: 272286.88
G38: =G39-0.5% -> 0.079 | H38: 329818.29 | I38: 312527.15 | J38: 297419.73 | K38: 284106.92
B39: Add:Cash | D39: ='Data Sheet'!K71 -> 40834 | G39: =D22 -> 0.084 | H39: 349803.52 | I39: 329818.29 | J39: 312527.15 | K39: 297419.73
B40: Less:Debt | D40: =SUM('Raw FS'!L7:L8) -> 62499 | G40: =G39+0.5% -> 0.089 | H40: 373165.65 | I40: 349803.52 | J40: 329818.29 | K40: 312527.15
B41: Value of Equity | D41: =D37+D39-D40 -> 290862.15 | G41: =G40+0.5% -> 0.094 | H41: 400839.58 | I41: 373165.65 | J41: 349803.52 | K41: 329818.29
B42: No. of shares | D42: ='Data Sheet'!B6 -> 368.22747
B44: Equity Value per Share | D44: =D41/D42 -> 789.89803
B46: Share Price | D46: 716
B47: Discount/Premium | D47: =D46/D44 -> 0.90644612

Sheet Comp_Val
B3: TATA MOTORS LTD
B4: ( TATA MOTORS LTD | BSE Code : 500570 )
B5: INR 716.00 (as on 05.10.2025)
B6: 52 Week ( High - INR 948.45 & Low - 535.75)
B9: Comparable Company valuation (Amount in Crores)
D11: Market Data | K11: Financials | O11: Valuation
B12: Company | C12: Ticker | D12: Share Price | E12: Shares Outstanding | F12: Equity Value | G12: Net Debt | H12: Enterprize Value | K12: Revenue | L12: EBITDA | M12: Net Income | O12: EV/Revenue | P12: EV/EBITDA | Q12: P/E
B14: ='Data Comp Val'!C3 -> Tata Motors | D14: ='Data Comp Val'!D3 -> 716.1 | E14: ='Data Comp Val'!E3 -> 368.23 | F14: =E14*D14 -> 263689.5 | G14: ='Data Comp Val'!I3 -> 30706 | H14: ='Data Comp Val'!J3 -> 294393.69 | K14: ='Data Comp Val'!K3 -> 437968 | L14: ='Data Comp Val'!L3 -> 61315.52 | M14: ='Data Comp Val'!M3 -> 28149 | O14: =$H14/K14 -> 0.67218082 | P14: =$H14/L14 -> 4.8012916 | Q14: =F14/M14 -> 9.3676331
B15: ='Data Comp Val'!C4 -> Maruti Suzuki | D15: ='Data Comp Val'!D4 -> 15806 | E15: ='Data Comp Val'!E4 -> 31.44 | F15: =E15*D15 -> 496940.64 | G15: ='Data Comp Val'!I4 -> -465.9 | H15: ='Data Comp Val'!J4 -> 496478.81 | K15: ='Data Comp Val'!K4 -> 155738.8 | L15: ='Data Comp Val'!L4 -> 24918.208 | M15: ='Data Comp Val'!M4 -> 14500.2 | O15: =$H15/K15 -> 3.1878942 | P15: =$H15/L15 -> 19.924338 | Q15: =F15/M15 -> 34.271296
B16: ='Data Comp Val'!C5 -> M & M | D16: ='Data Comp Val'!D5 -> 3462 | E16: ='Data Comp Val'!E5 -> 124.35 | F16: =E16*D16 -> 430499.7 | G16: ='Data Comp Val'!I5 -> 108409.74 | H16: ='Data Comp Val'!J5 -> 538919.42 | K16: ='Data Comp Val'!K5 -> 167522.29 | L16: ='Data Comp Val'!L5 -> 33504.458 | M16: ='Data Comp Val'!M5 -> 14073.17 | O16: =$H16/K16 -> 3.2170013 | P16: =$H16/L16 -> 16.085006 | Q16: =F16/M16 -> 30.590102
B17: ='Data Comp Val'!C6 -> Bajaj Auto | D17: ='Data Comp Val'!D6 -> 8679.5 | E17: ='Data Comp Val'!E6 -> 27.93 | F17: =E17*D17 -> 242418.43 | G17: ='Data Comp Val'!I6 -> 6516.56 | H17: ='Data Comp Val'!J6 -> 248898.2 | K17: ='Data Comp Val'!K6 -> 52195.83 | L17: ='Data Comp Val'!L6 -> 10961.124 | M17: ='Data Comp Val'!M6 -> 7324.73 | O17: =$H17/K17 -> 4.7685457 | P17: =$H17/L17 -> 22.70736 | Q17: =F17/M17 -> 33.095887
B18: ='Data Comp Val'!C7 -> Hyundai Motor | D18: ='Data Comp Val'!D7 -> 2507.6 | E18: ='Data Comp Val'!E7 -> 81.25 | F18: =E18*D18 -> 203742.5 | G18: ='Data Comp Val'!I7 -> -7288.06 | H18: ='Data Comp Val'!J7 -> 196464.75 | K18: ='Data Comp Val'!K7 -> 66704.55 | L18: ='Data Comp Val'!L7 -> 9338.637 | M18: ='Data Comp Val'!M7 -> 5492.25 | O18: =$H18/K18 -> 2.9452976 | P18: =$H18/L18 -> 21.03784 | Q18: =F18/M18 -> 37.096363
B19: ='Data Comp Val'!C8 -> Eicher Motors | D19: ='Data Comp Val'!D8 -> 6941 | E19: ='Data Comp Val'!E8 -> 27.43 | F19: =E19*D19 -> 190391.63 | G19: ='Data Comp Val'!I8 -> 195.12 | H19: ='Data Comp Val'!J8 -> 190571.47 | K19: ='Data Comp Val'!K8 -> 19519.14 | L19: ='Data Comp Val'!L8 -> 6636.5076 | M19: ='Data Comp Val'!M8 -> 4734.44 | O19: =$H19/K19 -> 9.7633128 | P19: =$H19/L19 -> 28.715626 | Q19: =F19/M19 -> 40.214182
B20: ='Data Comp Val'!C9 -> TVS Motor Co. | D20: ='Data Comp Val'!D9 -> 3456.1 | E20: ='Data Comp Val'!E9 -> 47.51 | F20: =E20*D20 -> 164199.31 | G20: ='Data Comp Val'!I9 -> 24222.47 | H20: ='Data Comp Val'!J9 -> 188417.33 | K20: ='Data Comp Val'!K9 -> 46088.61 | L20: ='Data Comp Val'!L9 -> 6452.4054 | M20: ='Data Comp Val'!M9 -> 2379.81 | O20: =$H20/K20 -> 4.0881539 | P20: =$H20/L20 -> 29.201099 | Q20: =F20/M20 -> 68.996815
B21: ='Data Comp Val'!C10 -> Bosch | D21: ='Data Comp Val'!D10 -> 38630 | E21: ='Data Comp Val'!E10 -> 2.95 | F21: =E21*D21 -> 113958.5 | G21: ='Data Comp Val'!I10 -> -389.4 | H21: ='Data Comp Val'!J10 -> 113544.53 | K21: ='Data Comp Val'!K10 -> 18559.2 | L21: ='Data Comp Val'!L10 -> 3155.064 | M21: ='Data Comp Val'!M10 -> 2013.3 | O21: =$H21/K21 -> 6.1179647 | P21: =$H21/L21 -> 35.988028 | Q21: =F21/M21 -> 56.602841
B22: ='Data Comp Val'!C11 -> Samvardh. Mothe. | D22: ='Data Comp Val'!D11 -> 106.67 | E22: ='Data Comp Val'!E11 -> 1055.44 | F22: =E22*D22 -> 112583.78 | G22: ='Data Comp Val'!I11 -> 10932.9 | H22: ='Data Comp Val'!J11 -> 123517.14 | K22: ='Data Comp Val'!K11 -> 115006.61 | L22: ='Data Comp Val'!L11 -> 11500.661 | M22: ='Data Comp Val'!M11 -> 4145.7 | O22: =$H22/K22 -> 1.0740004 | P22: =$H22/L22 -> 10.740004 | Q22: =F22/M22 -> 27.156761
B23: ='Data Comp Val'!C12 -> Hero Motocorp | D23: ='Data Comp Val'!D12 -> 5550.5 | E23: ='Data Comp Val'!E12 -> 20.01 | F23: =E23*D23 -> 111065.51 | G23: ='Data Comp Val'!I12 -> 125.85 | H23: ='Data Comp Val'!J12 -> 111173.52 | K23: ='Data Comp Val'!K12 -> 40440.38 | L23: ='Data Comp Val'!L12 -> 6470.4608 | M23: ='Data Comp Val'!M12 -> 4375.81 | O23: =$H23/K23 -> 2.7490721 | P23: =$H23/L23 -> 17.181701 | Q23: =F23/M23 -> 25.381702
B25: High | O25: =MAX(O14:O23) -> 9.7633128 | P25: =MAX(P14:P23) -> 35.988028 | Q25: =MAX(Q14:Q23) -> 68.996815
B26: 75th Percentile | O26: =QUARTILE(O14:O23,3) -> 4.5984477 | P26: =QUARTILE(P14:P23,3) -> 27.21356 | Q26: =QUARTILE(Q14:Q23,3) -> 39.434727
B27: Average | O27: =AVERAGE(O14:O23) -> 3.8583423 | P27: =AVERAGE(P14:P23) -> 20.638229 | Q27: =AVERAGE(Q14:Q23) -> 36.277358
B28: Median | O28: =MEDIAN(O14:O23) -> 3.2024477 | P28: =MEDIAN(P14:P23) -> 20.481089 | Q28: =MEDIAN(Q14:Q23) -> 33.683591
B29: 25th Percentile | O29: =QUARTILE(O14:O23,) -> 0.67218082 | P29: =QUARTILE(P14:P23,) -> 4.8012916 | Q29: =QUARTILE(Q14:Q23,) -> 9.3676331
B30: Low | O30: =MIN(O14:O23) -> 0.67218082 | P30: =MIN(P14:P23) -> 4.8012916 | Q30: =MIN(Q14:Q23) -> 9.3676331
B32: Tata Motors Comparable Valuation | O32: EV/Revenue | P32: EV/EBITDA | Q32: P/E
B34: Implied Enterprize Vale | O34: =O$28*K14 -> 1402569.6 | P34: =P$28*L14 -> 1255808.6 | Q34: =Q36+Q35 -> 978865.41
B35: Net Debt | O35: =G14 -> 30706 | P35: =O35 -> 30706 | Q35: =P35 -> 30706
B36: Implied market Value | O36: =O34-O35 -> 1371863.6 | P36: =P34-P35 -> 1225102.6 | Q36: =Q28*M14 -> 948159.41
B37: Shares Outstanding | O37: =E14 -> 368.23 | P37: =O37 -> 368.23 | Q37: =P37 -> 368.23
B39: Implied Value per Share | O39: =O36/O37 -> 3725.5618 | P39: =P36/P37 -> 3327.0039 | Q39: =Q36/Q37 -> 2574.9108
B41: Weight % | O41: 0.2 | P41: 0.5 | Q41: 0.3
B42: Weighted Value | O42: =O39*O41 -> 745.11236 | P42: =P39*P41 -> 1663.5019 | Q42: =Q39*Q41 -> 772.47324
B44: Business Enterprise Value | Q44: =SUM(O42:Q42) -> 3181.0875
Q45: Undervalued

Sheet Football Field
B3: TATA MOTORS LTD
B4: ( TATA MOTORS LTD | BSE Code : 500570 )
B5: INR 716.00 (as on 05.10.2025)
B6: 52 Week ( High - INR 948.45 & Low - 535.75)
L9: Football Field Analysis
N10: Open Low | O10: Low | P10: Open High | Q10: High
L11: CMP | N11: 715 | O11: =N11 -> 715 | P11: 739.7 | Q11: =P11 -> 739.7
L12: DCF Bear | N12: =DCF!K25 -> 680.61701 | O12: =N12 -> 680.61701 | P12: =DCF!K29 -> 836.85581 | Q12: =P12 -> 836.85581
L13: DCF Base | N13: =DCF!J25 -> 712.71685 | O13: =N13 -> 712.71685 | P13: =DCF!J29 -> 891.12993 | Q13: =P13 -> 891.12993
L14: DCF Bull | N14: =DCF!H25 -> 789.89803 | O14: =N14 -> 789.89803 | P14: =Q14 -> 1029.7292 | Q14: =DCF!H29 -> 1029.7292
L15: 52W H/L | N15: 535.75 | O15: =N15 -> 535.75 | P15: 948.45 | Q15: =P15 -> 948.45

Sheet Monte Carlo Simulation
B2: TATA MOTORS LTD
B3: ( TATA MOTORS LTD | BSE Code : 500570 )
B4: INR 716.00 (as on 05.10.2025)
B5: 52 Week ( High - INR 948.45 & Low - 535.75)
A8: x | B8: Date (1994 - 2025) | C8: Adj Close | D8: Return | E8: Sorted Returns | G8: Replication | H8: Simulated Returns | J8: Calculation of Value at Risk - Tata Motors (Simulation)
B9: 37753 | C9: 30.21 | D9: =C9/C10-1 -> -0.19867374 | E9: 2.146875 | G9: 1 | H9: =_xlfn.NORM.INV(RAND(),N$11,N$12) -> 0.073575932
B10: 37790 | C10: 37.7 | D10: =C10/C11-1 -> 0.070414537 | E10: 1.815534 | G10: 2 | H10: =_xlfn.NORM.INV(RAND(),N$11,N$12) -> 0.069035027 | J10: Historical Approach
B11: 37788 | C11: 35.22 | D11: =C11/C12-1 -> -0.059294872 | E11: 1.7387247 | G11: 3 | H11: =_xlfn.NORM.INV(RAND(),N$11,N$12) -> 0.091700894 | J11: Mean | N11: =AVERAGE(E9:E8492) -> 0.001662863
B12: 37798 | C12: 37.44 | D12: =C12/C13-1 -> 0.0026780932 | E12: 1.6819484 | G12: 4 | H12: =_xlfn.NORM.INV(RAND(),N$11,N$12) -> 0.023898337 | J12: STD Devation | N12: =_xlfn.STDEV.S(E9:E8492) -> 0.061125679
B13: 37792 | C13: 37.34 | D13: =C13/C14-1 -> -0.078707131 | E13: 1.6444759 | G13: 5 | H13: =_xlfn.NORM.INV(RAND(),N$11,N$12) -> 0.016707043 | J13: Min | N13: =MIN(E9:E8492) -> -0.68306372
B14: 37809 | C14: 40.53 | D14: =C14/C15-1 -> -0.0193564 | E14: 1.4313137 | G14: 6 | H14: =_xlfn.NORM.INV(RAND(),N$11,N$12) -> 0.059366589 | J14: Max | N14: =MAX(E9:E8492) -> 2.146875
B15: 37823 | C15: 41.33 | D15: =C15/C16-1 -> -0.67971172 | E15: 1.0623752 | G15: 7 | H15: =_xlfn.NORM.INV(RAND(),N$11,N$12) -> -0.039269352 | J15: CPM | N15: ='Historical Approach (VAR)'!K15 -> 716
B16: 34976 | C16: 129.04 | D16: =C16/C17-1 -> -0.74543302 | E16: 0.60218525 | G16: 8 | H16: =_xlfn.NORM.INV(RAND(),N$11,N$12) -> -0.021493329
B17: 44482 | C17: 506.9 | D17: =C17/C18-1 -> 4.4359249 | E17: 0.20446715 | G17: 9 | H17: =_xlfn.NORM.INV(RAND(),N$11,N$12) -> -0.095341707 | J17: Monte Carlo Simulation
B18: 43951 | C18: 93.25 | D18: =C18/C19-1 -> 0.29730106 | E18: 0.19321817 | G18: 10 | H18: =_xlfn.NORM.INV(RAND(),N$11,N$12) -> -0.030975072 | J18: Mean | N18: =AVERAGE(H9:H10008) -> 0.0010342462
B19: 39953 | C19: 71.88 | D19: =C19/C20-1 -> -0.58318353 | E19: 0.18829559 | G19: 11 | H19: =_xlfn.NORM.INV(RAND(),N$11,N$12) -> 0.14602141 | J19: STD Devation | N19: =_xlfn.STDEV.S(H9:H10008) -> 0.061201089
B20: 43767 | C20: 172.45 | D20: =C20/C21-1 -> 0.1675694 | E20: 0.1675694 | G20: 12 | H20: =_xlfn.NORM.INV(RAND(),N$11,N$12) -> 0.044988525 | J20: Min | N20: =MIN(H9:H10008) -> -0.21955902
B21: 43765 | C21: 147.7 | D21: =C21/C22-1 -> -0.54130435 | E21: 0.16436736 | G21: 13 | H21: =_xlfn.NORM.INV(RAND(),N$11,N$12) -> 0.0057374383 | J21: Max | N21: =MAX(H8:H10007) -> 0.21873828
B22: 44229 | C22: 322 | D22: =C22/C23-1 -> 4.4008722 | E22: 0.15164521 | G22: 14 | H22: =_xlfn.NORM.INV(RAND(),N$11,N$12) -> -0.045515942 | J22: CPM | N22: 1095
B23: 39951 | C23: 59.62 | D23: =C23/C24-1 -> 0.99598259 | E23: 0.1358354 | G23: 15 | H23: =_xlfn.NORM.INV(RAND(),N$11,N$12) -> -0.097910966
B24: 39786 | C24: 29.87 | D24: =C24/C25-1 -> -0.25880893 | E24: 0.13272658 | G24: 16 | H24: =_xlfn.NORM.INV(RAND(),N$11,N$12) -> 0.040153899 | J24: Percentile | K24: Confidence | L24: VAR % | M24: Stock Price | N24: VAR (INR)
B25: 39905 | C25: 40.3 | D25: =C25/C26-1 -> -0.63611738 | E25: 0.13138686 | G25: 17 | H25: =_xlfn.NORM.INV(RAND(),N$11,N$12) -> -0.0066343619 | J25: 0.05 | K25: =100%-J25 -> 0.95 | L25: =_xlfn.PERCENTILE.INC($H$9:$H$10008,J25) -> -0.097756021 | M25: =$N$15*(1+L25) -> 646.00669 | N25: =$N$15-M25 -> 69.993311
B26: 43987 | C26: 110.75 | D26: =C26/C27-1 -> 1.9384452 | E26: 0.12436548 | G26: 18 | H26: =_xlfn.NORM.INV(RAND(),N$11,N$12) -> 0.1276187 | J26: 0.01 | K26: =100%-J26 -> 0.99 | L26: =_xlfn.PERCENTILE.INC($H$9:$H$10008,J26) -> -0.14221509 | M26: =$N$15*(1+L26) -> 614.174 | N26: =$N$15-M26 -> 101.826
B27: 39755 | C27: 37.69 | D27: =C27/C28-1 -> -0.76133485 | E27: 0.12339791 | G27: 19 | H27: =_xlfn.NORM.INV(RAND(),N$11,N$12) -> 0.028483696 | J27: 0.005 | K27: =100%-J27 -> 0.995 | L27: =_xlfn.PERCENTILE.INC($H$9:$H$10008,J27) -> -0.15634829 | M27: =$N$15*(1+L27) -> 604.05462 | N27: =$N$15-M27 -> 111.94538
B28: 40239 | C28: 157.92 | D28: =C28/C29-1 -> -0.58055777 | E28: 0.1221488 | G28: 20 | H28: =_xlfn.NORM.INV(RAND(),N$11,N$12) -> 0.10096101 | J28: 0.1 | K28: =100%-J28 -> 0.9 | L28: =_xlfn.PERCENTILE.INC($H$9:$H$10008,J28) -> -0.076634089 | M28: =$N$15*(1+L28) -> 661.12999 | N28: =$N$15-M28 -> 54.870008
B29: 44476 | C29: 376.5 | D29: =C29/C30-1 -> 21.721786 | E29: 0.12036899 | G29: 21 | H29: =_xlfn.NORM.INV(RAND(),N$11,N$12) -> -0.093902559
B30: 36833 | C30: 16.57 | D30: =C30/C31-1 -> -0.70251346 | E30: 0.11808367 | G30: 22 | H30: =_xlfn.NORM.INV(RAND(),N$11,N$12) -> -0.067230525
B31: 39918 | C31: 55.7 | D31: =C31/C32-1 -> -0.74756402 | E31: 0.1164562 | G31: 23 | H31: =_xlfn.NORM.INV(RAND(),N$11,N$12) -> 0.025150678
B32: 44207 | C32: 220.65 | D32: =C32/C33-1 -> 0.97008929 | E32: 0.11355034 | G32: 24 | H32: =_xlfn.NORM.INV(RAND(),N$11,N$12) -> 0.023123804
B33: 40063 | C33: 112 | D33: =C33/C34-1 -> 1.2449389 | E33: 0.11354146 | G33: 25 | H33: =_xlfn.NORM.INV(RAND(),N$11,N$12) -> -0.088849922
B34: 39916 | C34: 49.89 | D34: =C34/C35-1 -> -0.7284898 | E34: 0.11163102 | G34: 26 | H34: =_xlfn.NORM.INV(RAND(),N$11,N$12) -> 0.11770138
B35: 43866 | C35: 183.75 | D35: =C35/C36-1 -> 0.3172043 | E35: 0.1089318 | G35: 27 | H35: =_xlfn.NORM.INV(RAND(),N$11,N$12) -> 0.022451178
B36: 43755 | C36: 139.5 | D36: =C36/C37-1 -> 8.4002695 | E36: 0.10846246 | G36: 28 | H36: =_xlfn.NORM.INV(RAND(),N$11,N$12) -> -0.02501233
B37: 37096 | C37: 14.84 | D37: =C37/C38-1 -> -0.81900232 | E37: 0.10828977 | G37: 29 | H37: =_xlfn.NORM.INV(RAND(),N$11,N$12) -> 0.021192504
B38: 40022 | C38: 81.99 | D38: =C38/C39-1 -> 1.5621875 | E38: 0.10752398 | G38: 30 | H38: =_xlfn.NORM.INV(RAND(),N$11,N$12) -> 0.079146221
B39: 39885 | C39: 32 | D39: =C39/C40-1 -> 0.072745558 | E39: 0.10726644 | G39: 31 | H39: =_xlfn.NORM.INV(RAND(),N$11,N$12) -> -0.071934173
B40: 37418 | C40: 29.83 | D40: =C40/C41-1 -> 1.0889356 | E40: 0.10645401 | G40: 32 | H40: =_xlfn.NORM.INV(RAND(),N$11,N$12) -> 0.045218422
... B7689: 37750 | C7689: 9.6 | D7689: =C7689/C7690-1 -> #DIV/0! | E7689: -0.68306372 | G7689: 7681 | H7689: =_xlfn.NORM.INV(RAND(),N$11,N$12) -> -0.052376817
G7690: 7682 | H7690: =_xlfn.NORM.INV(RAND(),N$11,N$12) -> 0.05761189
G7691: 7683 | H7691: =_xlfn.NORM.INV(RAND(),N$11,N$12) -> -0.10457966
G7692: 7684 | H7692: =_xlfn.NORM.INV(RAND(),N$11,N$12) -> -0.084640003
G7693: 7685 | H7693: =_xlfn.NORM.INV(RAND(),N$11,N$12) -> -0.02296694
G7694: 7686 | H7694: =_xlfn.NORM.INV(RAND(),N$11,N$12) -> -0.096149461
G7695: 7687 | H7695: =_xlfn.NORM.INV(RAND(),N$11,N$12) -> 0.10897229
G7696: 7688 | H7696: =_xlfn.NORM.INV(RAND(),N$11,N$12) -> -0.036729242
G7697: 7689 | H7697: =_xlfn.NORM.INV(RAND(),N$11,N$12) -> 0.084443102
G7698: 7690 | H7698: =_xlfn.NORM.INV(RAND(),N$11,N$12) -> 0.12049116
G7699: 7691 | H7699: =_xlfn.NORM.INV(RAND(),N$11,N$12) -> -0.087467106
G7700: 7692 | H7700: =_xlfn.NORM.INV(RAND(),N$11,N$12) -> 0.11838839
G7701: 7693 | H7701: =_xlfn.NORM.INV(RAND(),N$11,N$12) -> 0.096599239
... G10008: 10000 | H10008: =_xlfn.NORM.INV(RAND(),N$11,N$12) -> -0.082762406

Sheet Dupont Analysis
B2: TATA MOTORS LTD
B3: ( TATA MOTORS LTD | BSE Code : 500570 )
B4: INR 716.00 (as on 05.10.2025)
B5: 52 Week ( High - INR 948.45 & Low - 535.75)
B7: About the company
B8: Tata Motors Group is a leading global automobile manufacturer. Part of the illustrious multi-national conglomerate, the Tata group, it offers a wide and diverse portfolio of cars, sports utility vehicles, trucks, buses and defence vehicles to the world.It has operations in India, the UK, South Korea, South Africa, China, Brazil, Austria and Slovakia through a strong global network of subsidiaries, associate companies and Joint Ventures (JVs), including Jaguar Land Rover in the UK and Tata Daewoo in South Korea.
B13: Financial Summary
B64: Return on Equity (ROC)
C65: ='Historical FS'!F9 -> 43555 | D65: ='Historical FS'!G9 -> 43921 | E65: ='Historical FS'!H9 -> 44286 | F65: ='Historical FS'!I9 -> 44651 | G65: ='Historical FS'!J9 -> 45016 | H65: ='Historical FS'!K9 -> 45382 | I65: ='Historical FS'!L9 -> 45747
B66: Net Profit | C66: ='Data Sheet'!E30 -> -28826.23 | D66: ='Data Sheet'!F30 -> -12070.85 | E66: ='Data Sheet'!G30 -> -13451.39 | F66: ='Data Sheet'!H30 -> -11441.47 | G66: ='Data Sheet'!I30 -> 2414.29 | H66: ='Data Sheet'!J30 -> 31399 | I66: ='Data Sheet'!K30 -> 27830
B67: Average Shareholder Equity | C67: =(('Data Sheet'!E59+'Data Sheet'!E60)+('Data Sheet'!D59+'Data Sheet'!D60)/2) -> 107893.51 | D67: =(('Data Sheet'!F59+'Data Sheet'!F60)+('Data Sheet'!E59+'Data Sheet'!E60)/2) -> 93168.31 | E67: =(('Data Sheet'!G59+'Data Sheet'!G60)+('Data Sheet'!F59+'Data Sheet'!F60)/2) -> 86785.985 | F67: =(('Data Sheet'!H59+'Data Sheet'!H60)+('Data Sheet'!G59+'Data Sheet'!G60)/2) -> 72184.6 | G67: =(('Data Sheet'!I59+'Data Sheet'!I60)+('Data Sheet'!H59+'Data Sheet'!H60)/2) -> 67602.41 | H67: =(('Data Sheet'!J59+'Data Sheet'!J60)+('Data Sheet'!I59+'Data Sheet'!I60)/2) -> 107578.89 | I67: =(('Data Sheet'!K59+'Data Sheet'!K60)+('Data Sheet'!J59+'Data Sheet'!J60)/2) -> 158603
B68: Return on Equity | C68: =C66/C67 -> -0.26717296 | D68: =D66/D67 -> -0.12955961 | E68: =E66/E67 -> -0.15499496 | F68: =F66/F67 -> -0.15850292 | G68: =G66/G67 -> 0.035713076 | H68: =H66/H67 -> 0.29186952 | I68: =I66/I67 -> 0.17546957
B70: ROE - Dupont Equation
C71: =C65 -> 43555 | D71: =D65 -> 43921 | E71: =E65 -> 44286 | F71: =F65 -> 44651 | G71: =G65 -> 45016 | H71: =H65 -> 45382 | I71: =I65 -> 45747
B72: =B66 -> Net Profit | C72: =C66 -> -28826.23 | D72: =D66 -> -12070.85 | E72: =E66 -> -13451.39 | F72: =F66 -> -11441.47 | G72: =G66 -> 2414.29 | H72: =H66 -> 31399 | I72: =I66 -> 27830
B73: Revenues | C73: ='Data Sheet'!E44 -> 110577 | D73: ='Data Sheet'!F44 -> 119033 | E73: ='Data Sheet'!G44 -> 107102 | F73: ='Data Sheet'!H44 -> 101450 | G73: ='Data Sheet'!I44 -> 112608 | H73: ='Data Sheet'!J44 -> 119503 | I73: ='Data Sheet'!K44 -> 104407
B74: Net Profit Margin (A) | C74: =C72/C73 -> -0.2606892 | D74: =D72/D73 -> -0.10140759 | E74: =E72/E73 -> -0.1255942 | F74: =F72/F73 -> -0.1127794 | G74: =G72/G73 -> 0.021439773 | H74: =H72/H73 -> 0.26274654 | I74: =I72/I73 -> 0.26655301
B76: =B73 -> Revenues | C76: =C73 -> 110577 | D76: =D73 -> 119033 | E76: =E73 -> 107102 | F76: =F73 -> 101450 | G76: =G73 -> 112608 | H76: =H73 -> 119503 | I76: =I73 -> 104407
B77: Average Total Assets | C77: =('Data Sheet'!E68+'Data Sheet'!D68)/2 -> 316447.65 | D77: =('Data Sheet'!F68+'Data Sheet'!E68)/2 -> 312941.44 | E77: =('Data Sheet'!G68+'Data Sheet'!F68)/2 -> 330874.65 | F77: =('Data Sheet'!H68+'Data Sheet'!G68)/2 -> 335315.7 | G77: =('Data Sheet'!I68+'Data Sheet'!H68)/2 -> 331867.96 | H77: =('Data Sheet'!J68+'Data Sheet'!I68)/2 -> 352097.71 | I77: =('Data Sheet'!K68+'Data Sheet'!J68)/2 -> 373247
B78: Asset Turnover Ratio (B) | C78: =C76/C77 -> 0.3494322 | D78: =D76/D77 -> 0.38036829 | E78: =E76/E77 -> 0.32369358 | F78: =F76/F77 -> 0.3025507 | G78: =G76/G77 -> 0.33931567 | H78: =H76/H77 -> 0.33940294 | I78: =I76/I77 -> 0.27972629
B80: =B77 -> Average Total Assets | C80: =C77 -> 316447.65 | D80: =D77 -> 312941.44 | E80: =E77 -> 330874.65 | F80: =F77 -> 335315.7 | G80: =G77 -> 331867.96 | H80: =H77 -> 352097.71 | I80: =I77 -> 373247
B81: =B67 -> Average Shareholder Equity | C81: =C67 -> 107893.51 | D81: =D67 -> 93168.31 | E81: =E67 -> 86785.985 | F81: =F67 -> 72184.6 | G81: =G67 -> 67602.41 | H81: =H67 -> 107578.89 | I81: =I67 -> 158603
B82: Equity Multiplier (C) | C82: =C80/C81 -> 2.9329627 | D82: =D80/D81 -> 3.3588829 | E82: =E80/E81 -> 3.8125355 | F82: =F80/F81 -> 4.6452526 | G82: =G80/G81 -> 4.9091143 | H82: =H80/H81 -> 3.2729256 | I82: =I80/I81 -> 2.3533414
B84: Return on Equity (A*B*C) | C84: =C74*C78*C82 -> -0.26717296 | D84: =D74*D78*D82 -> -0.12955961 | E84: =E74*E78*E82 -> -0.15499496 | F84: =F74*F78*F82 -> -0.15850292 | G84: =G74*G78*G82 -> 0.035713076 | H84: =H74*H78*H82 -> 0.29186952 | I84: =I74*I78*I82 -> 0.17546957
B86: Return on Assets
C87: =C71 -> 43555 | D87: =D71 -> 43921 | E87: =E71 -> 44286 | F87: =F71 -> 44651 | G87: =G71 -> 45016 | H87: =H71 -> 45382 | I87: =I71 -> 45747
B88: Net Profit | C88: =C72 -> -28826.23 | D88: =D72 -> -12070.85 | E88: =E72 -> -13451.39 | F88: =F72 -> -11441.47 | G88: =G72 -> 2414.29 | H88: =H72 -> 31399 | I88: =I72 -> 27830
B89: =B80 -> Average Total Assets | C89: =C80 -> 316447.65 | D89: =D80 -> 312941.44 | E89: =E80 -> 330874.65 | F89: =F80 -> 335315.7 | G89: =G80 -> 331867.96 | H89: =H80 -> 352097.71 | I89: =I80 -> 373247
B90: Return on Assets | C90: =C88/C89 -> -0.091093203 | D90: =D88/D89 -> -0.038572233 | E90: =E88/E89 -> -0.040654036 | F90: =F88/F89 -> -0.034121486 | G90: =G88/G89 -> 0.0072748511 | H90: =H88/H89 -> 0.089176949 | I90: =I88/I89 -> 0.074561885
B92: ROA - Dupont Equation
C93: =C87 -> 43555 | D93: =D87 -> 43921 | E93: =E87 -> 44286 | F93: =F87 -> 44651 | G93: =G87 -> 45016 | H93: =H87 -> 45382 | I93: =I87 -> 45747
B94: =B88 -> Net Profit | C94: =C88 -> -28826.23 | D94: =D88 -> -12070.85 | E94: =E88 -> -13451.39 | F94: =F88 -> -11441.47 | G94: =G88 -> 2414.29 | H94: =H88 -> 31399 | I94: =I88 -> 27830
B95: Revenues | C95: =C73 -> 110577 | D95: =D73 -> 119033 | E95: =E73 -> 107102 | F95: =F73 -> 101450 | G95: =G73 -> 112608 | H95: =H73 -> 119503 | I95: =I73 -> 104407
B96: Net Profit Margin (A) | C96: =C94/C95 -> -0.2606892 | D96: =D94/D95 -> -0.10140759 | E96: =E94/E95 -> -0.1255942 | F96: =F94/F95 -> -0.1127794 | G96: =G94/G95 -> 0.021439773 | H96: =H94/H95 -> 0.26274654 | I96: =I94/I95 -> 0.26655301
B98: Revenues | C98: =C95 -> 110577 | D98: =D95 -> 119033 | E98: =E95 -> 107102 | F98: =F95 -> 101450 | G98: =G95 -> 112608 | H98: =H95 -> 119503 | I98: =I95 -> 104407
B99: Average Total Assets | C99: =C89 -> 316447.65 | D99: =D89 -> 312941.44 | E99: =E89 -> 330874.65 | F99: =F89 -> 335315.7 | G99: =G89 -> 331867.96 | H99: =H89 -> 352097.71 | I99: =I89 -> 373247
B100: Asset Turnover Ratio (B) | C100: =C98/C99 -> 0.3494322 | D100: =D98/D99 -> 0.38036829 | E100: =E98/E99 -> 0.32369358 | F100: =F98/F99 -> 0.3025507 | G100: =G98/G99 -> 0.33931567 | H100: =H98/H99 -> 0.33940294 | I100: =I98/I99 -> 0.27972629
B102: Return on Asset (A*B) | C102: =C96*C100 -> -0.091093203 | D102: =D96*D100 -> -0.038572233 | E102: =E96*E100 -> -0.040654036 | F102: =F96*F100 -> -0.034121486 | G102: =G96*G100 -> 0.0072748511 | H102: =H96*H100 -> 0.089176949 | I102: =I96*I100 -> 0.074561885

Sheet Altman Z Score
B2: TATA MOTORS LTD
B3: ( TATA MOTORS LTD | BSE Code : 500570 )
B4: INR 716.00 (as on 05.10.2025)
B5: 52 Week ( High - INR 948.45 & Low - 535.75)
B7: About the company
B8: Tata Motors Group is a leading global automobile manufacturer. Part of the illustrious multi-national conglomerate, the Tata group, it offers a wide and diverse portfolio of cars, sports utility vehicles, trucks, buses and defence vehicles to the world.It has operations in India, the UK, South Korea, South Africa, China, Brazil, Austria and Slovakia through a strong global network of subsidiaries, associate companies and Joint Ventures (JVs), including Jaguar Land Rover in the UK and Tata Daewoo in South Korea.
B13: Financial Summary
B67: Working Capital/Total Asset
C68: ='Historical FS'!F9 -> 43555 | D68: ='Historical FS'!G9 -> 43921 | E68: ='Historical FS'!H9 -> 44286 | F68: ='Historical FS'!I9 -> 44651 | G68: ='Historical FS'!J9 -> 45016 | H68: ='Historical FS'!K9 -> 45382 | I68: ='Historical FS'!L9 -> 45747
B69: Working Capital | C69: ='Data Sheet'!E67-'Data Sheet'!E62 -> 7465.87 | D69: ='Data Sheet'!F67-'Data Sheet'!F62 -> 8828.26 | E69: ='Data Sheet'!G67-'Data Sheet'!G62 -> 13085.47 | F69: ='Data Sheet'!H67-'Data Sheet'!H62 -> 12524.2 | G69: ='Data Sheet'!I67-'Data Sheet'!I62 -> 6701.81 | H69: ='Data Sheet'!J67-'Data Sheet'!J62 -> 12228 | I69: ='Data Sheet'!K67-'Data Sheet'!K62 -> -29475
B70: Total Assets | C70: ='Data Sheet'!E68 -> 305703.49 | D70: ='Data Sheet'!F68 -> 320179.39 | E70: ='Data Sheet'!G68 -> 341569.91 | F70: ='Data Sheet'!H68 -> 329061.49 | G70: ='Data Sheet'!I68 -> 334674.43 | H70: ='Data Sheet'!J68 -> 369521 | I70: ='Data Sheet'!K68 -> 376973
B71: Working Capital/Total Asset (A) | C71: =C69/C70 -> 0.024421933 | D71: =D69/D70 -> 0.027572855 | E71: =E69/E70 -> 0.038309786 | F71: =F69/F70 -> 0.038060364 | G71: =G69/G70 -> 0.020024864 | H71: =H69/H70 -> 0.033091489 | I71: =I69/I70 -> -0.078188624
B73: Retained Earnings/Total Assets
C74: =C68 -> 43555 | D74: =D68 -> 43921 | E74: =E68 -> 44286 | F74: =F68 -> 44651 | G74: =G68 -> 45016 | H74: =H68 -> 45382 | I74: =I68 -> 45747
B75: Retained Earnings | C75: ='Historical FS'!F42*'Historical FS'!F44*'Historical FS'!F50 -> 0 | D75: ='Historical FS'!G42*'Historical FS'!G44*'Historical FS'!G50 -> 0 | E75: ='Historical FS'!H42*'Historical FS'!H44*'Historical FS'!H50 -> 0 | F75: ='Historical FS'!I42*'Historical FS'!I44*'Historical FS'!I50 -> 0 | G75: ='Historical FS'!J42*'Historical FS'!J44*'Historical FS'!J50 -> 0 | H75: ='Historical FS'!K42*'Historical FS'!K44*'Historical FS'!K50 -> 24714 | I75: ='Historical FS'!L42*'Historical FS'!L44*'Historical FS'!L50 -> 14167
B76: Total Assets | C76: =C70 -> 305703.49 | D76: =D70 -> 320179.39 | E76: =E70 -> 341569.91 | F76: =F70 -> 329061.49 | G76: =G70 -> 334674.43 | H76: =H70 -> 369521 | I76: =I70 -> 376973
B77: Retained Earnings/Total Assets (B) | C77: =C75/C76 -> 0 | D77: =D75/D76 -> 0 | E77: =E75/E76 -> 0 | F77: =F75/F76 -> 0 | G77: =G75/G76 -> 0 | H77: =H75/H76 -> 0.066881179 | I77: =I75/I76 -> 0.037580941
B79: EBIT/Total Assets
C80: =C74 -> 43555 | D80: =D74 -> 43921 | E80: =E74 -> 44286 | F80: =F74 -> 44651 | G80: =G74 -> 45016 | H80: =H74 -> 45382 | I80: =I74 -> 45747
B81: EBIT | C81: ='Historical FS'!F24-'Historical FS'!F30 -> 1073.7 | D81: ='Historical FS'!G24-'Historical FS'!G30 -> -3438.36 | E81: ='Historical FS'!H24-'Historical FS'!H30 -> 8740.72 | F81: ='Historical FS'!I24-'Historical FS'!I30 -> -115.6 | G81: ='Historical FS'!J24-'Historical FS'!J30 -> 6955.44 | H81: ='Historical FS'!K24-'Historical FS'!K30 -> 30585 | I81: ='Historical FS'!L24-'Historical FS'!L30 -> 31960
B82: =B76 -> Total Assets | C82: =C76 -> 305703.49 | D82: =D76 -> 320179.39 | E82: =E76 -> 341569.91 | F82: =F76 -> 329061.49 | G82: =G76 -> 334674.43 | H82: =H76 -> 369521 | I82: =I76 -> 376973
B83: EBIT/Total Assets (C) | C83: =C81/C82 -> 0.0035122268 | D83: =D81/D82 -> -0.010738855 | E83: =E81/E82 -> 0.025589842 | F83: =F81/F82 -> -0.00035130212 | G83: =G81/G82 -> 0.020782705 | H83: =H81/H82 -> 0.082769315 | I83: =I81/I82 -> 0.084780608
B85: Market Cap/Long Term Liabilities
C86: =C80 -> 43555 | D86: =D80 -> 43921 | E86: =E80 -> 44286 | F86: =F80 -> 44651 | G86: =G80 -> 45016 | H86: =H80 -> 45382 | I86: =I80 -> 45747
B87: market Cap | C87: =('Data Sheet'!E72*'Data Sheet'!E93)/10000000 -> 111001.55 | D87: =('Data Sheet'!F72*'Data Sheet'!F93)/10000000 -> 62690.379 | E87: =('Data Sheet'!G72*'Data Sheet'!G93)/10000000 -> 27205.476 | F87: =('Data Sheet'!H72*'Data Sheet'!H93)/10000000 -> 115571.74 | G87: =('Data Sheet'!I72*'Data Sheet'!I93)/10000000 -> 166130.47 | H87: =('Data Sheet'!J72*'Data Sheet'!J93)/10000000 -> 161271.26 | I87: =('Data Sheet'!K72*'Data Sheet'!K93)/10000000 -> 365484.3
B88: Long Term Liabilities | C88: ='Data Sheet'!E61 -> 106175.34 | D88: ='Data Sheet'!F61 -> 124787.64 | E88: ='Data Sheet'!G61 -> 142130.57 | F88: ='Data Sheet'!H61 -> 146449.03 | G88: ='Data Sheet'!I61 -> 134113.44 | H88: ='Data Sheet'!J61 -> 107264 | I88: ='Data Sheet'!K61 -> 71540
B89: Market Cap/Long Term Liabilities (D) | C89: =C87/C88 -> 1.0454551 | D89: =D87/D88 -> 0.50237651 | E89: =E87/E88 -> 0.19141185 | F89: =F87/F88 -> 0.78916017 | G89: =G87/G88 -> 1.2387309 | H89: =H87/H88 -> 1.5034985 | I89: =I87/I88 -> 5.1088105
B92: Sales/Total Assets
C93: =C74 -> 43555 | D93: =D74 -> 43921 | E93: =E74 -> 44286 | F93: =F74 -> 44651 | G93: =G74 -> 45016 | H93: =H74 -> 45382 | I93: =I74 -> 45747
B94: Total Sales | C94: ='Data Sheet'!E17 -> 301938.4 | D94: ='Data Sheet'!F17 -> 261067.97 | E94: ='Data Sheet'!G17 -> 249794.75 | F94: ='Data Sheet'!H17 -> 278453.62 | G94: ='Data Sheet'!I17 -> 345966.97 | H94: ='Data Sheet'!J17 -> 434016 | I94: ='Data Sheet'!K17 -> 439695
B95: =B82 -> Total Assets | C95: =C82 -> 305703.49 | D95: =D82 -> 320179.39 | E95: =E82 -> 341569.91 | F95: =F82 -> 329061.49 | G95: =G82 -> 334674.43 | H95: =H82 -> 369521 | I95: =I82 -> 376973
B96: Return on Assets (E) | C96: =C94/C95 -> 0.98768385 | D96: =D94/D95 -> 0.81538031 | E96: =E94/E95 -> 0.73131369 | F96: =F94/F95 -> 0.84620543 | G96: =G94/G95 -> 1.0337419 | H96: =H94/H95 -> 1.1745368 | I96: =I94/I95 -> 1.1663833
B98: Altman's Z Score
C99: =C93 -> 43555 | D99: =D93 -> 43921 | E99: =E93 -> 44286 | F99: =F93 -> 44651 | G99: =G93 -> 45016 | H99: =H93 -> 45382 | I99: =I93 -> 45747
B100: Final Score | C100: =(C71*1.2)+(C77*1.4)+(C83*3.3)+(C89*0.6)+(C96*1) -> 1.6558536 | D100: =(D71*1.2)+(D77*1.4)+(D83*3.3)+(D89*0.6)+(D96*1) -> 1.1144554 | E100: =(E71*1.2)+(E77*1.4)+(E83*3.3)+(E89*0.6)+(E96*1) -> 0.97657902 | F100: =(F71*1.2)+(F77*1.4)+(F83*3.3)+(F89*0.6)+(F96*1) -> 1.3642147 | G100: =(G71*1.2)+(G77*1.4)+(G83*3.3)+(G89*0.6)+(G96*1) -> 1.8695932 | H100: =(H71*1.2)+(H77*1.4)+(H83*3.3)+(H89*0.6)+(H96*1) -> 2.483118 | I100: =(I71*1.2)+(I77*1.4)+(I83*3.3)+(I89*0.6)+(I96*1) -> 4.4702325
B101: Financial Stability | C101: =IF(C100<1.81,"Distressed",IF(C100>3,"Stong","Grey Zone")) -> Distressed | D101: =IF(D100<1.81,"Distressed",IF(D100>3,"Stong","Grey Zone")) -> Distressed | E101: =IF(E100<1.81,"Distressed",IF(E100>3,"Stong","Grey Zone")) -> Distressed | F101: =IF(F100<1.81,"Distressed",IF(F100>3,"Stong","Grey Zone")) -> Distressed | G101: =IF(G100<1.81,"Distressed",IF(G100>3,"Stong","Grey Zone")) -> Grey Zone | H101: =IF(H100<1.81,"Distressed",IF(H100>3,"Stong","Grey Zone")) -> Grey Zone | I101: =IF(I100<1.81,"Distressed",IF(I100>3,"Stong","Grey Zone")) -> Stong

Sheet Historical Approach (VAR)
B3: TATA MOTORS LTD
B4: ( TATA MOTORS LTD | BSE Code : 500570 )
B5: INR 1095.00
B6: 52 Week ( High - INR 1179.00 & Low - 593.30)
A9: x | B9: Date | C9: Adj Close | D9: Return | E9: Sorted Returns | G9: Calculation of Value at Risk - Tata Motors (Histoeical)
B10: 37753 | C10: 30.21 | D10: =C10/C11-1 -> -0.19867374 | E10: 2.146875
B11: 37790 | C11: 37.7 | D11: =C11/C12-1 -> 0.070414537 | E11: 1.815534 | G11: Mean | K11: =AVERAGE(E10:E8492) -> 0.001662863
B12: 37788 | C12: 35.22 | D12: =C12/C13-1 -> -0.059294872 | E12: 1.7387247 | G12: STD Devation | K12: =_xlfn.STDEV.S(E10:E8492) -> 0.061125679
B13: 37798 | C13: 37.44 | D13: =C13/C14-1 -> 0.0026780932 | E13: 1.6819484 | G13: Min | K13: =MIN(E10:E8492) -> -0.68306372
B14: 37792 | C14: 37.34 | D14: =C14/C15-1 -> -0.078707131 | E14: 1.6444759 | G14: Max | K14: =MAX(E10:E8492) -> 2.146875
B15: 37809 | C15: 40.53 | D15: =C15/C16-1 -> -0.0193564 | E15: 1.4313137 | G15: CPM | K15: 716
B16: 37823 | C16: 41.33 | D16: =C16/C17-1 -> -0.67971172 | E16: 1.0623752
B17: 34976 | C17: 129.04 | D17: =C17/C18-1 -> -0.74543302 | E17: 0.60218525 | G17: Percentile | H17: Confidence | I17: VAR % | J17: Stock Price | K17: VAR (INR)
B18: 44482 | C18: 506.9 | D18: =C18/C19-1 -> 4.4359249 | E18: 0.20446715 | G18: 0.05 | H18: =100%-G18 -> 0.95 | I18: =_xlfn.PERCENTILE.INC($E$10:$E$8492,G18) -> -0.042127521 | J18: =$K$15*(1-I18) -> 746.16331 | K18: =$K$15-J18 -> -30.163305
B19: 43951 | C19: 93.25 | D19: =C19/C20-1 -> 0.29730106 | E19: 0.19321817 | G19: 0.01 | H19: =100%-G19 -> 0.99 | I19: =_xlfn.PERCENTILE.INC($E$10:$E$8492,G19) -> -0.074447186 | J19: =$K$15*(1-I19) -> 769.30418 | K19: =$K$15-J19 -> -53.304185
B20: 39953 | C20: 71.88 | D20: =C20/C21-1 -> -0.58318353 | E20: 0.18829559 | G20: 0.005 | H20: =100%-G20 -> 0.995 | I20: =_xlfn.PERCENTILE.INC($E$10:$E$8492,G20) -> -0.08839814 | J20: =$K$15*(1-I20) -> 779.29307 | K20: =$K$15-J20 -> -63.293068
B21: 43767 | C21: 172.45 | D21: =C21/C22-1 -> 0.1675694 | E21: 0.1675694 | G21: 0.1 | H21: =100%-G21 -> 0.9 | I21: =_xlfn.PERCENTILE.INC($E$10:$E$8492,G21) -> -0.03011645 | J21: =$K$15*(1-I21) -> 737.56338 | K21: =$K$15-J21 -> -21.563378
B22: 43765 | C22: 147.7 | D22: =C22/C23-1 -> -0.54130435 | E22: 0.16436736
B23: 44229 | C23: 322 | D23: =C23/C24-1 -> 4.4008722 | E23: 0.15164521
B24: 39951 | C24: 59.62 | D24: =C24/C25-1 -> 0.99598259 | E24: 0.1358354
B25: 39786 | C25: 29.87 | D25: =C25/C26-1 -> -0.25880893 | E25: 0.13272658
B26: 39905 | C26: 40.3 | D26: =C26/C27-1 -> -0.63611738 | E26: 0.13138686
B27: 43987 | C27: 110.75 | D27: =C27/C28-1 -> 1.9384452 | E27: 0.12436548
B28: 39755 | C28: 37.69 | D28: =C28/C29-1 -> -0.76133485 | E28: 0.12339791
B29: 40239 | C29: 157.92 | D29: =C29/C30-1 -> -0.58055777 | E29: 0.1221488
B30: 44476 | C30: 376.5 | D30: =C30/C31-1 -> 21.721786 | E30: 0.12036899
B31: 36833 | C31: 16.57 | D31: =C31/C32-1 -> -0.70251346 | E31: 0.11808367
B32: 39918 | C32: 55.7 | D32: =C32/C33-1 -> -0.74756402 | E32: 0.1164562
B33: 44207 | C33: 220.65 | D33: =C33/C34-1 -> 0.97008929 | E33: 0.11355034
... B7690: 37750 | C7690: 9.6 | D7690: =C7690/C7691-1 -> #DIV/0! | E7690: -0.68306372

Sheet Raw FS
B2: Particulars | C2: 42430 | D2: 42795 | E2: 43160 | F2: 43525 | G2: 43891 | H2: 44256 | I2: 44621 | J2: 44986 | K2: 45352 | L2: 45717
A4: x | B4: Equity Capital | C4: 679 | D4: 679 | E4: 679 | F4: 679 | G4: 720 | H4: 766 | I4: 766 | J4: 766 | K4: 767 | L4: 736
B5: Reserves | C5: 78273 | D5: 57383 | E5: 94749 | F5: 59500 | G5: 62359 | H5: 54481 | I5: 43795 | J5: 44556 | K5: 84151 | L5: 115408
B6: Borrowings -
B7: Long term Borrowings | C7: 50510 | D7: 60629 | E7: 61200 | F7: 70818 | G7: 83316 | H7: 93113 | I7: 97759 | J7: 88696 | K7: 62149 | L7: 40217
B8: Short term Borrowings | C8: 11451 | D8: 13860 | E8: 16795 | F8: 20150 | G8: 16363 | H8: 42792 | I8: 41918 | J8: 36965 | K8: 36352 | L8: 22282
B9: Lease Liabilities | C9: 0 | D9: 0 | E9: 0 | F9: 173 | G9: 5977 | H9: 6226 | I9: 6772 | J9: 8453 | K9: 8763 | L9: 9041
B10: Other Borrowings | C10: 7399 | D10: 4115 | E10: 10956 | F10: 15034 | G10: 19132 | H10: 0 | I10: 0 | J10: 0 | K10: 0 | L10: 0
B11: Other Liabilities -
B12: Non controlling int | C12: 433 | D12: 453 | E12: 525 | F12: 523 | G12: 814 | H12: 1573 | I12: 4271 | J12: 7278 | K12: 8176 | L12: 6610
B13: Trade Payables | C13: 61562 | D13: 62533 | E13: 76940 | F13: 71691 | G13: 66398 | H13: 76040 | I13: 69750 | J13: 79252 | K13: 93978 | L13: 97368
B14: Advance from Customers | C14: 2165 | D14: 1711 | E14: 0 | F14: 0 | G14: 0 | H14: 0 | I14: 0 | J14: 0 | K14: 0 | L14: 0
B15: Other liability items | C15: 50712 | D15: 71218 | E15: 65349 | F15: 67135 | G15: 65101 | H15: 66579 | I15: 64030 | J15: 68710 | K15: 75185 | L15: 85311
B16: Total Liabilities | C16: 263184 | D16: 272580 | E16: 327192 | F16: 305703 | G16: 320179 | H16: 341570 | I16: 329061 | J16: 334674 | K16: 369521 | L16: 376973
B18: Fixed Assets -
B19: Land | C19: 7185 | D19: 6762 | E19: 7339 | F19: 7286 | G19: 7675 | H19: 7819 | I19: 7760 | J19: 8045 | K19: 7996 | L19: 7900
B20: Building | C20: 12343 | D20: 12164 | E20: 16552 | F20: 22938 | G20: 32665 | H20: 35537 | I20: 36466 | J20: 38674 | K20: 40583 | L20: 44662
B21: Plant Machinery | C21: 80063 | D21: 79976 | E21: 100226 | F21: 109415 | G21: 124158 | H21: 138868 | I21: 148585 | J21: 153672 | K21: 151877 | L21: 155939
B22: Equipments | C22: 498 | D22: 0 | E22: 0 | F22: 0 | G22: 0 | H22: 0 | I22: 0 | J22: 0 | K22: 0 | L22: 0
B23: Computers | C23: 1634 | D23: 1767 | E23: 1943 | F23: 2335 | G23: 3054 | H23: 3172 | I23: 3383 | J23: 3499 | K23: 3667 | L23: 3879
B24: Furniture n fittings | C24: 1241 | D24: 1401 | E24: 1430 | F24: 1626 | G24: 1890 | H24: 1956 | I24: 1984 | J24: 2084 | K24: 2029 | L24: 1970
B25: Vehicles | C25: 280 | D25: 291 | E25: 353 | F25: 387 | G25: 601 | H25: 845 | I25: 725 | J25: 788 | K25: 956 | L25: 1151
B26: Intangible Assets | C26: 58951 | D26: 54932 | E26: 77870 | F26: 80480 | G26: 91157 | H26: 114809 | I26: 114323 | J26: 112538 | K26: 116714 | L26: 93455
B27: Other fixed assets | C27: 6746 | D27: 6219 | E27: 7497 | F27: 8049 | G27: 9380 | H27: 10686 | I27: 10870 | J27: 11841 | K27: 10657 | L27: 11044
B28: Gross Block | C28: 168941 | D28: 163512 | E28: 213209 | F28: 232517 | G28: 270579 | H28: 313692 | I28: 324096 | J28: 331141 | K28: 334479 | L28: 320000
B29: Accumulated Depreciation | C29: 61709 | D29: 67568 | E29: 91795 | F29: 121283 | G29: 143471 | H29: 174985 | I29: 185241 | J29: 199062 | K29: 213194 | L29: 204303
B30: Net Block | C30: =C28-C29 -> 107232 | D30: =D28-D29 -> 95944 | E30: =E28-E29 -> 121414 | F30: =F28-F29 -> 111234 | G30: =G28-G29 -> 127108 | H30: =H28-H29 -> 138707 | I30: =I28-I29 -> 138855 | J30: =J28-J29 -> 132079 | ... L30: =L28-L29 -> 115697
B32: CWIP | C32: 25919 | D32: 33699 | E32: 40034 | F32: 31884 | G32: 35622 | H32: 20964 | I32: 10251 | J32: 14274 | K32: 35698 | L32: 65806
B33: Investments | C33: 23767 | D33: 20338 | E33: 20813 | F33: 15771 | G33: 16308 | H33: 24620 | I33: 29380 | J33: 26379 | K33: 22971 | L33: 35656
B35: Other Assets -
B36: Inventories | C36: 32656 | D36: 35085 | E36: 42138 | F36: 39014 | G36: 37457 | H36: 36089 | I36: 35240 | J36: 40755 | K36: 47788 | L36: 47269
B37: Trade receivables + | C37: 13571 | D37: 14076 | E37: 19893 | F37: 18996 | G37: 11173 | H37: 12679 | I37: 12442 | J37: 15738 | K37: 16952 | L37: 13248
B38: Cash Equivalents | C38: 30460 | D38: 36078 | E38: 34614 | F38: 32649 | G38: 33727 | H38: 46792 | I38: 40669 | J38: 37016 | K38: 45807 | L38: 40834
B39: Loans n Advances | C39: 2072 | D39: 1816 | E39: 4066 | F39: 3620 | G39: 3353 | H39: 4520 | I39: 4583 | J39: -4029 | K39: -1743 | L39: 7552
B40: Other asset items | C40: 27508 | D40: 35544 | E40: 44221 | F40: 52535 | G40: 55432 | H40: 57198 | I40: 57641 | J40: 72461 | K40: 80763 | L40: 50911
B41: Total Assets | C41: 263184 | D41: 272580 | E41: 327192 | F41: 305703 | G41: 320179 | H41: 341570 | I41: 329061 | J41: 334674 | K41: 369521 | L41: 376973
A43: x | B43: Cash Flow Satement
B44: Particulars | C44: 42064 | D44: 42430 | E44: 42795 | F44: 43160 | G44: 43525 | H44: 43891 | I44: 44256 | J44: 44621 | K44: 44986 | L44: 45352
B45: Cash from Operating Activity -
B46: Profit from operations | C46: 38626 | D46: 28840 | E46: 33312 | F46: 28771 | G46: 23352 | H46: 31198 | I46: 26943 | J46: 41694 | K46: 65106 | L46: 58937
B47: Receivables | C47: -2223 | D47: -4152 | E47: -10688 | F47: -9109 | G47: 9950 | H47: -5505 | I47: 185 | J47: -2213 | K47: -1876 | L47: 3573
B48: Inventory | C48: -5743 | D48: -6621 | E48: -3560 | F48: 2069 | G48: 2326 | H48: 3814 | I48: 472 | J48: -5665 | K48: -7265 | L48: 2127
B49: Payables | C49: 3947 | D49: 9301 | E49: 7320 | F49: -4692 | G49: -8085 | H49: 5748 | I49: -7012 | J49: 6945 | K49: 13706 | L49: 1303
B50: Loans Advances | C50: -520 | D50: 0 | E50: 0 | F50: 0 | G50: 0 | H50: 0 | I50: 0 | J50: 0 | K50: 0 | L50: 0
B51: Other WC items | C51: 5852 | D51: 4727 | E51: 494 | F51: 4512 | G51: 875 | H51: -4150 | I51: -4396 | J51: -2194 | K51: 2760 | L51: 1153
B52: Working capital changes | C52: 1313 | D52: 3254 | E52: -6434 | F52: -7221 | G52: 5065 | H52: -93 | I52: -10750 | J52: -3127 | K52: 7325 | L52: 8156
B53: Direct taxes | C53: -2040 | D53: -1895 | E53: -3021 | F53: -2659 | G53: -1785 | H53: -2105 | I53: -1910 | J53: -3179 | K53: -4516 | L53: -3991
B54: Cash from Investing Activity -
B55: Fixed assets purchased | C55: -31503 | D55: -16072 | E55: -35079 | F55: -35304 | G55: -29702 | H55: -20205 | I55: -15168 | J55: -19230 | K55: -31414 | L55: -38042
B56: Fixed assets sold | C56: 59 | D56: 53 | E56: 30 | F56: 67 | G56: 171 | H56: 351 | I56: 230 | J56: 285 | K56: 231 | L56: 974
B57: Investments purchased | C57: -4728 | D57: -6 | E57: -329 | F57: -130 | G57: -1439 | H57: -7530 | I57: -3008 | J57: -50 | K57: -74 | L57: -12677
B58: Investments sold | C58: 89 | D58: 1965 | E58: 2381 | F58: 5644 | G58: 21 | H58: 226 | I58: 104 | J58: 6895 | K58: 10821 | L58: 111
B59: Interest received | C59: 731 | D59: 638 | E59: 690 | F59: 761 | G59: 1104 | H59: 428 | I59: 653 | J59: 973 | K59: 2493 | L59: 2420
B60: Dividends received | C60: 58 | D60: 620 | E60: 1797 | F60: 232 | G60: 21 | H60: 18 | I60: 32 | J60: 46 | K60: 47 | L60: 64
B61: Investment in group cos | C61: 0 | D61: -107 | E61: -4 | F61: -9 | G61: -606 | H61: -10 | I61: 0 | J61: 0 | K61: -150 | L61: 0
B62: Redemp n Canc of Shares | C62: 0 | D62: 0 | E62: 14 | F62: 533 | G62: 0 | H62: 0 | I62: 0 | J62: 19 | K62: 107 | L62: 765
B63: Acquisition of companies | C63: -111 | D63: 0 | E63: 0 | F63: -8 | G63: -27 | H63: 0 | I63: -98 | J63: 0 | K63: 0 | L63: -688
B64: Inter corporate deposits | C64: 0 | D64: 0 | E64: 0 | F64: 0 | G64: 0 | H64: 0 | I64: 0 | J64: 0 | K64: -25 | L64: -20
B65: Other investing items | C65: -1289 | D65: -26663 | E65: 5360 | F65: 7335 | G65: -2659 | H65: 1051 | I65: 12813 | J65: -4357 | K65: -4817 | L65: -2889
B66: Cash from Financing Activity -
B67: Proceeds from shares | C67: 7433 | D67: 5 | E67: 0 | F67: 0 | G67: 3889 | H67: 2603 | I67: 19 | J67: 20 | K67: 82 | L67: 1108
B68: Redemption of debentures | C68: 0 | D68: 0 | E68: 0 | F68: 0 | G68: 0 | H68: 0 | I68: 0 | J68: 0 | K68: 0 | L68: 0
B69: Proceeds from borrowings | C69: 19519 | D69: 33390 | E69: 37482 | F69: 51128 | G69: 38297 | H69: 46641 | I69: 46578 | J69: 43934 | K69: 18829 | L69: 13384
B70: Repayment of borrowings | C70: -24924 | D70: -21732 | E70: -29964 | F70: -35198 | G70: -29847 | H70: -29709 | I70: -42816 | J70: -62557 | K70: -47414 | L70: -21443
B71: Interest paid fin | C71: -5716 | D71: -5336 | E71: -5411 | F71: -7005 | G71: -7518 | H71: -8123 | I71: -9251 | J71: -9336 | K71: -9332 | L71: -5814
B72: Dividends paid | C72: -108 | D72: -121 | E72: -96 | F72: -95 | G72: -57 | H72: -30 | I72: -100 | J72: -141 | K72: -1059 | L72: -2492
B73: Financial liabilities | C73: 0 | D73: 0 | E73: 0 | F73: 0 | G73: -1346 | H73: -1477 | I73: -1559 | J73: -1517 | K73: -1924 | L73: -2393
B74: Other financing items | C74: 0 | D74: 0 | E74: 0 | F74: 0 | G74: -29 | H74: 0 | I74: 3750 | J74: 3355 | K74: 3812 | L74: -1136
B75: Net Cash Flow | C75: -2589 | D75: -3167 | E75: 730 | F75: 6843 | G75: -3092 | H75: 13232 | I75: 6459 | J75: -6272 | K75: 8128 | L75: -5666

Sheet Data Room-->

Sheet Sheet1
C3: 42430 | D3: 42795 | E3: 43160 | F3: 43525 | G3: 43891 | H3: 44256 | I3: 44621 | J3: 44986 | K3: 45352 | L3: 45717
B4: Cash from Operating Activity -
B5: Profit from operations | C5: 38626 | D5: 28840 | E5: 33312 | F5: 28771 | G5: 23352 | H5: 31198 | I5: 26943 | J5: 41694 | K5: 65106 | L5: 58937
B6: Receivables | C6: -2223 | D6: -4152 | E6: -10688 | F6: -9109 | G6: 9950 | H6: -5505 | I6: 185 | J6: -2213 | K6: -1876 | L6: 3573
B7: Inventory | C7: -5743 | D7: -6621 | E7: -3560 | F7: 2069 | G7: 2326 | H7: 3814 | I7: 472 | J7: -5665 | K7: -7265 | L7: 2127
B8: Payables | C8: 3947 | D8: 9301 | E8: 7320 | F8: -4692 | G8: -8085 | H8: 5748 | I8: -7012 | J8: 6945 | K8: 13706 | L8: 1303
B9: Loans Advances | C9: -520 | D9: 0 | E9: 0 | F9: 0 | G9: 0 | H9: 0 | I9: 0 | J9: 0 | K9: 0 | L9: 0
B10: Other WC items | C10: 5852 | D10: 4727 | E10: 494 | F10: 4512 | G10: 875 | H10: -4150 | I10: -4396 | J10: -2194 | K10: 2760 | L10: 1153
B11: Working capital changes | C11: 1313 | D11: 3254 | E11: -6434 | F11: -7221 | G11: 5065 | H11: -93 | I11: -10750 | J11: -3127 | K11: 7325 | L11: 8156
B12: Direct taxes | C12: -2040 | D12: -1895 | E12: -3021 | F12: -2659 | G12: -1785 | H12: -2105 | I12: -1910 | J12: -3179 | K12: -4516 | L12: -3991
B13: Cash from Investing Activity -
B14: Fixed assets purchased | C14: -31503 | D14: -16072 | E14: -35079 | F14: -35304 | G14: -29702 | H14: -20205 | I14: -15168 | J14: -19230 | K14: -31414 | L14: -38042
B15: Fixed assets sold | C15: 59 | D15: 53 | E15: 30 | F15: 67 | G15: 171 | H15: 351 | I15: 230 | J15: 285 | K15: 231 | L15: 974
B16: Investments purchased | C16: -4728 | D16: -6 | E16: -329 | F16: -130 | G16: -1439 | H16: -7530 | I16: -3008 | J16: -50 | K16: -74 | L16: -12677
B17: Investments sold | C17: 89 | D17: 1965 | E17: 2381 | F17: 5644 | G17: 21 | H17: 226 | I17: 104 | J17: 6895 | K17: 10821 | L17: 111
B18: Interest received | C18: 731 | D18: 638 | E18: 690 | F18: 761 | G18: 1104 | H18: 428 | I18: 653 | J18: 973 | K18: 2493 | L18: 2420
B19: Dividends received | C19: 58 | D19: 620 | E19: 1797 | F19: 232 | G19: 21 | H19: 18 | I19: 32 | J19: 46 | K19: 47 | L19: 64
B20: Investment in group cos | C20: 0 | D20: -107 | E20: -4 | F20: -9 | G20: -606 | H20: -10 | I20: 0 | J20: 0 | K20: -150 | L20: 0
B21: Redemp n Canc of Shares | C21: 0 | D21: 0 | E21: 14 | F21: 533 | G21: 0 | H21: 0 | I21: 0 | J21: 19 | K21: 107 | L21: 765
B22: Acquisition of companies | C22: -111 | D22: 0 | E22: 0 | F22: -8 | G22: -27 | H22: 0 | I22: -98 | J22: 0 | K22: 0 | L22: -688
B23: Inter corporate deposits | C23: 0 | D23: 0 | E23: 0 | F23: 0 | G23: 0 | H23: 0 | I23: 0 | J23: 0 | K23: -25 | L23: -20
B24: Other investing items | C24: -1289 | D24: -26663 | E24: 5360 | F24: 7335 | G24: -2659 | H24: 1051 | I24: 12813 | J24: -4357 | K24: -4817 | L24: -2889
B25: Cash from Financing Activity -
B26: Proceeds from shares | C26: 7433 | D26: 5 | E26: 0 | F26: 0 | G26: 3889 | H26: 2603 | I26: 19 | J26: 20 | K26: 82 | L26: 1108
B27: Redemption of debentures | C27: 0 | D27: 0 | E27: 0 | F27: 0 | G27: 0 | H27: 0 | I27: 0 | J27: 0 | K27: 0 | L27: 0
B28: Proceeds from borrowings | C28: 19519 | D28: 33390 | E28: 37482 | F28: 51128 | G28: 38297 | H28: 46641 | I28: 46578 | J28: 43934 | K28: 18829 | L28: 13384
B29: Repayment of borrowings | C29: -24924 | D29: -21732 | E29: -29964 | F29: -35198 | G29: -29847 | H29: -29709 | I29: -42816 | J29: -62557 | K29: -47414 | L29: -21443
B30: Interest paid fin | C30: -5716 | D30: -5336 | E30: -5411 | F30: -7005 | G30: -7518 | H30: -8123 | I30: -9251 | J30: -9336 | K30: -9332 | L30: -5814
B31: Dividends paid | C31: -108 | D31: -121 | E31: -96 | F31: -95 | G31: -57 | H31: -30 | I31: -100 | J31: -141 | K31: -1059 | L31: -2492
B32: Financial liabilities | C32: 0 | D32: 0 | E32: 0 | F32: 0 | G32: -1346 | H32: -1477 | I32: -1559 | J32: -1517 | K32: -1924 | L32: -2393
B33: Other financing items | C33: 0 | D33: 0 | E33: 0 | F33: 0 | G33: -29 | H33: 0 | I33: 3750 | J33: 3355 | K33: 3812 | L33: -1136
B34: Net Cash Flow | C34: -2589 | D34: -3167 | E34: 730 | F34: 6843 | G34: -3092 | H34: 13232 | I34: 6459 | J34: -6272 | K34: 8128 | L34: -5666
B35: Ratios

Sheet Data Comp Val
B2: S.No. | C2: Name | D2: CMP Rs. | E2: No. Eq. Shares Cr. | F2: Market Cap | G2: Debt Rs.Cr. | H2: Cash End Rs.Cr. | I2: Net Debt | J2: EV | K2: Sales Rs.Cr. | L2: EBITDA | M2: NP 12M Rs.Cr.
B3: 1 | C3: Tata Motors | D3: 716.1 | E3: 368.23 | F3: 263687.69 | G3: 71540 | H3: 40834 | I3: =G3-H3 -> 30706 | J3: =F3+G3-H3 -> 294393.69 | K3: 437968 | L3: 61315.52 | M3: 28149
B4: 2 | C4: Maruti Suzuki | D4: 15806 | E4: 31.44 | F4: 496944.71 | G4: 87 | H4: 552.9 | I4: =G4-H4 -> -465.9 | J4: =F4+G4-H4 -> 496478.81 | K4: 155738.8 | L4: 24918.208 | M4: 14500.2
B5: 3 | C5: M & M | D5: 3462 | E5: 124.35 | F5: 430509.68 | G5: 129024.58 | H5: 20614.84 | I5: =G5-H5 -> 108409.74 | J5: =F5+G5-H5 -> 538919.42 | K5: 167522.29 | L5: 33504.458 | M5: 14073.17
B6: 4 | C6: Bajaj Auto | D6: 8679.5 | E6: 27.93 | F6: 242381.64 | G6: 9364.16 | H6: 2847.6 | I6: =G6-H6 -> 6516.56 | J6: =F6+G6-H6 -> 248898.2 | K6: 52195.83 | L6: 10961.124 | M6: 7324.73
B7: 5 | C7: Hyundai Motor | D7: 2507.6 | E7: 81.25 | F7: 203752.81 | G7: 847.29 | H7: 8135.35 | I7: =G7-H7 -> -7288.06 | J7: =F7+G7-H7 -> 196464.75 | K7: 66704.55 | L7: 9338.637 | M7: 5492.25
B8: 6 | C8: Eicher Motors | D8: 6941 | E8: 27.43 | F8: 190376.35 | G8: 458.13 | H8: 263.01 | I8: =G8-H8 -> 195.12 | J8: =F8+G8-H8 -> 190571.47 | K8: 19519.14 | L8: 6636.5076 | M8: 4734.44
B9: 7 | C9: TVS Motor Co. | D9: 3456.1 | E9: 47.51 | F9: 164194.86 | G9: 28608.71 | H9: 4386.24 | I9: =G9-H9 -> 24222.47 | J9: =F9+G9-H9 -> 188417.33 | K9: 46088.61 | L9: 6452.4054 | M9: 2379.81
B10: 8 | C10: Bosch | D10: 38630 | E10: 2.95 | F10: 113933.93 | G10: 118.3 | H10: 507.7 | I10: =G10-H10 -> -389.4 | J10: =F10+G10-H10 -> 113544.53 | K10: 18559.2 | L10: 3155.064 | M10: 2013.3
B11: 9 | C11: Samvardh. Mothe. | D11: 106.67 | E11: 1055.44 | F11: 112584.24 | G11: 17221.7 | H11: 6288.8 | I11: =G11-H11 -> 10932.9 | J11: =F11+G11-H11 -> 123517.14 | K11: 115006.61 | L11: 11500.661 | M11: 4145.7
B12: 10 | C12: Hero Motocorp | D12: 5550.5 | E12: 20.01 | F12: 111047.67 | G12: 699.93 | H12: 574.08 | I12: =G12-H12 -> 125.85 | J12: =F12+G12-H12 -> 111173.52 | K12: 40440.38 | L12: 6470.4608 | M12: 4375.81

Sheet Beta - Comps
B7: S.No. | C7: Name | D7: CMP Rs. | E7: Mar Cap Rs.Cr. | F7: Debt / Equity | G7: Debt Rs.Cr.
B8: 1 | C8: Maruti Suzuki | D8: 15806 | E8: 496944.71 | F8: =G8/E8 -> 0.00017506978 | G8: 87
B9: 2 | C9: M & M | D9: 3462 | E9: 430509.68 | F9: =G9/E9 -> 0.29970193 | G9: 129024.58
B10: 3 | C10: Tata Motors | D10: 716.1 | E10: 263687.69 | F10: =G10/E10 -> 0.2713058 | G10: 71540
B11: 4 | C11: Bajaj Auto | D11: 8679.5 | E11: 242381.64 | F11: =G11/E11 -> 0.038633949 | G11: 9364.16
B12: 5 | C12: Eicher Motors | D12: 6941 | E12: 190376.35 | F12: =G12/E12 -> 0.0024064439 | G12: 458.13

Sheet Data Sheet
A1: COMPANY NAME | B1: TATA MOTORS LTD | E1: =IF(B2<>B3, "A NEW VERSION OF THE WORKSHEET IS AVAILABLE", "")
A2: LATEST VERSION | B2: 2.1 | E2: PLEASE DO NOT MAKE ANY CHANGES TO THIS SHEET
A3: CURRENT VERSION | B3: 2.1
A5: META
A6: Number of shares | B6: =IF(B9>0, B9/B8, 0) -> 368.22747
A7: Face Value | B7: 2
A8: Current Price | B8: 716.1
A9: Market Capitalization | B9: 263687.69
A15: PROFIT & LOSS
A16: Report Date | B16: 42460 | C16: 42825 | D16: 43190 | E16: 43555 | F16: 43921 | G16: 44286 | H16: 44651 | I16: 45016 | J16: 45382 | K16: 45747
A17: Sales | B17: 273045.6 | C17: 269692.51 | D17: 291550.48 | E17: 301938.4 | F17: 261067.97 | G17: 249794.75 | H17: 278453.62 | I17: 345966.97 | J17: 434016 | K17: 439695
A18: Raw Material Cost | B18: 166134.01 | C18: 173294.08 | D18: 187896.58 | E18: 194267.91 | F18: 164899.82 | G18: 153607.36 | H18: 179295.33 | I18: 231251.26 | J18: 274321 | K18: 268950
A19: Change in Inventory | B19: 2750.99 | C19: 7399.92 | D19: 2046.58 | E19: -2053.28 | F19: -2231.19 | G19: -4684.16 | H19: -1590.49 | I19: 4781.62 | J19: 1566 | K19: -2836
A20: Power and Fuel | B20: 1143.63 | C20: 1159.82 | D20: 1308.08 | E20: 1585.93 | F20: 1264.95 | G20: 1112.87 | H20: 2178.29 | I20: 2513.33 | J20: 2189 | K20: 2443
A21: Other Mfr. Exp | B21: 12101.53 | C21: 10067.37 | D21: 10971.66 | E21: 11694.54 | F21: 11541.51 | G21: 8273.17 | H21: 9427.38 | I21: 11765.97 | J21: 17446 | K21: 18813
A22: Employee Cost | B22: 28880.89 | C22: 28332.89 | D22: 30300.09 | E22: 33243.87 | F22: 30438.6 | G22: 27648.48 | H22: 30808.52 | I22: 33654.7 | J22: 41990 | K22: 47767
A23: Selling and admin | B23: 21991.9 | C23: 30039.38 | D23: 31004.58 | E23: 32719.8 | F23: 29248.32 | G23: 23015.79 | H23: 29205.4 | I23: 34839.19 | J23: 42765 | K23: 47099
A24: Other Expenses | B24: 7149.38 | C24: 4610.2 | D24: 658.39 | E24: 1708.74 | F24: 3456.51 | G24: -834.51 | H24: 1228.12 | I24: 4908.34 | J24: -953 | K24: -3429
A25: Other Income | B25: -2669.62 | C25: 1869.1 | D25: 5932.73 | E25: -26686.25 | F25: 101.71 | G25: -11117.83 | H25: 2424.05 | I25: 6663.97 | J25: 4792 | K25: 11774
A26: Depreciation | B26: 16710.78 | C26: 17904.99 | D26: 21553.59 | E26: 23590.63 | F26: 21425.43 | G26: 23546.71 | H26: 24835.69 | I26: 24860.36 | J26: 27239 | K26: 23256
A27: Interest | B27: 4889.08 | C27: 4238.01 | D27: 4681.79 | E27: 5758.6 | F27: 7243.33 | G27: 8097.17 | H27: 9311.86 | I27: 10225.48 | J27: 7594 | K27: 5083
... A30: Net profit | B30: 11579.31 | C30: 7454.36 | D30: 8988.91 | E30: -28826.23 | F30: -12070.85 | G30: -13451.39 | H30: -11441.47 | I30: 2414.29 | J30: 31399 | K30: 27830
A31: Dividend Amount | B31: 67.92 | I31: 766.02 | J31: 2301 | K31: 2208
A34: EBITDA | B34: =B30+B29+B27+B26 -> 36204.22 | C34: =C30+C29+C27+C26 -> 32848.59 | D34: =D30+D29+D27+D26 -> 39566.22 | E34: =E30+E29+E27+E26 -> -1914.45 | F34: =F30+F29+F27+F26 -> 16993.16 | G34: =G30+G29+G27+G26 -> 20734.35 | H34: =H30+H29+H27+H26 -> 26937.37 | I34: =I30+I29+I27+I26 -> 38204.19 | ... K34: =K30+K29+K27+K26 -> 66671
A35: EBITDA Margins | B35: =B34/B17 -> 0.13259404 | C35: =C34/C17 -> 0.12180016 | D35: =D34/D17 -> 0.13570967 | E35: =E34/E17 -> -0.0063405317 | F35: =F34/F17 -> 0.065090942 | G35: =G34/G17 -> 0.083005548 | H35: =H34/H17 -> 0.096739163 | I35: =I34/I17 -> 0.11042728 | ... K35: =K34/K17 -> 0.15163011
A36: Sales Growth YOY | C36: =C17/B17-1 -> -0.01228033 | D36: =D17/C17-1 -> 0.081047746 | E36: =E17/D17-1 -> 0.035629919 | F36: =F17/E17-1 -> -0.13536016 | G36: =G17/F17-1 -> -0.043181168 | H36: =H17/G17-1 -> 0.11472967 | I36: =I17/H17-1 -> 0.24245815 | J36: =J17/I17-1 -> 0.25450126 | K36: =K17/J17-1 -> 0.013084771
A37: Gross profit | B37: =B17-SUM(B18:B21) -> 90915.44 | C37: =C17-SUM(C18:C21) -> 77771.32 | D37: =D17-SUM(D18:D21) -> 89327.58 | E37: =E17-SUM(E18:E21) -> 96443.3 | F37: =F17-SUM(F18:F21) -> 85592.88 | G37: =G17-SUM(G18:G21) -> 91485.51 | H37: =H17-SUM(H18:H21) -> 89143.11 | I37: =I17-SUM(I18:I21) -> 95654.79 | ... K37: =K17-SUM(K18:K21) -> 152325
A38: GPM | B38: =B37/B17 -> 0.33296797 | C38: =C37/C17 -> 0.28837034 | D38: =D37/D17 -> 0.30638804 | E38: =E37/E17 -> 0.31941383 | F38: =F37/F17 -> 0.32785669 | G38: =G37/G17 -> 0.36624273 | H38: =H37/H17 -> 0.32013629 | I38: =I37/I17 -> 0.27648532 | ... K38: =K37/K17 -> 0.34643332
A39: EBIT Margins | B39: =(B34-B26)/B17 -> 0.071392617 | C39: =(C34-C26)/C17 -> 0.05540977 | D39: =(D34-D26)/D17 -> 0.0617822 | E39: =(E34-E26)/E17 -> -0.084471137 | F39: =(F34-F26)/F17 -> -0.016977456 | G39: =(G34-G26)/G17 -> -0.011258683 | H39: =(H34-H26)/H17 -> 0.0075476842 | I39: =(I34-I26)/I17 -> 0.038569665 | ... K39: =(K34-K26)/K17 -> 0.098738899
A40: NPM | B40: =B30/B17 -> 0.042407971 | C40: =C30/C17 -> 0.027640219 | D40: =D30/D17 -> 0.030831402 | E40: =E30/E17 -> -0.095470566 | F40: =F30/F17 -> -0.046236426 | G40: =G30/G17 -> -0.053849771 | H40: =H30/H17 -> -0.04108932 | I40: =I30/I17 -> 0.0069783829 | ... K40: =K30/K17 -> 0.063293874
A42: Quarters
A43: Report Date | B43: 45016 | C43: 45107 | D43: 45199 | E43: 45291 | F43: 45382 | G43: 45473 | H43: 45565 | I43: 45657 | J43: 45747 | K43: 45838
A44: Sales | B44: 105932.35 | C44: 102236 | D44: 105129 | E44: 110577 | F44: 119033 | G44: 107102 | H44: 101450 | I44: 112608 | J44: 119503 | K44: 104407
A45: Expenses | B45: 92817.95 | C45: 89019 | D45: 91362 | E45: 95159 | F45: 102348 | G45: 91854 | H45: 89291 | I45: 100185 | J45: 102685 | K45: 94183
A46: Other Income | B46: 1452.86 | C46: 895 | D46: 1557 | E46: 1604 | F46: 1412 | G46: 6553 | H46: 1647 | I46: 1700 | J46: 1057 | K46: 1595
A47: Depreciation | B47: 7050.2 | C47: 6633 | D47: 6637 | E47: 6850 | F47: 7143 | G47: 6565 | H47: 6005 | I47: 5399 | J47: 5295 | K47: 5320
A48: Interest | B48: 2641.67 | C48: 2615 | D48: 2652 | E48: 2485 | F48: 1645 | G48: 1471 | H48: 2034 | I48: 1119 | J48: 1076 | K48: 938
A49: Profit before tax | B49: 4875.39 | C49: 4864 | D49: 6035 | E49: 7687 | F49: 9309 | G49: 13765 | H49: 5767 | I49: 7605 | J49: 11504 | K49: 5561
A50: Tax | B50: -620.65 | C50: 1563 | D50: 2203 | E50: 542 | F50: -8219 | G50: 3178 | H50: 2317 | I50: 2120 | J50: 2948 | K50: 1558
A51: Net profit | B51: 5407.79 | C51: 3203 | D51: 3764 | E51: 7025 | F51: 17407 | G51: 10514 | H51: 3343 | I51: 5406 | J51: 8470 | K51: 3924
A52: Operating Profit | B52: 13114.4 | C52: 13217 | D52: 13767 | E52: 15418 | F52: 16685 | G52: 15248 | H52: 12159 | I52: 12423 | J52: 16818 | K52: 10224
A53: EBITDA | B53: =B51+B50+B48+B47 -> 14479.01 | C53: =C51+C50+C48+C47 -> 14014 | D53: =D51+D50+D48+D47 -> 15256 | E53: =E51+E50+E48+E47 -> 16902 | F53: =F51+F50+F48+F47 -> 17976 | G53: =G51+G50+G48+G47 -> 21728 | H53: =H51+H50+H48+H47 -> 13699 | I53: =I51+I50+I48+I47 -> 14044 | ... K53: =K51+K50+K48+K47 -> 11740
A57: BALANCE SHEET
A58: Report Date | B58: 42460 | C58: 42825 | D58: 43190 | E58: 43555 | F58: 43921 | G58: 44286 | H58: 44651 | I58: 45016 | J58: 45382 | K58: 45747
A59: Equity Share Capital | B59: 679.18 | C59: 679.22 | D59: 679.22 | E59: 679.22 | F59: 719.54 | G59: 765.81 | H59: 765.88 | I59: 766.02 | J59: 767 | K59: 736
A60: Reserves | B60: 78273.23 | C60: 57382.67 | D60: 94748.69 | E60: 59500.34 | F60: 62358.99 | G60: 54480.91 | H60: 43795.36 | I60: 44555.77 | J60: 84151 | K60: 115408
A61: Borrowings | B61: 69359.96 | C61: 78603.98 | D61: 88950.47 | E61: 106175.34 | F61: 124787.64 | G61: 142130.57 | H61: 146449.03 | I61: 134113.44 | J61: 107264 | K61: 71540
A62: Other Liabilities | B62: 114871.75 | C62: 135914.49 | D62: 142813.43 | E62: 139348.59 | F62: 132313.22 | G62: 144192.62 | H62: 138051.22 | I62: 155239.2 | J62: 177339 | K62: 189289
A63: Total | B63: 263184.12 | C63: 272580.36 | D63: 327191.81 | E63: 305703.49 | F63: 320179.39 | G63: 341569.91 | H63: 329061.49 | I63: 334674.43 | J63: 369521 | K63: 376973
A64: Net Block | B64: 107231.76 | C64: 95944.08 | D64: 121413.86 | E64: 111234.47 | F64: 127107.14 | G64: 138707.61 | H64: 138855.45 | I64: 132079.76 | J64: 121285 | K64: 115697
A65: Capital Work in Progress | B65: 25918.94 | C65: 33698.84 | D65: 40033.5 | E65: 31883.84 | F65: 35622.29 | G65: 20963.93 | H65: 10251.09 | I65: 14274.5 | J65: 35698 | K65: 65806
A66: Investments | B66: 23767.02 | C66: 20337.92 | D66: 20812.75 | E66: 15770.72 | F66: 16308.48 | G66: 24620.28 | H66: 29379.53 | I66: 26379.16 | J66: 22971 | K66: 35656
A67: Other Assets | B67: 106266.4 | C67: 122599.52 | D67: 144931.7 | E67: 146814.46 | F67: 141141.48 | G67: 157278.09 | H67: 150575.42 | I67: 161941.01 | J67: 189567 | K67: 159814
A68: Total | B68: 263184.12 | C68: 272580.36 | D68: 327191.81 | E68: 305703.49 | F68: 320179.39 | G68: 341569.91 | H68: 329061.49 | I68: 334674.43 | J68: 369521 | K68: 376973
A69: Receivables | B69: 13570.91 | C69: 14075.55 | D69: 19893.3 | E69: 18996.17 | F69: 11172.69 | G69: 12679.08 | H69: 12442.12 | I69: 15737.97 | J69: 16952 | K69: 13248
... A72: No. of Equity Shares | B72: 3395930306 | C72: 3396100719 | D72: 3396100719 | E72: 3396100719 | F72: 3597726185 | G72: 3829060661 | H72: 3829414903 | I72: 3830097221 | J72: 3832491897 | K72: 3681348742
A73: New Bonus Shares
A74: Face value | B74: 2 | C74: 2 | D74: 2 | E74: 2 | F74: 2 | G74: 2 | H74: 2 | I74: 2 | J74: 2 | K74: 2
A76: Other Assets | B76: =B67-SUM(B69:B71) -> 29579.36 | C76: =C67-SUM(C69:C71) -> 37360.78 | D76: =D67-SUM(D69:D71) -> 48286.86 | E76: =E67-SUM(E69:E71) -> 56155.74 | F76: =F67-SUM(F69:F71) -> 58784.94 | G76: =G67-SUM(G69:G71) -> 61717.96 | H76: =H67-SUM(H69:H71) -> 62223.77 | I76: =I67-SUM(I69:I71) -> 68432.09 | ... K76: =K67-SUM(K69:K71) -> 58463
A77: Total Assets | B77: =B63 -> 263184.12 | C77: =C63 -> 272580.36 | D77: =D63 -> 327191.81 | E77: =E63 -> 305703.49 | F77: =F63 -> 320179.39 | G77: =G63 -> 341569.91 | H77: =H63 -> 329061.49 | I77: =I63 -> 334674.43 | ... K77: =K63 -> 376973
A83: CASH FLOW: | B83: 42460 | C83: 42825 | D83: 43190 | E83: 43555 | F83: 43921 | G83: 44286 | H83: 44651 | I83: 45016 | J83: 45382 | K83: 45747
A84: Report Date | B84: 37899.54 | C84: 30199.25 | D84: 23857.42 | E84: 18890.75 | F84: 26632.94 | G84: 29000.51 | H84: 14282.83 | I84: 35388.01 | J84: 67915 | K84: 63102
A85: Cash from Operating Activity | B85: -36693.9 | C85: -39571.4 | D85: -25139.14 | E85: -20878.07 | F85: -33114.55 | G85: -25672.5 | H85: -4443.66 | I85: -15417.17 | J85: -22781 | K85: -49982
A86: Cash from Investing Activity | B86: -3795.12 | C86: 6205.3 | D86: 2011.71 | E86: 8830.37 | F86: 3389.61 | G86: 9904.2 | H86: -3380.17 | I86: -26242.9 | J86: -37006 | K86: -18786
A87: Cash from Financing Activity | B87: -2589.48 | C87: -3166.85 | D87: 729.99 | E87: 6843.05 | F87: -3092 | G87: 13232.21 | H87: 6459 | I87: -6272.06 | J87: 8128 | K87: -5666
A88: Net Cash Flow | B88: 4500.35 | C88: -2589.48 | D88: -3166.85 | E88: 729.99 | F88: 6843.05 | G88: -3092 | H88: 13232.21 | I88: 6459 | J88: -6272.06 | K88: 8127.81
B92: 386.6 | C92: 465.85 | D92: 326.85 | E92: 174.25 | F92: 71.05 | G92: 301.8 | H92: 433.75 | I92: 420.8 | J92: 992.8 | K92: 674.45
A93: PRICE: | B93: 544.37 | C93: 386.6 | D93: 465.85 | E93: 326.85 | F93: 174.25 | G93: 71.05 | H93: 301.8 | I93: 433.75 | J93: 420.8 | K93: 992.8
A95: DERIVED: | B95: 288.72 | C95: 288.73 | D95: 288.73 | E95: 288.73 | F95: 308.9 | G95: 332.03 | H95: 332.07 | I95: 332.13 | J95: 332.37 | K95: 368.13
A96: Adjusted Equity Shares in Cr | B96: 288.74 | C96: 288.72 | D96: 288.73 | E96: 288.73 | F96: 288.73 | G96: 308.9 | H96: 332.03 | I96: 332.07 | J96: 332.13 | K96: 332.37
A98: Market Capitalization | B98: =B93*B96 -> 157181.39 | C98: =C93*C96 -> 111619.15 | D98: =D93*D96 -> 134504.87 | E98: =E93*E96 -> 94371.401 | F98: =F93*F96 -> 50311.203 | G98: =G93*G96 -> 21947.345 | H98: =H93*H96 -> 100206.65 | I98: =I93*I96 -> 144035.36 | ... K98: =K93*K96 -> 329976.94
A99: Debt | B99: =B61 -> 69359.96 | C99: =C61 -> 78603.98 | D99: =D61 -> 88950.47 | E99: =E61 -> 106175.34 | F99: =F61 -> 124787.64 | G99: =G61 -> 142130.57 | H99: =H61 -> 146449.03 | I99: =I61 -> 134113.44 | ... K99: =K61 -> 71540
A100: Cash | B100: =B71 -> 30460.4 | C100: =C71 -> 36077.88 | D100: =D71 -> 34613.91 | E100: =E71 -> 32648.82 | F100: =F71 -> 33726.97 | G100: =G71 -> 46792.46 | H100: =H71 -> 40669.19 | I100: =I71 -> 37015.56 | ... K100: =K71 -> 40834
A101: EV | B101: =B98+B99-B100 -> 196080.95 | C101: =C98+C99-C100 -> 154145.25 | D101: =D98+D99-D100 -> 188841.43 | E101: =E98+E99-E100 -> 167897.92 | F101: =F98+F99-F100 -> 141371.87 | G101: =G98+G99-G100 -> 117285.46 | H101: =H98+H99-H100 -> 205986.49 | I101: =I98+I99-I100 -> 241133.24 | ... K101: =K98+K99-K100 -> 360682.94
A103: EV / EBITDA | B103: =B101/B34 -> 5.4159696 | C103: =C101/C34 -> 4.6925987 | D103: =D101/D34 -> 4.7727943 | E103: =E101/E34 -> -87.700342 | F103: =F101/F34 -> 8.3193398 | G103: =G101/G34 -> 5.6565774 | H103: =H101/H34 -> 7.6468673 | I103: =I101/I34 -> 6.3116962 | ... K103: =K101/K34 -> 5.4098924
A104: EV / Sales | B104: =B101/B17 -> 0.7181253 | C104: =C101/C17 -> 0.57155926 | D104: =D101/D17 -> 0.64771435 | E104: =E101/E17 -> 0.5560668 | F104: =F101/F17 -> 0.54151366 | G104: =G101/G17 -> 0.4695273 | H104: =H101/H17 -> 0.73975154 | I104: =I101/I17 -> 0.69698342 | ... K104: =K101/K17 -> 0.82030256
A106: Book value | B106: =B59+B60 -> 78952.41 | C106: =C59+C60 -> 58061.89 | D106: =D59+D60 -> 95427.91 | E106: =E59+E60 -> 60179.56 | F106: =F59+F60 -> 63078.53 | G106: =G59+G60 -> 55246.72 | H106: =H59+H60 -> 44561.24 | I106: =I59+I60 -> 45321.79 | ... K106: =K59+K60 -> 116144
A107: P/B Ratio | B107: =B98/B106 -> 1.9908372 | C107: =C98/C106 -> 1.9224168 | D107: =D98/D106 -> 1.4094919 | E107: =E98/E106 -> 1.5681637 | F107: =F98/F106 -> 0.79759631 | G107: =G98/G106 -> 0.3972606 | H107: =H98/H106 -> 2.2487403 | I107: =I98/I106 -> 3.1780599 | ... K107: =K98/K106 -> 2.8411019

Sheet Beta Data-->

Sheet ERP
B7: Return on Markets
B9: Year | C9: Annual
B10: 2000 | C10: -0.1465 | E10: Average Return | F10: =AVERAGE(C10:C33) -> 0.15609167
B11: 2001 | C11: -0.1618 | E11: Dividend Yield | F11: 0.0138
B12: 2002 | C12: 0.0325 | E12: Total Market Return | F12: =SUM(F10:F11) -> 0.16989167
B13: 2003 | C13: 0.719
B14: 2004 | C14: 0.1068
B15: 2005 | C15: 0.3634 | E15: =STDEV(C10:C33) -> 0.2887659
B16: 2006 | C16: 0.3983 | E16: 0.1661
B17: 2007 | C17: 0.5477
B18: 2008 | C18: -0.5179 | E18: =2.39%*(E15/E16) -> 0.041550302
B19: 2009 | C19: 0.7576
B20: 2010 | C20: 0.1795
B21: 2011 | C21: -0.2462
B22: 2012 | C22: 0.277
B23: 2013 | C23: 0.0676
B24: 2014 | C24: 0.3139
B25: 2015 | C25: -0.0406
B26: 2016 | C26: 0.0301
B27: 2017 | C27: 0.2865
B28: 2018 | C28: 0.0315
B29: 2019 | C29: 0.1202
B30: 2020 | C30: 0.149
... B34: 2024 | C34: 0.0875

Sheet TAMO
B2: TATA MOTORS LTD
B3: ( TATA MOTORS LTD | BSE Code : 500570 )
B4: INR 716.00 (as on 05.10.2025)
B5: 52 Week ( High - INR 948.45 & Low - 535.75)
B8: Regression Beta - 2 Years Weekly
B10: TAMO WEEKLY RETURNS | F10: NIFTY Returns | I10: Beta Drifting | L10: Beta 1 | M10: =SLOPE(D14:D138,G14:G138) -> 0.22671716
L11: Beta 2 | M11: =_xlfn.COVARIANCE.S(D14:D138,G14:G138)/_xlfn.VAR.S(G14:G138) -> 0.22671716
B12: Date | C12: Closing Price | D12: Returns | F12: Closing Price | G12: Return | I12: Levered Raw Beta | J12: =M13 -> 1.3913567
B13: 45207 | C13: 665.05 | F13: 19751.05 | I13: Beta Weight | J13: 0.75 | L13: Beta 3 | M13: =M32 -> 1.3913567
B14: 45214 | C14: 661.16 | D14: -0.0058491843 | F14: 19542.65 | G14: =F14/F13-1 -> -0.010551338
B15: 45221 | C15: 639.08 | D15: -0.03339585 | F15: 19047.25 | G15: =F15/F14-1 -> -0.025349684 | I15: Mean Beta | J15: 1 | L15: SUMMARY OUTPUT
B16: 45228 | C16: 645.51 | D16: 0.010061338 | F16: 19230.6 | G16: =F16/F15-1 -> 0.0096260615 | I16: Mean Beta Weight | J16: 0.25
B17: 45235 | C17: 649.05 | D17: 0.0054840359 | F17: 19425.35 | G17: =F17/F16-1 -> 0.010127089 | L17: Regression Statistics
B18: 45242 | C18: 679.45 | D18: 0.046837686 | F18: 19731.8 | G18: =F18/F17-1 -> 0.015775778 | I18: Adjusted Beta | J18: =(J12*J13)+(J15*J16) -> 1.2935176 | L18: Multiple R | M18: 0.58092574
B19: 45249 | C19: 671.63 | D19: -0.011509309 | F19: 19794.7 | G19: =F19/F18-1 -> 0.0031877477 | L19: R Square | M19: 0.33747471
B20: 45256 | C20: 703.28 | D20: 0.047124161 | F20: 20267.9 | G20: =F20/F19-1 -> 0.023905389 | L20: Adjusted R Square | M20: 0.33091506
B21: 45263 | C21: 712.35 | D21: 0.012896713 | F21: 20969.4 | G21: =F21/F20-1 -> 0.034611381 | L21: Standard Error | M21: 0.034031041
B22: 45270 | C22: 730.15 | D22: 0.024987717 | F22: 21456.65 | G22: =F22/F21-1 -> 0.023236239 | L22: Observations | M22: 103
B23: 45277 | C23: 722.47 | D23: -0.010518387 | F23: 21349.4 | G23: =F23/F22-1 -> -0.0049984504
B24: 45284 | C24: 777.55 | D24: 0.07623846 | F24: 21731.4 | G24: =F24/F23-1 -> 0.017892775 | L24: ANOVA
B25: 45291 | C25: 788.52 | D25: 0.014108417 | F25: 21710.8 | G25: =F25/F24-1 -> -0.00094793709 | M25: df | N25: SS | O25: MS | P25: F | Q25: Significance F
B26: 45298 | C26: 813.94 | D26: 0.03223761 | F26: 21894.55 | G26: =F26/F25-1 -> 0.0084635297 | L26: Regression | M26: 1 | N26: 0.059581388 | O26: 0.059581388 | P26: 51.447011 | Q26: 1.2513674e-10
B27: 45305 | C27: 821.02 | D27: 0.0086984299 | F27: 21622.4 | G27: =F27/F26-1 -> -0.012430034 | L27: Residual | M27: 101 | N27: 0.11696929 | O27: 0.0011581117
B28: 45312 | C28: 809.35 | D28: -0.014214026 | F28: 21352.6 | G28: =F28/F27-1 -> -0.012477801 | L28: Total | M28: 102 | N28: 0.17655067
B29: 45319 | C29: 876.05 | D29: 0.082411812 | F29: 21853.8 | G29: =F29/F28-1 -> 0.023472551
B30: 45326 | C30: 912.18 | D30: 0.041241938 | F30: 21782.5 | G30: =F30/F29-1 -> -0.0032625905 | M30: Coefficients | N30: Standard Error | O30: t Stat | P30: P-value | Q30: Lower 95% | R30: Upper 95% | S30: Lower 95.0% | T30: Upper 95.0%
B31: 45333 | C31: 935.71 | D31: 0.025795347 | F31: 22040.7 | G31: =F31/F30-1 -> 0.011853552 | L31: Intercept | M31: -0.0017620689 | N31: 0.0033853144 | O31: -0.52050375 | P31: 0.60385168 | Q31: -0.008477622 | R31: 0.0049534843 | S31: -0.008477622 | T31: 0.0049534843
B32: 45340 | C32: 934.52 | D32: -0.0012717616 | F32: 22212.7 | G32: =F32/F31-1 -> 0.0078037449 | L32: X Variable 1 | M32: 1.3913567 | N32: 0.19398066 | O32: 7.1726572 | P32: 1.2513674e-10 | Q32: 1.0065513 | R32: 1.7761622 | S32: 1.0065513 | T32: 1.7761622
B33: 45347 | C33: 974.39 | D33: 0.042663613 | F33: 22338.75 | G33: =F33/F32-1 -> 0.0056746816
B34: 45354 | C34: 1036.1 | D34: 0.063331931 | F34: 22493.55 | G34: =F34/F33-1 -> 0.0069296626
B35: 45361 | C35: 942.94 | D35: -0.089914101 | F35: 22023.35 | G35: =F35/F34-1 -> -0.02090377
B37: Regression Statistics
B38: Multiple R | C38: 0.58092574
B39: R Square | C39: 0.33747471
B40: Adjusted R Square | C40: 0.33091506
B41: Standard Error | C41: 0.034031041
B42: Observations | C42: 103
B44: ANOVA
C45: df | D45: SS | E45: MS | F45: F | G45: Significance F
B46: Regression | C46: 1 | D46: 0.059581388 | E46: 0.059581388 | F46: 51.447011 | G46: 1.2513674e-10
B47: Residual | C47: 101 | D47: 0.11696929 | E47: 0.0011581117
B48: Total | C48: 102 | D48: 0.17655067
C50: Coefficients | D50: Standard Error | E50: t Stat | F50: P-value | G50: Lower 95% | H50: Upper 95% | I50: Lower 95.0% | J50: Upper 95.0%
B51: Intercept | C51: -0.0017620689 | D51: 0.0033853144 | E51: -0.52050375 | F51: 0.60385168 | G51: -0.008477622 | H51: 0.0049534843 | I51: -0.008477622 | J51: 0.0049534843
B52: X Variable 1 | C52: 1.3913567 | D52: 0.19398066 | E52: 7.1726572 | F52: 1.2513674e-10 | G52: 1.0065513 | H52: 1.7761622 | I52: 1.0065513 | J52: 1.7761622
B56: 45368 | C56: 976.79 | D56: 0.03589836 | F56: 22096.75 | G56: =F56/F35-1 -> 0.0033328263
B57: 45375 | C57: 989.75 | D57: 0.013267949 | F57: 22326.9 | G57: =F57/F56-1 -> 0.010415559
B58: 45382 | C58: 1004 | D58: 0.014397575 | F58: 22513.7 | G58: =F58/F57-1 -> 0.0083665892
B59: 45389 | C59: 1015.37 | D59: 0.011324701 | F59: 22519.4 | G59: =F59/F58-1 -> 0.00025317918
B60: 45396 | C60: 960.24 | D60: -0.054295478 | F60: 22147 | G60: =F60/F59-1 -> -0.016536853
B61: 45403 | C61: 996.43 | D61: 0.037688495 | F61: 22419.95 | G61: =F61/F60-1 -> 0.012324468
B62: 45410 | C62: 1010.28 | D62: 0.013899622 | F62: 22475.85 | G62: =F62/F61-1 -> 0.0024933151
B63: 45417 | C63: 1043.43 | D63: 0.032812686 | F63: 22055.2 | G63: =F63/F62-1 -> -0.018715644
B64: 45424 | C64: 942.79 | D64: -0.096451128 | F64: 22466.1 | G64: =F64/F63-1 -> 0.018630527
B65: 45431 | C65: 957.59 | D65: 0.015698088 | F65: 22957.1 | G65: =F65/F64-1 -> 0.021855151
B66: 45438 | C66: 920.16 | D66: -0.03908771 | F66: 22530.7 | G66: =F66/F65-1 -> -0.018573775
B67: 45445 | C67: 967.52 | D67: 0.05146931 | F67: 23290.15 | G67: =F67/F66-1 -> 0.033707342
B68: 45452 | C68: 993.4 | D68: 0.026748801 | F68: 23465.6 | G68: =F68/F67-1 -> 0.0075332276
... B136: 45928 | C136: 716.1 | D136: 0.064199733 | F136: 24894.25 | G136: =F136/F135-1 -> 0.0097162002

Sheet Maruti Suzuki
B7: Regression Beta - 2 Years Weekly
B9: Maruti Suzuki Weekly Return | F9: NIFTY Returns | I9: Beta Drifting | L9: Beta 1 | M9: =SLOPE(D13:D117,G13:G117) -> 0.74366658
L10: Beta 2 | M10: =_xlfn.COVARIANCE.S(D13:D117,G13:G117)/_xlfn.VAR.S(G13:G117) -> 0.74366658
B11: Date | C11: Closing Price | D11: Return | F11: Closing Price | G11: Return | I11: Levered Raw Beta | J11: =M12 -> 0.74366658
B12: 45207 | C12: 10727.55 | F12: 19751.05 | I12: Beta Weight | J12: 0.75 | L12: Beta 3 | M12: =M31 -> 0.74366658
B13: 45214 | C13: 10725.65 | D13: =C13/C12-1 -> -0.00017711407 | F13: 19542.65 | G13: =F13/F12-1 -> -0.010551338
B14: 45221 | C14: 10560.7 | D14: =C14/C13-1 -> -0.015379021 | F14: 19047.25 | G14: =F14/F13-1 -> -0.025349684 | I14: Mean Beta | J14: 1 | L14: SUMMARY OUTPUT
B15: 45228 | C15: 10276.3 | D15: =C15/C14-1 -> -0.026930033 | F15: 19230.6 | G15: =F15/F14-1 -> 0.0096260615 | I15: Mean Beta Weight | J15: 0.25
B16: 45235 | C16: 10388.8 | D16: =C16/C15-1 -> 0.01094752 | F16: 19425.35 | G16: =F16/F15-1 -> 0.010127089 | L16: Regression Statistics
B17: 45242 | C17: 10523.5 | D17: =C17/C16-1 -> 0.012965886 | F17: 19731.8 | G17: =F17/F16-1 -> 0.015775778 | I17: Adjusted Beta | J17: =(J11*J12)+(J14*J15) -> 0.80774994 | L17: Multiple R | M17: 0.41712885
B18: 45249 | C18: 10515.65 | D18: =C18/C17-1 -> -0.00074594954 | F18: 19794.7 | G18: =F18/F17-1 -> 0.0031877477 | L18: R Square | M18: 0.17399648
B19: 45256 | C19: 10585.7 | D19: =C19/C18-1 -> 0.0066614998 | F19: 20267.9 | G19: =F19/F18-1 -> 0.023905389 | L19: Adjusted R Square | M19: 0.16581823
B20: 45263 | C20: 10618.55 | D20: =C20/C19-1 -> 0.0031032431 | F20: 20969.4 | G20: =F20/F19-1 -> 0.034611381 | L20: Standard Error | M20: 0.02828493
B21: 45270 | C21: 10286.4 | D21: =C21/C20-1 -> -0.031280165 | F21: 21456.65 | G21: =F21/F20-1 -> 0.023236239 | L21: Observations | M21: 103
B22: 45277 | C22: 10217.15 | D22: =C22/C21-1 -> -0.0067321901 | F22: 21349.4 | G22: =F22/F21-1 -> -0.0049984504
B23: 45284 | C23: 10302.35 | D23: =C23/C22-1 -> 0.0083389203 | F23: 21731.4 | G23: =F23/F22-1 -> 0.017892775 | L23: ANOVA
B24: 45291 | C24: 10017 | D24: =C24/C23-1 -> -0.027697564 | F24: 21710.8 | G24: =F24/F23-1 -> -0.00094793709 | M24: df | N24: SS | O24: MS | P24: F | Q24: Significance F
B25: 45298 | C25: 9965.65 | D25: =C25/C24-1 -> -0.0051262853 | F25: 21894.55 | G25: =F25/F24-1 -> 0.0084635297 | L25: Regression | M25: 1 | N25: 0.017021199 | O25: 0.017021199 | P25: 21.275508 | Q25: 1.1691682e-05
B26: 45305 | C26: 10037.7 | D26: =C26/C25-1 -> 0.0072298345 | F26: 21622.4 | G26: =F26/F25-1 -> -0.012430034 | L26: Residual | M26: 101 | N26: 0.080803764 | O26: 0.00080003727
B27: 45312 | C27: 9881 | D27: =C27/C26-1 -> -0.015611146 | F27: 21352.6 | G27: =F27/F26-1 -> -0.012477801 | L27: Total | M27: 102 | N27: 0.097824964
B28: 45319 | C28: 10655.45 | D28: =C28/C27-1 -> 0.078377695 | F28: 21853.8 | G28: =F28/F27-1 -> 0.023472551
B29: 45326 | C29: 10732.85 | D29: =C29/C28-1 -> 0.0072638884 | F29: 21782.5 | G29: =F29/F28-1 -> -0.0032625905 | M29: Coefficients | N29: Standard Error | O29: t Stat | P29: P-value | Q29: Lower 95% | R29: Upper 95% | S29: Lower 95.0% | T29: Upper 95.0%
B30: 45333 | C30: 11380.4 | D30: =C30/C29-1 -> 0.060333462 | F30: 22040.7 | G30: =F30/F29-1 -> 0.011853552 | L30: Intercept | M30: 0.0024525564 | N30: 0.0028137071 | O30: 0.87164596 | P30: 0.38546883 | Q30: -0.0031290816 | R30: 0.0080341945 | S30: -0.0031290816 | T30: 0.0080341945
B31: 45340 | C31: 11535.6 | D31: =C31/C30-1 -> 0.013637482 | F31: 22212.7 | G31: =F31/F30-1 -> 0.0078037449 | L31: X Variable 1 | M31: 0.74366658 | N31: 0.1612272 | O31: 4.6125381 | P31: 1.1691682e-05 | Q31: 0.4238352 | R31: 1.063498 | S31: 0.4238352 | T31: 1.063498
B32: 45347 | C32: 11620.95 | D32: =C32/C31-1 -> 0.0073988349 | F32: 22338.75 | G32: =F32/F31-1 -> 0.0056746816
B33: 45354 | C33: 11510.05 | D33: =C33/C32-1 -> -0.0095431096 | F33: 22493.55 | G33: =F33/F32-1 -> 0.0069296626
B34: 45361 | C34: 11476.65 | D34: =C34/C33-1 -> -0.0029018119 | F34: 22023.35 | G34: =F34/F33-1 -> -0.02090377
B35: 45368 | C35: 12337.7 | D35: =C35/C34-1 -> 0.075026249 | F35: 22096.75 | G35: =F35/F34-1 -> 0.0033328263
B36: 45375 | C36: 12600.35 | D36: =C36/C35-1 -> 0.021288409 | F36: 22326.9 | G36: =F36/F35-1 -> 0.010415559
B37: 45382 | C37: 12421.6 | D37: =C37/C36-1 -> -0.014186114 | F37: 22513.7 | G37: =F37/F36-1 -> 0.0083665892
B38: 45389 | C38: 12266.55 | D38: =C38/C37-1 -> -0.012482289 | F38: 22519.4 | G38: =F38/F37-1 -> 0.00025317918
B39: 45396 | C39: 12710.95 | D39: =C39/C38-1 -> 0.036228605 | F39: 22147 | G39: =F39/F38-1 -> -0.016536853
B40: 45403 | C40: 12703.35 | D40: =C40/C39-1 -> -0.00059790968 | F40: 22419.95 | G40: =F40/F39-1 -> 0.012324468
B41: 45410 | C41: 12492.15 | D41: =C41/C40-1 -> -0.016625536 | F41: 22475.85 | G41: =F41/F40-1 -> 0.0024933151
B42: 45417 | C42: 12675.5 | D42: =C42/C41-1 -> 0.014677217 | F42: 22055.2 | G42: =F42/F41-1 -> -0.018715644
B43: 45424 | C43: 12641.5 | D43: =C43/C42-1 -> -0.0026823399 | F43: 22466.1 | G43: =F43/F42-1 -> 0.018630527
... B115: 45928 | C115: 15806 | D115: =C115/C114-1 -> -0.029473167 | F115: 24894.25 | G115: =F115/F114-1 -> 0.0097162002

Sheet Mahindra
B7: Regression Beta - 2 Years Weekly
B9: Mahindra Weekly Return | F9: NIFTY Returns | I9: Beta Drifting | L9: Beta 1 | M9: =SLOPE(D13:D117,G13:G117) -> 1.7587691
L10: Beta 2 | M10: =_xlfn.COVARIANCE.S(D13:D117,G13:G117)/_xlfn.VAR.S(G13:G117) -> 1.7587691
B11: Date | C11: Closing Price | D11: Return | F11: Closing Price | G11: Return | I11: Levered Raw Beta | J11: =M12 -> 1.7587691
B12: 45207 | C12: 1562.45 | F12: 19751.05 | I12: Beta Weight | J12: 0.75 | L12: Beta 3 | M12: =M31 -> 1.7587691
B13: 45214 | C13: 1558.25 | D13: =C13/C12-1 -> -0.002688086 | F13: 19542.65 | G13: =F13/F12-1 -> -0.010551338
B14: 45221 | C14: 1510.8 | D14: =C14/C13-1 -> -0.030450826 | F14: 19047.25 | G14: =F14/F13-1 -> -0.025349684 | I14: Mean Beta | J14: 1 | L14: SUMMARY OUTPUT
B15: 45228 | C15: 1469 | D15: =C15/C14-1 -> -0.027667461 | F15: 19230.6 | G15: =F15/F14-1 -> 0.0096260615 | I15: Mean Beta Weight | J15: 0.25
B16: 45235 | C16: 1524.1 | D16: =C16/C15-1 -> 0.037508509 | F16: 19425.35 | G16: =F16/F15-1 -> 0.010127089 | L16: Regression Statistics
B17: 45242 | C17: 1584.55 | D17: =C17/C16-1 -> 0.039662752 | F17: 19731.8 | G17: =F17/F16-1 -> 0.015775778 | I17: Adjusted Beta | J17: =(J11*J12)+(J14*J15) -> 1.5690768 | L17: Multiple R | M17: 0.63795844
B18: 45249 | C18: 1553.2 | D18: =C18/C17-1 -> -0.019784797 | F18: 19794.7 | G18: =F18/F17-1 -> 0.0031877477 | L18: R Square | M18: 0.40699098
B19: 45256 | C19: 1625.5 | D19: =C19/C18-1 -> 0.04654906 | F19: 20267.9 | G19: =F19/F18-1 -> 0.023905389 | L19: Adjusted R Square | M19: 0.4011196
B20: 45263 | C20: 1668.55 | D20: =C20/C19-1 -> 0.026484159 | F20: 20969.4 | G20: =F20/F19-1 -> 0.034611381 | L20: Standard Error | M20: 0.037059812
B21: 45270 | C21: 1724.95 | D21: =C21/C20-1 -> 0.033801804 | F21: 21456.65 | G21: =F21/F20-1 -> 0.023236239 | L21: Observations | M21: 103
B22: 45277 | C22: 1634.25 | D22: =C22/C21-1 -> -0.052581234 | F22: 21349.4 | G22: =F22/F21-1 -> -0.0049984504
B23: 45284 | C23: 1729.4 | D23: =C23/C22-1 -> 0.058222426 | F23: 21731.4 | G23: =F23/F22-1 -> 0.017892775 | L23: ANOVA
B24: 45291 | C24: 1642 | D24: =C24/C23-1 -> -0.050537759 | F24: 21710.8 | G24: =F24/F23-1 -> -0.00094793709 | M24: df | N24: SS | O24: MS | P24: F | Q24: Significance F
B25: 45298 | C25: 1624.45 | D25: =C25/C24-1 -> -0.010688185 | F25: 21894.55 | G25: =F25/F24-1 -> 0.0084635297 | L25: Regression | M25: 1 | N25: 0.095203141 | O25: 0.095203141 | P25: 69.317813 | Q25: 4.2419295e-13
B26: 45305 | C26: 1655.55 | D26: =C26/C25-1 -> 0.019144941 | F26: 21622.4 | G26: =F26/F25-1 -> -0.012430034 | L26: Residual | M26: 101 | N26: 0.1387164 | O26: 0.0013734297
B27: 45312 | C27: 1635.5 | D27: =C27/C26-1 -> -0.012110779 | F27: 21352.6 | G27: =F27/F26-1 -> -0.012477801 | L27: Total | M27: 102 | N27: 0.23391954
B28: 45319 | C28: 1660.75 | D28: =C28/C27-1 -> 0.015438704 | F28: 21853.8 | G28: =F28/F27-1 -> 0.023472551
B29: 45326 | C29: 1646.4 | D29: =C29/C28-1 -> -0.0086406744 | F29: 21782.5 | G29: =F29/F28-1 -> -0.0032625905 | M29: Coefficients | N29: Standard Error | O29: t Stat | P29: P-value | Q29: Lower 95% | R29: Upper 95% | S29: Lower 95.0% | T29: Upper 95.0%
B30: 45333 | C30: 1835.55 | D30: =C30/C29-1 -> 0.11488703 | F30: 22040.7 | G30: =F30/F29-1 -> 0.011853552 | L30: Intercept | M30: 0.0046524563 | N30: 0.0036866082 | O30: 1.2619883 | P30: 0.20985951 | Q30: -0.0026607828 | R30: 0.011965695 | S30: -0.0026607828 | T30: 0.011965695
B31: 45340 | C31: 1929.95 | D31: =C31/C30-1 -> 0.051428727 | F31: 22212.7 | G31: =F31/F30-1 -> 0.0078037449 | L31: X Variable 1 | M31: 1.7587691 | N31: 0.21124498 | O31: 8.325732 | P31: 4.2419295e-13 | Q31: 1.3397159 | R31: 2.1778223 | S31: 1.3397159 | T31: 2.1778223
B32: 45347 | C32: 1972.95 | D32: =C32/C31-1 -> 0.02228037 | F32: 22338.75 | G32: =F32/F31-1 -> 0.0056746816
B33: 45354 | C33: 1897.55 | D33: =C33/C32-1 -> -0.038216883 | F33: 22493.55 | G33: =F33/F32-1 -> 0.0069296626
B34: 45361 | C34: 1799.5 | D34: =C34/C33-1 -> -0.051671893 | F34: 22023.35 | G34: =F34/F33-1 -> -0.02090377
B35: 45368 | C35: 1878.8 | D35: =C35/C34-1 -> 0.044067797 | F35: 22096.75 | G35: =F35/F34-1 -> 0.0033328263
B36: 45375 | C36: 1921.35 | D36: =C36/C35-1 -> 0.022647435 | F36: 22326.9 | G36: =F36/F35-1 -> 0.010415559
B37: 45382 | C37: 2013.3 | D37: =C37/C36-1 -> 0.047856976 | F37: 22513.7 | G37: =F37/F36-1 -> 0.0083665892
B38: 45389 | C38: 2070.95 | D38: =C38/C37-1 -> 0.02863458 | F38: 22519.4 | G38: =F38/F37-1 -> 0.00025317918
B39: 45396 | C39: 2082.9 | D39: =C39/C38-1 -> 0.0057702987 | F39: 22147 | G39: =F39/F38-1 -> -0.016536853
B40: 45403 | C40: 2044.9 | D40: =C40/C39-1 -> -0.018243795 | F40: 22419.95 | G40: =F40/F39-1 -> 0.012324468
B41: 45410 | C41: 2193 | D41: =C41/C40-1 -> 0.072424079 | F41: 22475.85 | G41: =F41/F40-1 -> 0.0024933151
B42: 45417 | C42: 2193.05 | D42: =C42/C41-1 -> 2.2799818e-05 | F42: 22055.2 | G42: =F42/F41-1 -> -0.018715644
B43: 45424 | C43: 2514.6 | D43: =C43/C42-1 -> 0.14662228 | F43: 22466.1 | G43: =F43/F42-1 -> 0.018630527
... B115: 45928 | C115: 3462 | D115: =C115/C114-1 -> 0.019284558 | F115: 24894.25 | G115: =F115/F114-1 -> 0.0097162002

Sheet Bajaj Auto
B7: Regression Beta - 2 Years Weekly
B9: Bajaj Auto Weekly Return | F9: NIFTY Returns | I9: Beta Drifting | L9: Beta 1 | M9: =SLOPE(D13:D117,G13:G117) -> 1.1030738
L10: Beta 2 | M10: =_xlfn.COVARIANCE.S(D13:D117,G13:G117)/_xlfn.VAR.S(G13:G117) -> 1.1030738
B11: Date | C11: Closing Price | D11: Return | F11: Closing Price | G11: Return | I11: Levered Raw Beta | J11: =M12 -> 1.1030738
B12: 45207 | C12: 5052.4 | F12: 19751.05 | I12: Beta Weight | J12: 0.75 | L12: Beta 3 | M12: =M31 -> 1.1030738
B13: 45214 | C13: 5489.3 | D13: =C13/C12-1 -> 0.086473755 | F13: 19542.65 | G13: =F13/F12-1 -> -0.010551338
B14: 45221 | C14: 5373.55 | D14: =C14/C13-1 -> -0.021086477 | F14: 19047.25 | G14: =F14/F13-1 -> -0.025349684 | I14: Mean Beta | J14: 1 | L14: SUMMARY OUTPUT
B15: 45228 | C15: 5368.95 | D15: =C15/C14-1 -> -0.00085604489 | F15: 19230.6 | G15: =F15/F14-1 -> 0.0096260615 | I15: Mean Beta Weight | J15: 0.25
B16: 45235 | C16: 5392.05 | D16: =C16/C15-1 -> 0.0043025173 | F16: 19425.35 | G16: =F16/F15-1 -> 0.010127089 | L16: Regression Statistics
B17: 45242 | C17: 5631.5 | D17: =C17/C16-1 -> 0.044407971 | F17: 19731.8 | G17: =F17/F16-1 -> 0.015775778 | I17: Adjusted Beta | J17: =(J11*J12)+(J14*J15) -> 1.0773054 | L17: Multiple R | M17: 0.48424459
B18: 45249 | C18: 5930.3 | D18: =C18/C17-1 -> 0.053058688 | F18: 19794.7 | G18: =F18/F17-1 -> 0.0031877477 | L18: R Square | M18: 0.23449282
B19: 45256 | C19: 6046.05 | D19: =C19/C18-1 -> 0.019518405 | F19: 20267.9 | G19: =F19/F18-1 -> 0.023905389 | L19: Adjusted R Square | M19: 0.22691354
B20: 45263 | C20: 6075.7 | D20: =C20/C19-1 -> 0.0049040282 | F20: 20969.4 | G20: =F20/F19-1 -> 0.034611381 | L20: Standard Error | M20: 0.034791292
B21: 45270 | C21: 6275.2 | D21: =C21/C20-1 -> 0.032835723 | F21: 21456.65 | G21: =F21/F20-1 -> 0.023236239 | L21: Observations | M21: 103
B22: 45277 | C22: 6372.1 | D22: =C22/C21-1 -> 0.015441739 | F22: 21349.4 | G22: =F22/F21-1 -> -0.0049984504
B23: 45284 | C23: 6797.25 | D23: =C23/C22-1 -> 0.066720547 | F23: 21731.4 | G23: =F23/F22-1 -> 0.017892775 | L23: ANOVA
B24: 45291 | C24: 6978.5 | D24: =C24/C23-1 -> 0.026665195 | F24: 21710.8 | G24: =F24/F23-1 -> -0.00094793709 | M24: df | N24: SS | O24: MS | P24: F | Q24: Significance F
B25: 45298 | C25: 7301.95 | D25: =C25/C24-1 -> 0.046349502 | F25: 21894.55 | G25: =F25/F24-1 -> 0.0084635297 | L25: Regression | M25: 1 | N25: 0.03744922 | O25: 0.03744922 | P25: 30.938671 | Q25: 2.1890016e-07
B26: 45305 | C26: 7136.55 | D26: =C26/C25-1 -> -0.022651484 | F26: 21622.4 | G26: =F26/F25-1 -> -0.012430034 | L26: Residual | M26: 101 | N26: 0.12225384 | O26: 0.001210434
B27: 45312 | C27: 7597.5 | D27: =C27/C26-1 -> 0.064590033 | F27: 21352.6 | G27: =F27/F26-1 -> -0.012477801 | L27: Total | M27: 102 | N27: 0.15970306
B28: 45319 | C28: 7738.2 | D28: =C28/C27-1 -> 0.01851925 | F28: 21853.8 | G28: =F28/F27-1 -> 0.023472551
B29: 45326 | C29: 7784.85 | D29: =C29/C28-1 -> 0.0060285338 | F29: 21782.5 | G29: =F29/F28-1 -> -0.0032625905 | M29: Coefficients | N29: Standard Error | O29: t Stat | P29: P-value | Q29: Lower 95% | R29: Upper 95% | S29: Lower 95.0% | T29: Upper 95.0%
B30: 45333 | C30: 8325.05 | D30: =C30/C29-1 -> 0.069391189 | F30: 22040.7 | G30: =F30/F29-1 -> 0.011853552 | L30: Intercept | M30: 0.0033982861 | N30: 0.0034609422 | O30: 0.98189626 | P30: 0.3284972 | Q30: -0.0034672921 | R30: 0.010263864 | S30: -0.0034672921 | T30: 0.010263864
B31: 45340 | C31: 8436.95 | D31: =C31/C30-1 -> 0.013441361 | F31: 22212.7 | G31: =F31/F30-1 -> 0.0078037449 | L31: X Variable 1 | M31: 1.1030738 | N31: 0.19831417 | O31: 5.5622541 | P31: 2.1890016e-07 | Q31: 0.70967185 | R31: 1.4964758 | S31: 0.70967185 | T31: 1.4964758
B32: 45347 | C32: 8040.05 | D32: =C32/C31-1 -> -0.047043067 | F32: 22338.75 | G32: =F32/F31-1 -> 0.0056746816
B33: 45354 | C33: 8879.05 | D33: =C33/C32-1 -> 0.10435258 | F33: 22493.55 | G33: =F33/F32-1 -> 0.0069296626
B34: 45361 | C34: 8350.7 | D34: =C34/C33-1 -> -0.05950524 | F34: 22023.35 | G34: =F34/F33-1 -> -0.02090377
B35: 45368 | C35: 8945.25 | D35: =C35/C34-1 -> 0.071197624 | F35: 22096.75 | G35: =F35/F34-1 -> 0.0033328263
B36: 45375 | C36: 9148.15 | D36: =C36/C35-1 -> 0.022682429 | F36: 22326.9 | G36: =F36/F35-1 -> 0.010415559
B37: 45382 | C37: 9009.5 | D37: =C37/C36-1 -> -0.01515607 | F37: 22513.7 | G37: =F37/F36-1 -> 0.0083665892
B38: 45389 | C38: 9064.85 | D38: =C38/C37-1 -> 0.0061435152 | F38: 22519.4 | G38: =F38/F37-1 -> 0.00025317918
B39: 45396 | C39: 8804.5 | D39: =C39/C38-1 -> -0.028720828 | F39: 22147 | G39: =F39/F38-1 -> -0.016536853
B40: 45403 | C40: 8974.3 | D40: =C40/C39-1 -> 0.019285593 | F40: 22419.95 | G40: =F40/F39-1 -> 0.012324468
B41: 45410 | C41: 9105.6 | D41: =C41/C40-1 -> 0.014630668 | F41: 22475.85 | G41: =F41/F40-1 -> 0.0024933151
B42: 45417 | C42: 8981.8 | D42: =C42/C41-1 -> -0.013596029 | F42: 22055.2 | G42: =F42/F41-1 -> -0.018715644
B43: 45424 | C43: 8780.7 | D43: =C43/C42-1 -> -0.022389721 | F43: 22466.1 | G43: =F43/F42-1 -> 0.018630527
... B115: 45928 | C115: 8679.5 | D115: =C115/C114-1 -> -0.0025856125 | F115: 24894.25 | G115: =F115/F114-1 -> 0.0097162002

Sheet Eicher Motors
B7: Regression Beta - 2 Years Weekly
B9: Eicher Motors Weekly Return | F9: NIFTY Returns | I9: Beta Drifting | L9: Beta 1 | M9: =SLOPE(D13:D117,G13:G117) -> 1.0732584
L10: Beta 2 | M10: =_xlfn.COVARIANCE.S(D13:D117,G13:G117)/_xlfn.VAR.S(G13:G117) -> 1.0732584
B11: Date | C11: Closing Price | D11: Return | F11: Closing Price | G11: Return | I11: Levered Raw Beta | J11: =M12 -> 1.0732584
B12: 45207 | C12: 3476.4 | F12: 19751.05 | I12: Beta Weight | J12: 0.75 | L12: Beta 3 | M12: =M31 -> 1.0732584
B13: 45214 | C13: 3480.9 | D13: =C13/C12-1 -> 0.0012944425 | F13: 19542.65 | G13: =F13/F12-1 -> -0.010551338
B14: 45221 | C14: 3394.85 | D14: =C14/C13-1 -> -0.024720618 | F14: 19047.25 | G14: =F14/F13-1 -> -0.025349684 | I14: Mean Beta | J14: 1 | L14: SUMMARY OUTPUT
B15: 45228 | C15: 3428 | D15: =C15/C14-1 -> 0.0097647908 | F15: 19230.6 | G15: =F15/F14-1 -> 0.0096260615 | I15: Mean Beta Weight | J15: 0.25
B16: 45235 | C16: 3540.75 | D16: =C16/C15-1 -> 0.032890898 | F16: 19425.35 | G16: =F16/F15-1 -> 0.010127089 | L16: Regression Statistics
B17: 45242 | C17: 3865.3 | D17: =C17/C16-1 -> 0.091661371 | F17: 19731.8 | G17: =F17/F16-1 -> 0.015775778 | I17: Adjusted Beta | J17: =(J11*J12)+(J14*J15) -> 1.0549438 | L17: Multiple R | M17: 0.52691574
B18: 45249 | C18: 3849.05 | D18: =C18/C17-1 -> -0.0042040721 | F18: 19794.7 | G18: =F18/F17-1 -> 0.0031877477 | L18: R Square | M18: 0.2776402
B19: 45256 | C19: 3891.2 | D19: =C19/C18-1 -> 0.010950754 | F19: 20267.9 | G19: =F19/F18-1 -> 0.023905389 | L19: Adjusted R Square | M19: 0.27048812
B20: 45263 | C20: 4055 | D20: =C20/C19-1 -> 0.042094984 | F20: 20969.4 | G20: =F20/F19-1 -> 0.034611381 | L20: Standard Error | M20: 0.030220109
B21: 45270 | C21: 4059.9 | D21: =C21/C20-1 -> 0.0012083847 | F21: 21456.65 | G21: =F21/F20-1 -> 0.023236239 | L21: Observations | M21: 103
B22: 45277 | C22: 4006.05 | D22: =C22/C21-1 -> -0.013263873 | F22: 21349.4 | G22: =F22/F21-1 -> -0.0049984504
B23: 45284 | C23: 4143.5 | D23: =C23/C22-1 -> 0.034310605 | F23: 21731.4 | G23: =F23/F22-1 -> 0.017892775 | L23: ANOVA
B24: 45291 | C24: 3877.05 | D24: =C24/C23-1 -> -0.064305539 | F24: 21710.8 | G24: =F24/F23-1 -> -0.00094793709 | M24: df | N24: SS | O24: MS | P24: F | Q24: Significance F
B25: 45298 | C25: 3870.85 | D25: =C25/C24-1 -> -0.001599154 | F25: 21894.55 | G25: =F25/F24-1 -> 0.0084635297 | L25: Regression | M25: 1 | N25: 0.035452119 | O25: 0.035452119 | P25: 38.819519 | Q25: 1.0805771e-08
B26: 45305 | C26: 3699.45 | D26: =C26/C25-1 -> -0.04427968 | F26: 21622.4 | G26: =F26/F25-1 -> -0.012430034 | L26: Residual | M26: 101 | N26: 0.092238755 | O26: 0.000913255
B27: 45312 | C27: 3616.45 | D27: =C27/C26-1 -> -0.022435767 | F27: 21352.6 | G27: =F27/F26-1 -> -0.012477801 | L27: Total | M27: 102 | N27: 0.12769087
B28: 45319 | C28: 3825.55 | D28: =C28/C27-1 -> 0.057819132 | F28: 21853.8 | G28: =F28/F27-1 -> 0.023472551
B29: 45326 | C29: 3840.95 | D29: =C29/C28-1 -> 0.004025565 | F29: 21782.5 | G29: =F29/F28-1 -> -0.0032625905 | M29: Coefficients | N29: Standard Error | O29: t Stat | P29: P-value | Q29: Lower 95% | R29: Upper 95% | S29: Lower 95.0% | T29: Upper 95.0%
B30: 45333 | C30: 3928.65 | D30: =C30/C29-1 -> 0.022832893 | F30: 22040.7 | G30: =F30/F29-1 -> 0.011853552 | L30: Intercept | M30: 0.0047812986 | N30: 0.0030062134 | O30: 1.5904721 | P30: 0.11485377 | Q30: -0.0011822201 | R30: 0.010744817 | S30: -0.0011822201 | T30: 0.010744817
B31: 45340 | C31: 3927.05 | D31: =C31/C30-1 -> -0.00040726458 | F31: 22212.7 | G31: =F31/F30-1 -> 0.0078037449 | L31: X Variable 1 | M31: 1.0732584 | N31: 0.17225793 | O31: 6.2305312 | P31: 1.0805771e-08 | Q31: 0.731545 | R31: 1.4149718 | S31: 0.731545 | T31: 1.4149718
B32: 45347 | C32: 3843.55 | D32: =C32/C31-1 -> -0.02126278 | F32: 22338.75 | G32: =F32/F31-1 -> 0.0056746816
B33: 45354 | C33: 3785.25 | D33: =C33/C32-1 -> -0.015168269 | F33: 22493.55 | G33: =F33/F32-1 -> 0.0069296626
B34: 45361 | C34: 3745.65 | D34: =C34/C33-1 -> -0.01046166 | F34: 22023.35 | G34: =F34/F33-1 -> -0.02090377
B35: 45368 | C35: 3988.4 | D35: =C35/C34-1 -> 0.064808511 | F35: 22096.75 | G35: =F35/F34-1 -> 0.0033328263
B36: 45375 | C36: 4019.3 | D36: =C36/C35-1 -> 0.0077474677 | F36: 22326.9 | G36: =F36/F35-1 -> 0.010415559
B37: 45382 | C37: 4031.25 | D37: =C37/C36-1 -> 0.0029731545 | F37: 22513.7 | G37: =F37/F36-1 -> 0.0083665892
B38: 45389 | C38: 4302.25 | D38: =C38/C37-1 -> 0.067224806 | F38: 22519.4 | G38: =F38/F37-1 -> 0.00025317918
B39: 45396 | C39: 4344.15 | D39: =C39/C38-1 -> 0.00973909 | F39: 22147 | G39: =F39/F38-1 -> -0.016536853
B40: 45403 | C40: 4601 | D40: =C40/C39-1 -> 0.059125491 | F40: 22419.95 | G40: =F40/F39-1 -> 0.012324468
B41: 45410 | C41: 4599.25 | D41: =C41/C40-1 -> -0.0003803521 | F41: 22475.85 | G41: =F41/F40-1 -> 0.0024933151
B42: 45417 | C42: 4657.85 | D42: =C42/C41-1 -> 0.012741208 | F42: 22055.2 | G42: =F42/F41-1 -> -0.018715644
B43: 45424 | C43: 4693.9 | D43: =C43/C42-1 -> 0.0077396224 | F43: 22466.1 | G43: =F43/F42-1 -> 0.018630527
... B115: 45928 | C115: 6941 | D115: =C115/C114-1 -> -0.015041862 | F115: 24894.25 | G115: =F115/F114-1 -> 0.0097162002
